Workbook

Sheet Protfolio
F2: =B4 | G2: Beginning Balance | I2: 1037509.3 | J2: YTD | K2: =B4 | L2: $ Gain/Loss w/o Dis | N2: =IF(I3>0,(IT263+IV263)-I2,0)
F3: =B4 | G3: Ending Balance | I3: =IT263 | J3: =IT265 | K3: =B4 | L3: $ Gain/Loss w Dist. | N3: =IF(I3>0,IT263/I2,0) | O3: =300*43.8 | FD3: Spinoff (GEV) on 4/2/24
B4: ='Investment Analysis'!B3 | C4: Portfolio Data | F4: =B4 | G4: YTD Gain/Loss | I4: =IF(IT263>0,I3-I2,0) | J4: =J3+J5-I2 | K4: Current | L4: $ Gain/Loss w Dist. | N4: =J3-I2 | P4: Current Investment Position Results | V4: =B4 | W4: Beginning Value
F5: =B4 | G5: Distrabution Taken | I5: =IV263 | J5: =IU265 | K5: =B4 | L5: % Gain/Loss w/o Dis. | N5: =IF(J3>0,((J3+J5)-I2)/I2,0) | P5: 1 | Q5: ='Investment Analysis'!Y10 | R5: =IF(P264>0,P264/$IT$7,0) | S5: =P5+1 | T5: =22468+'Investment Analysis'!AH4 | U5: =IF(S264>0,S264/$IT$7,0) | V5: =S5+1 | W5: =17715+'Investment Analysis'!AO4 | X5: =IF(V264>0,V264/$IT$7,0) | Y5: =V5+1 | Z5: =9976+'Investment Analysis'!GM4 | AA5: =IF(Y264>0,Y264/$IT$7,0) | AB5: =Y5+1 | AC5: =2663+'Investment Analysis'!AV4 | AD5: =IF(AB264>0,AB264/$IT$7,0) | AE5: =AB5+1 | AF5: =22429+'Investment Analysis'!BC4 | AG5: =IF(AE264>0,AE264/$IT$7,0) | AH5: =AE5+1 | AI5: ='Investment Analysis'!BJ4 | AJ5: =IF(AH264>0,AH264/$IT$7,0) | AK5: =AH5+1 | AL5: =18847+'Investment Analysis'!BQ4 | AM5: =IF(AK264>0,AK264/$IT$7,0) | AN5: =AK5+1 | AO5: =14640+'Investment Analysis'!BX4 | AP5: =IF(AN264>0,AN264/$IT$7,0) | AQ5: =AN5+1 | AR5: ='Investment Analysis'!GT4 | AS5: =IF(AQ264>0,AQ264/$IT$7,0) | AT5: =AQ5+1 | AU5: =27227+'Investment Analysis'!CL4 | AV5: =IF(AT264>0,AT264/$IT$7,0) | AW5: =AT5+1 | AX5: =19243+'Investment Analysis'!CS4 | AY5: =IF(AW264>0,AW264/$IT$7,0) | AZ5: =AW5+1 | BA5: =16827+'Investment Analysis'!CZ4 | BB5: =IF(AZ264>0,AZ264/$IT$7,0) | BC5: =AZ5+1 | BD5: =10041+'Investment Analysis'!DG4 | BE5: =IF(BC264>0,BC264/$IT$7,0) | BF5: =BC5+1 | BG5: =4195+'Investment Analysis'!DN4 | BH5: =IF(BF264>0,BF264/$IT$7,0) | BI5: =BF5+1 | BJ5: =2554+'Investment Analysis'!EB4 | BK5: =IF(BI264>0,BI264/$IT$7,0) | BL5: =BI5+1 | BM5: =4401+'Investment Analysis'!EI4 | BN5: =IF(BL264>0,BL264/$IT$7,0) | BO5: =BL5+1 | BP5: ='Investment Analysis'!DU4 | BQ5: =IF(BO264>0,BO264/$IT$7,0) | BR5: =BO5+1 | BS5: =5659+'Investment Analysis'!EP4 | BT5: =IF(BR264>0,BR264/$IT$7,0) | BU5: =BR5+1 | BV5: =14858+'Investment Analysis'!EW4 | BW5: =IF(BU264>0,BU264/$IT$7,0) | BX5: =BU5+1 | BY5: ='Investment Analysis'!FD4 | BZ5: =IF(BX264>0,BX264/$IT$7,0) | CA5: =BX5+1 | CB5: =3200+'Investment Analysis'!FK4 | CC5: =IF(CA264>0,CA264/$IT$7,0) | CD5: =CA5+1 | CE5: =19032+'Investment Analysis'!FR4 | CF5: =IF(CD264>0,CD264/$IT$7,0) | CG5: =CD5+1 | CH5: =5077+'Investment Analysis'!FY4 | CI5: =IF(CG264>0,CG264/$IT$7,0) | CJ5: =CG5+1 | CK5: ='Investment Analysis'!GF4 | CL5: =IF(CJ264>0,CJ264/$IT$7,0) | CM5: =CJ5+1 | CN5: =4950+'Investment Analysis'!HA4 | CO5: =IF(CM264>0,CM264/$IT$7,0) | CP5: =CM5+1 | CQ5: ='Investment Analysis'!HE5 | CR5: =IF(CP264>0,CP264/$IT$7,0) | CS5: =CP5+1 | CT5: ='Investment Analysis'!HL5 | CU5: =IF(CS264>0,CS264/$IT$7,0) | CV5: =CS5+1 | CW5: ='Investment Analysis'!HZ5 | CX5: =IF(CV264>0,CV264/$IT$7,0) | CY5: =CV5+1 | CZ5: ='Investment Analysis'!IG5 | DA5: =IF(CY264>0,CY264/$IT$7,0) | DB5: =CY5+1 | DC5: ='Investment Analysis'!IN5 | DD5: =IF(DB264>0,DB264/$IT$7,0) | DE5: =DB5+1 | DF5: ='Investment Analysis'!IU5 | DG5: =IF(DE264>0,DE264/$IT$7,0) | DH5: =DE5+1 | DI5: ='Investment Analysis'!JB5 | DJ5: =IF(DH264>0,DH264/$IT$7,0) | DK5: =DH5+1 | DL5: ='Investment Analysis'!JI5 | DM5: =IF(DK264>0,DK264/$IT$7,0) | DN5: =DK5+1 | DO5: ='Investment Analysis'!HS5 | DP5: =IF(DN264>0,DN264/$IT$7,0) | DQ5: =DN5+1 | DR5: ='Investment Analysis'!JP5 | DS5: =IF(DQ264>0,DQ264/$IT$7,0) | DT5: =DQ5+1 | DU5: ='Investment Analysis'!JW5 | DV5: =IF(DT264>0,DT264/$IT$7,0) | DW5: =DT5+1 | DX5: ='Investment Analysis'!KD5 | DY5: =IF(DW264>0,DW264/$IT$7,0) | DZ5: =DW5+1 | EA5: ='Investment Analysis'!KK5 | EB5: =IF(DZ264>0,DZ264/$IT$7,0) | EC5: =DZ5+1 | ED5: ='Investment Analysis'!KR5 | EE5: =IF(EC264>0,EC264/$IT$7,0) | EF5: =EC5+1 | EG5: ='Investment Analysis'!LF5 | EH5: =IF(EF264>0,EF264/$IT$7,0) | EI5: =EF5+1 | EJ5: ='Investment Analysis'!LM5 | EK5: =IF(EI264>0,EI264/$IT$7,0) | EL5: =EI5+1 | EM5: ='Investment Analysis'!LT5 | EN5: =IF(EL264>0,EL264/$IT$7,0) | EO5: =EL5+1 | EP5: ='Investment Analysis'!MA5 | EQ5: =IF(EO264>0,EO264/$IT$7,0) | ER5: =EO5+1 | ES5: ='Investment Analysis'!KY5 | ET5: =IF(ER264>0,ER264/$IT$7,0) | EU5: =ER5+1 | EV5: ='Investment Analysis'!MH5 | EW5: =IF(EU264>0,EU264/$IT$7,0) | EX5: =EU5+1 | EY5: ='Investment Analysis'!MO5 | EZ5: =IF(EX264>0,EX264/$IT$7,0) | FA5: =EX5+1 | FB5: ='Investment Analysis'!MV5 | FC5: =IF(FA264>0,FA264/$IT$7,0) | FD5: =FA5+1 | FE5: ='Investment Analysis'!NC5 | FF5: =IF(FD264>0,FD264/$IT$7,0) | FG5: =FD5+1 | FH5: ='Investment Analysis'!NJ5 | FI5: =IF(FG264>0,FG264/$IT$7,0) | FJ5: =FG5+1 | FK5: ='Investment Analysis'!NQ5 | FL5: =IF(FJ264>0,FJ264/$IT$7,0) | FM5: =FJ5+1 | FN5: ='Investment Analysis'!NX5 | FO5: =IF(FM264>0,FM264/$IT$7,0) | FP5: =FM5+1 | FQ5: ='Investment Analysis'!OE5 | FR5: =IF(FP264>0,FP264/$IT$7,0) | FS5: =FP5+1 | FT5: ='Investment Analysis'!OL5 | FU5: =IF(FS264>0,FS264/$IT$7,0) | FV5: =FS5+1 | FW5: ='Investment Analysis'!OS5 | FX5: =IF(FV264>0,FV264/$IT$7,0) | FY5: =FV5+1 | FZ5: ='Investment Analysis'!OZ5 | GA5: =IF(FY264>0,FY264/$IT$7,0) | GB5: =FY5+1 | GC5: ='Investment Analysis'!PG5 | GD5: =IF(GB264>0,GB264/$IT$7,0) | GE5: =GB5+1 | GF5: ='Investment Analysis'!PU5 | GG5: =IF(GE264>0,GE264/$IT$7,0) | GH5: =GE5+1 | GI5: ='Investment Analysis'!QB5 | GJ5: =IF(GH264>0,GH264/$IT$7,0) | GK5: =GH5+1 | GL5: ='Investment Analysis'!QI5 | GM5: =IF(GK264>0,GK264/$IT$7,0) | GN5: =GK5+1 | GO5: ='Investment Analysis'!QP5 | GP5: =IF(GN264>0,GN264/$IT$7,0) | GQ5: =GN5+1 | GR5: ='Investment Analysis'!QW5 | GS5: =IF(GQ264>0,GQ264/$IT$7,0) | GT5: =GQ5+1 | GU5: ='Investment Analysis'!RD5 | GV5: =IF(GT264>0,GT264/$IT$7,0) | GW5: =GT5+1 | GX5: ='Investment Analysis'!RK5 | GY5: =IF(GW264>0,GW264/$IT$7,0) | GZ5: =GW5+1 | HA5: ='Investment Analysis'!RR5 | HB5: =IF(GZ264>0,GZ264/$IT$7,0) | HC5: =GZ5+1 | HD5: ='Investment Analysis'!RY5 | HE5: =IF(HC264>0,HC264/$IT$7,0) | HF5: =HC5+1 | HG5: ='Investment Analysis'!SF5 | HH5: =IF(HF264>0,HF264/$IT$7,0) | HI5: =HF5+1 | HJ5: ='Investment Analysis'!SM5 | HK5: =IF(HI264>0,HI264/$IT$7,0) | HL5: =HI5+1 | HM5: ='Investment Analysis'!ST5 | HN5: =IF(HL264>0,HL264/$IT$7,0) | HO5: =HL5+1 | HP5: ='Investment Analysis'!TA5 | HQ5: =IF(HO264>0,HO264/$IT$7,0) | HR5: =HO5+1 | HS5: ='Investment Analysis'!TH5 | HT5: =IF(HR264>0,HR264/$IT$7,0) | HU5: =HR5+1 | HV5: ='Investment Analysis'!TO5 | HW5: =IF(HU264>0,HU264/$IT$7,0) | HX5: =HU5+1 | HY5: ='Investment Analysis'!TV5 | HZ5: =IF(HX264>0,HX264/$IT$7,0) | IA5: =HX5+1 | IB5: ='Investment Analysis'!UC5 | IC5: =IF(IA264>0,IA264/$IT$7,0) | ID5: =IA5+1 | IE5: ='Investment Analysis'!UJ5 | IF5: =IF(ID264>0,ID264/$IT$7,0) | IG5: =ID5+1 | IH5: ='Investment Analysis'!UJ5 | II5: =IF(IG264>0,IG264/$IT$7,0) | IJ5: =IG5+1 | IK5: ='Investment Analysis'!UQ3 | IL5: =IF(IJ264>0,IJ264/$IT$7,0) | IM5: =IJ5+1 | IN5: ='Investment Analysis'!UX3 | IO5: =IF(IM264>0,IM264/$IT$7,0)
F6: =B4 | G6: End Bal. w/o Dist. | I6: =IT265+IV265 | J6: =J3+J5 | K6: =B4 | L6: % Gain/Loss w Dist. | N6: =IF(I3>0,((I3-I2)/I2),0) | P6: ='Investment Analysis'!Y6 | S6: ='Investment Analysis'!AC6 | V6: ='Investment Analysis'!AJ7 | Y6: Health Care - Biotech | AB6: ='Investment Analysis'!AQ6 | AE6: ='Investment Analysis'!AX6 | AH6: ='Investment Analysis'!BE6 | AK6: ='Investment Analysis'!BL6 | AN6: ='Investment Analysis'!BS6 | AQ6: ='Investment Analysis'!GO4 | AT6: ='Investment Analysis'!CG6 | AW6: ='Investment Analysis'!CN6 | AZ6: ='Investment Analysis'!CU6 | BC6: ='Investment Analysis'!DB6 | BF6: ='Investment Analysis'!DI6 | BI6: ='Investment Analysis'!DW6 | BL6: ='Investment Analysis'!ED6 | BO6: ='Investment Analysis'!DP6 | BR6: ='Investment Analysis'!EK6 | BU6: ='Investment Analysis'!ER6 | BX6: ='Investment Analysis'!EY6 | CA6: ='Investment Analysis'!FF6 | CD6: ='Investment Analysis'!FM6 | CG6: ='Investment Analysis'!FT6 | CJ6: ='Investment Analysis'!GA6 | CM6: ='Investment Analysis'!GV6 | CP6: ='Investment Analysis'!HD6 | CS6: ='Investment Analysis'!HK6 | CV6: ='Investment Analysis'!HY6 | CY6: ='Investment Analysis'!IF6 | DB6: ='Investment Analysis'!IM6 | DE6: ='Investment Analysis'!IT6 | DH6: ='Investment Analysis'!JA6 | DK6: ='Investment Analysis'!JH6 | DN6: ='Investment Analysis'!HR6 | DQ6: ='Investment Analysis'!JO6 | DT6: ='Investment Analysis'!JV6 | DW6: ='Investment Analysis'!KC6 | DZ6: ='Investment Analysis'!KJ6 | EC6: ='Investment Analysis'!KQ6 | EF6: ='Investment Analysis'!LE6 | EI6: ='Investment Analysis'!LL6 | EL6: ='Investment Analysis'!LS6 | EO6: ='Investment Analysis'!LZ6 | ER6: ='Investment Analysis'!KX6 | EU6: ='Investment Analysis'!MG6 | EX6: ='Investment Analysis'!MN6 | FA6: ='Investment Analysis'!MU6 | FD6: ='Investment Analysis'!NB6 | FG6: ='Investment Analysis'!NI6 | FJ6: ='Investment Analysis'!NP6 | FM6: ='Investment Analysis'!NW6 | FP6: ='Investment Analysis'!OD6 | FS6: ='Investment Analysis'!OK6 | FV6: ='Investment Analysis'!OR6 | FY6: ='Investment Analysis'!OY6 | GB6: ='Investment Analysis'!PF6 | GE6: ='Investment Analysis'!PT6 | GH6: ='Investment Analysis'!QA6 | GK6: ='Investment Analysis'!QH6 | GN6: ='Investment Analysis'!QO6 | GQ6: ='Investment Analysis'!QV6 | GT6: ='Investment Analysis'!RC6 | GW6: ='Investment Analysis'!RJ6 | GZ6: ='Investment Analysis'!RX6 | HC6: ='Investment Analysis'!RX6 | HF6: ='Investment Analysis'!SE6 | HI6: ='Investment Analysis'!SL6 | HL6: ='Investment Analysis'!SS6 | HO6: ='Investment Analysis'!SZ6 | HR6: ='Investment Analysis'!TG6 | HU6: ='Investment Analysis'!TN6 | HX6: ='Investment Analysis'!TU6 | IA6: ='Investment Analysis'!UB6 | ID6: ='Investment Analysis'!UI6 | IG6: ='Investment Analysis'!UP6 | IJ6: ='Investment Analysis'!UW6 | IM6: ='Investment Analysis'!VD6
K7: Current | L7: % Gain/Loss w Dist. | N7: =IF(J3>0,(J3-I2)/I2,0) | P7: Percent of Portfolio | R7: ='Investment Analysis'!AA5 | S7: Percent of Portfolio | U7: ='Investment Analysis'!AH5 | V7: Percent of Portfolio | X7: ='Investment Analysis'!AO5 | Y7: Percent of Portfolio | AA7: ='Investment Analysis'!GM5 | AB7: Percent of Portfolio | AD7: ='Investment Analysis'!AV5 | AE7: Percent of Portfolio | AG7: ='Investment Analysis'!BC5 | AH7: Percent of Portfolio | AJ7: ='Investment Analysis'!BF5 | AK7: Percent of Portfolio | AM7: ='Investment Analysis'!BQ5 | AN7: Percent of Portfolio | AP7: ='Investment Analysis'!BX5 | AQ7: Percent of Portfolio | AS7: =AS5 | AT7: Percent of Portfolio | AV7: ='Investment Analysis'!CL5 | AW7: Percent of Portfolio | AY7: ='Investment Analysis'!CZ5 | AZ7: Percent of Portfolio | BB7: ='Investment Analysis'!DG5 | BC7: Percent of Portfolio | BE7: ='Investment Analysis'!DJ5 | BF7: Percent of Portfolio | BH7: ='Investment Analysis'!DN5 | BI7: Percent of Portfolio | BK7: ='Investment Analysis'!EB5 | BL7: Percent of Portfolio | BN7: ='Investment Analysis'!EI5 | BO7: Percent of Portfolio | BQ7: =BQ5 | BR7: Percent of Portfolio | BT7: ='Investment Analysis'!EP5 | BU7: Percent of Portfolio | BW7: ='Investment Analysis'!EW5 | BX7: Percent of Portfolio | BZ7: ='Investment Analysis'!FD5 | CA7: Percent of Portfolio | CC7: =CC5 | CD7: Percent of Portfolio | CF7: ='Investment Analysis'!FR5 | CG7: Percent of Portfolio | CI7: ='Investment Analysis'!FY5 | CJ7: Percent of Portfolio | CL7: ='Investment Analysis'!GF5 | CM7: Percent of Portfolio | CO7: ='Investment Analysis'!HA5 | CP7: Shares | CQ7: ='Investment Analysis'!HG5 | CR7: =CR5 | CS7: Shares | CT7: ='Investment Analysis'!HN5 | CU7: =CU5 | CV7: Shares | CW7: ='Investment Analysis'!IB5 | CX7: =CX5 | CY7: Shares | CZ7: ='Investment Analysis'!II5 | DA7: =DA5 | DB7: Shares | DC7: ='Investment Analysis'!IP5 | DD7: =DD5 | DE7: Shares | DF7: ='Investment Analysis'!IW5 | DG7: =DG5 | DH7: Shares | DI7: ='Investment Analysis'!JD5 | DJ7: =DJ5 | DK7: Shares | DL7: ='Investment Analysis'!JK5 | DM7: =DM5 | DN7: Shares | DO7: ='Investment Analysis'!HU5 | DP7: =DP5 | DQ7: Shares | DR7: ='Investment Analysis'!JR5 | DS7: =DS5 | DT7: Shares | DU7: ='Investment Analysis'!JY5 | DV7: =DV5 | DW7: Shares | DX7: ='Investment Analysis'!KF5 | DY7: =DY5 | DZ7: Shares | EA7: ='Investment Analysis'!KM5 | EB7: =EB5 | EC7: Shares | ED7: ='Investment Analysis'!KT5 | EE7: =EE5 | EF7: Shares | EG7: ='Investment Analysis'!LH5 | EH7: =EH5 | EI7: Shares | EJ7: ='Investment Analysis'!LO5 | EK7: =EK5 | EL7: Shares | EM7: ='Investment Analysis'!LV5 | EN7: =EN5 | EO7: Shares | EP7: ='Investment Analysis'!MC5 | EQ7: =EQ5 | ER7: Shares | ES7: ='Investment Analysis'!LA5 | ET7: =ET5 | EU7: Shares | EV7: ='Investment Analysis'!MJ5 | EW7: =EW5 | EX7: Shares | EY7: ='Investment Analysis'!MQ5 | EZ7: =EZ5 | FA7: Shares | FB7: ='Investment Analysis'!MX5 | FC7: =FC5 | FD7: Shares | FE7: ='Investment Analysis'!NE5 | FF7: =FF5 | FG7: Shares | FH7: ='Investment Analysis'!NL5 | FI7: =FI5 | FJ7: Shares | FK7: ='Investment Analysis'!NS5 | FL7: =FL5 | FM7: Shares | FN7: ='Investment Analysis'!NZ5 | FO7: =FO5 | FP7: Shares | FQ7: ='Investment Analysis'!NY5 | FR7: =FR5 | FS7: Shares | FT7: ='Investment Analysis'!ON5 | FU7: =FU5 | FV7: Shares | FW7: ='Investment Analysis'!OU5 | FX7: =FX5 | FY7: Shares | FZ7: ='Investment Analysis'!PB5 | GA7: =GA5 | GB7: Shares | GC7: ='Investment Analysis'!PI5 | GD7: =GD5 | GE7: Shares | GF7: ='Investment Analysis'!PW5 | GG7: =GG5 | GH7: Shares | GI7: ='Investment Analysis'!QD5 | GJ7: =GJ5 | GK7: Shares | GL7: ='Investment Analysis'!QK5 | GM7: =GM5 | GN7: Shares | GO7: ='Investment Analysis'!QR5 | GP7: =GP5 | GQ7: Shares | GR7: ='Investment Analysis'!QY5 | GS7: =GS5 | GT7: Shares | GU7: ='Investment Analysis'!RF5 | GV7: =GV5 | GW7: Shares | GX7: ='Investment Analysis'!RM5 | GY7: =GY5 | GZ7: Shares | HA7: ='Investment Analysis'!RT5 | HB7: =HB5 | HC7: Shares | HD7: ='Investment Analysis'!SA5 | HE7: =HE5 | HF7: Shares | HG7: ='Investment Analysis'!SH5 | HH7: =HH5 | HI7: Shares | HJ7: ='Investment Analysis'!SO5 | HK7: =HK5 | HL7: Shares | HM7: ='Investment Analysis'!SV5 | HN7: =HN5 | HO7: Shares | HP7: ='Investment Analysis'!TC5 | HQ7: =HQ5 | HR7: Shares | HS7: ='Investment Analysis'!TJ5 | HT7: =HT5 | HU7: Shares | HV7: ='Investment Analysis'!TQ5 | HW7: =HW5 | HX7: Shares | HY7: ='Investment Analysis'!TX5 | HZ7: =HZ5 | IA7: Shares | IB7: ='Investment Analysis'!UE5 | IC7: =IC5 | ID7: Shares | IE7: ='Investment Analysis'!UL5 | IF7: =IF5 | IG7: Shares | IH7: ='Investment Analysis'!US5 | II7: =II5 | IJ7: Shares | IK7: ='Investment Analysis'!UZ5 | IL7: =IL5 | IM7: Shares | IN7: ='Investment Analysis'!VG5 | IO7: =IO5 | IT7: =IT265
D8: Dow Jones | G8: S&P 500 | J8: Nasdaq | L8: Comp. | M8: Daily | N8: YTD | P8: ='Investment Analysis'!Y7 | S8: ='Investment Analysis'!AC7 | V8: ='Investment Analysis'!AJ7 | Y8: ='Investment Analysis'!GH7 | AB8: ='Investment Analysis'!AQ7 | AE8: ='Investment Analysis'!AX7 | AH8: ='Investment Analysis'!BE7 | AK8: ='Investment Analysis'!BL7 | AN8: ='Investment Analysis'!BS7 | AQ8: ='Investment Analysis'!GO7 | AT8: ='Investment Analysis'!CG7 | AW8: ='Investment Analysis'!CN7 | AZ8: ='Investment Analysis'!CU7 | BC8: ='Investment Analysis'!DB7 | BF8: ='Investment Analysis'!DI7 | BI8: ='Investment Analysis'!DW7 | BL8: ='Investment Analysis'!ED7 | BO8: ='Investment Analysis'!DP7 | BR8: ='Investment Analysis'!EK7 | BU8: ='Investment Analysis'!ER7 | BX8: ='Investment Analysis'!EY7 | CA8: ='Investment Analysis'!FF7 | CD8: ='Investment Analysis'!FM7 | CG8: ='Investment Analysis'!FT7 | CJ8: ='Investment Analysis'!GA7 | CM8: ='Investment Analysis'!GV7 | CP8: ='Investment Analysis'!HD7 | CS8: ='Investment Analysis'!HK7 | CV8: ='Investment Analysis'!HY7 | CY8: ='Investment Analysis'!IF7 | DB8: ='Investment Analysis'!IM7 | DE8: ='Investment Analysis'!IT7 | DH8: ='Investment Analysis'!JA7 | DK8: ='Investment Analysis'!JH7 | DN8: ='Investment Analysis'!HR7 | DQ8: ='Investment Analysis'!JO7 | DT8: ='Investment Analysis'!JV7 | DW8: ='Investment Analysis'!KC7 | DZ8: ='Investment Analysis'!KJ7 | EC8: ='Investment Analysis'!KQ7 | EF8: ='Investment Analysis'!LE7 | EI8: ='Investment Analysis'!LL7 | EL8: ='Investment Analysis'!LS7 | EO8: ='Investment Analysis'!LZ7 | ER8: ='Investment Analysis'!KX7 | EU8: ='Investment Analysis'!MG7 | EX8: ='Investment Analysis'!MN7 | FA8: ='Investment Analysis'!MU7 | FD8: ='Investment Analysis'!NB7 | FG8: ='Investment Analysis'!NI7 | FJ8: ='Investment Analysis'!NP7 | FM8: ='Investment Analysis'!NW7 | FP8: ='Investment Analysis'!OD7 | FS8: ='Investment Analysis'!OK7 | FV8: ='Investment Analysis'!OR7 | FY8: ='Investment Analysis'!OY7 | GB8: ='Investment Analysis'!PF7 | GE8: ='Investment Analysis'!PT7 | GH8: ='Investment Analysis'!QA7 | GK8: ='Investment Analysis'!QH7 | GN8: ='Investment Analysis'!QO7 | GQ8: ='Investment Analysis'!QV7 | GT8: ='Investment Analysis'!RC7 | GW8: ='Investment Analysis'!RJ7 | GZ8: ='Investment Analysis'!RQ7 | HC8: ='Investment Analysis'!RX7 | HF8: ='Investment Analysis'!SE7 | HI8: ='Investment Analysis'!SL7 | HL8: ='Investment Analysis'!SS7 | HO8: ='Investment Analysis'!SZ7 | HR8: ='Investment Analysis'!TG7 | HU8: ='Investment Analysis'!TN7 | HX8: ='Investment Analysis'!TU7 | IA8: ='Investment Analysis'!UB7 | ID8: ='Investment Analysis'!UI7 | IG8: ='Investment Analysis'!UP7 | IJ8: ='Investment Analysis'!UW7 | IM8: ='Investment Analysis'!VD7 | IS8: =I2 | IT8: ='Investment Analysis'!VM6
D9: Value | E9: % | G9: Value | H9: % | J9: Value | K9: % | L9: Index | M9: Index | N9: Market | P9: ='Investment Analysis'!Y8 | Q9: % Change | R9: % Change | S9: ='Investment Analysis'!AC8 | T9: % Change | U9: % Change | V9: ='Investment Analysis'!AJ8 | W9: % Change | X9: % Change | Y9: FBIOX | Z9: % Change | AA9: % Change | AB9: ='Investment Analysis'!AQ8 | AC9: % Change | AD9: % Change | AE9: ='Investment Analysis'!AX8 | AF9: % Change | AG9: % Change | AH9: ='Investment Analysis'!BE8 | AI9: % Change | AJ9: % Change | AK9: ='Investment Analysis'!BL8 | AL9: % Change | AM9: % Change | AN9: ='Investment Analysis'!BS8 | AO9: % Change | AP9: % Change | AQ9: ='Investment Analysis'!GO8 | AR9: % Change | AS9: % Change | AT9: ='Investment Analysis'!CG8 | AU9: % Change | AV9: % Change | AW9: ='Investment Analysis'!CN8 | AX9: % Change | AY9: % Change | AZ9: ='Investment Analysis'!CU8 | BA9: % Change | BB9: % Change | BC9: ='Investment Analysis'!DB8 | BD9: % Change | BE9: % Change | BF9: ='Investment Analysis'!DI8 | BG9: % Change | BH9: % Change | BI9: ='Investment Analysis'!DW8 | BJ9: % Change | BK9: % Change | BL9: ='Investment Analysis'!ED8 | BM9: % Change | BN9: % Change | BO9: ='Investment Analysis'!DP8 | BP9: % Change | BQ9: % Change | BR9: ='Investment Analysis'!EK8 | BS9: % Change | BT9: % Change | BU9: ='Investment Analysis'!ER8 | BV9: % Change | BW9: % Change | BX9: ='Investment Analysis'!EY8 | BY9: % Change | BZ9: % Change | CA9: ='Investment Analysis'!FF8 | CB9: % Change | CC9: % Change | CD9: ='Investment Analysis'!FM8 | CE9: % Change | CF9: % Change | CG9: ='Investment Analysis'!FT8 | CH9: % Change | CI9: % Change | CJ9: ='Investment Analysis'!GA8 | CK9: % Change | CL9: % Change | CM9: ='Investment Analysis'!GV8 | CN9: % Change | CO9: % Change | CP9: ='Investment Analysis'!HD8 | CQ9: % Change | CR9: % Change | CS9: ='Investment Analysis'!HK8 | CT9: % Change | CU9: % Change | CV9: ='Investment Analysis'!HY8 | CW9: % Change | CX9: % Change | CY9: ='Investment Analysis'!IF8 | CZ9: % Change | DA9: % Change | DB9: ='Investment Analysis'!IM8 | DC9: % Change | DD9: % Change | DE9: ='Investment Analysis'!IT8 | DF9: % Change | DG9: % Change | DH9: ='Investment Analysis'!JA8 | DI9: % Change | DJ9: % Change | DK9: ='Investment Analysis'!JH8 | DL9: % Change | DM9: % Change | DN9: ='Investment Analysis'!HR8 | DO9: % Change | DP9: % Change | DQ9: ='Investment Analysis'!JO8 | DR9: % Change | DS9: % Change | DT9: ='Investment Analysis'!JV8 | DU9: % Change | DV9: % Change | DW9: ='Investment Analysis'!KC8 | DX9: % Change | DY9: % Change | DZ9: ='Investment Analysis'!KJ8 | EA9: % Change | EB9: % Change | EC9: ='Investment Analysis'!KQ8 | ED9: % Change | EE9: % Change | EF9: ='Investment Analysis'!LE8 | EG9: % Change | EH9: % Change | EI9: ='Investment Analysis'!LL8 | EJ9: % Change | EK9: % Change | EL9: ='Investment Analysis'!LS8 | EM9: % Change | EN9: % Change | EO9: ='Investment Analysis'!LZ8 | EP9: % Change | EQ9: % Change | ER9: ='Investment Analysis'!KX8 | ES9: % Change | ET9: % Change | EU9: ='Investment Analysis'!MG8 | EV9: % Change | EW9: % Change | EX9: ='Investment Analysis'!MN8 | EY9: % Change | EZ9: % Change | FA9: ='Investment Analysis'!MU8 | FB9: % Change | FC9: % Change | FD9: ='Investment Analysis'!NB8 | FE9: % Change | FF9: % Change | FG9: ='Investment Analysis'!NI8 | FH9: % Change | FI9: % Change | FJ9: ='Investment Analysis'!NP8 | FK9: % Change | FL9: % Change | FM9: ='Investment Analysis'!NW8 | FN9: % Change | FO9: % Change | FP9: ='Investment Analysis'!OD8 | FQ9: % Change | FR9: % Change | FS9: ='Investment Analysis'!OK8 | FT9: % Change | FU9: % Change | FV9: ='Investment Analysis'!OR8 | FW9: % Change | FX9: % Change | FY9: ='Investment Analysis'!OY8 | FZ9: % Change | GA9: % Change | GB9: ='Investment Analysis'!PF8 | GC9: % Change | GD9: % Change | GE9: ='Investment Analysis'!PT8 | GF9: % Change | GG9: % Change | GH9: ='Investment Analysis'!QA8 | GI9: % Change | GJ9: % Change | GK9: ='Investment Analysis'!QH8 | GL9: % Change | GM9: % Change | GN9: ='Investment Analysis'!QO8 | GO9: % Change | GP9: % Change | GQ9: ='Investment Analysis'!QV8 | GR9: % Change | GS9: % Change | GT9: ='Investment Analysis'!RC8 | GU9: % Change | GV9: % Change | GW9: ='Investment Analysis'!RJ8 | GX9: % Change | GY9: % Change | GZ9: ='Investment Analysis'!RQ8 | HA9: % Change | HB9: % Change | HC9: ='Investment Analysis'!RX8 | HD9: % Change | HE9: % Change | HF9: ='Investment Analysis'!SE8 | HG9: % Change | HH9: % Change | HI9: ='Investment Analysis'!SL8 | HJ9: % Change | HK9: % Change | HL9: ='Investment Analysis'!SS8 | HM9: % Change | HN9: % Change | HO9: ='Investment Analysis'!SZ8 | HP9: % Change | HQ9: % Change | HR9: ='Investment Analysis'!TG8 | HS9: % Change | HT9: % Change | HU9: ='Investment Analysis'!TN8 | HV9: % Change | HW9: % Change | HX9: VSLA | HY9: % Change | HZ9: % Change | IA9: ='Investment Analysis'!UB8:UB9 | IB9: % Change | IC9: % Change | ID9: ='Investment Analysis'!UI8:UI9 | IE9: % Change | IF9: % Change | IG9: ='Investment Analysis'!UP8:UP9 | IH9: % Change | II9: % Change | IJ9: =-'Investment Analysis'!UW8:UW9 | IK9: % Change | IL9: % Change | IM9: ='Investment Analysis'!VD8:VD9 | IN9: % Change | IO9: % Change | IS9: Daily | IT9: Portfolio | IU9: Dist. | IV9: Distribution | IW9: YTD % | IX9: YTD $ | IY9: % G/L | IZ9: $ G/L
A10: Date | B10: Day | C10: Value | D10: Gn/Ls | E10: Chang | F10: Value | G10: Gn/Ls | H10: Chang | I10: Value | J10: Gn/Ls | K10: Chang | L10: Avg | M10: Change | N10: Gain/Loss | Q10: YTD | R10: FromTrade | T10: YTD | U10: FromTrade | W10: YTD | X10: FromTrade | Z10: YTD | AA10: FromTrade | AC10: YTD | AD10: FromTrade | AF10: YTD | AG10: FromTrade | AI10: YTD | AJ10: FromTrade | AL10: YTD | AM10: FromTrade | AO10: YTD | AP10: FromTrade | AR10: YTD | AS10: FromTrade | AU10: YTD | AV10: FromTrade | AX10: YTD | AY10: FromTrade | BA10: YTD | BB10: FromTrade | BD10: YTD | BE10: FromTrade | BG10: YTD | BH10: FromTrade | BJ10: YTD | BK10: FromTrade | BM10: YTD | BN10: FromTrade | BP10: YTD | BQ10: FromTrade | BS10: YTD | BT10: FromTrade | BV10: YTD | BW10: FromTrade | BY10: YTD | BZ10: FromTrade | CB10: YTD | CC10: FromTrade | CE10: YTD | CF10: FromTrade | CH10: YTD | CI10: FromTrade | CK10: YTD | CL10: FromTrade | CN10: YTD | CO10: FromTrade | CQ10: YTD | CR10: FromTrade | CT10: YTD | CU10: FromTrade | CW10: YTD | CX10: FromTrade | CZ10: YTD | DA10: FromTrade | DC10: YTD | DD10: FromTrade | DF10: YTD | DG10: FromTrade | DI10: YTD | DJ10: FromTrade | DL10: YTD | DM10: FromTrade | DO10: YTD | DP10: FromTrade | DR10: YTD | DS10: FromTrade | DU10: YTD | DV10: FromTrade | DX10: YTD | DY10: FromTrade | EA10: YTD | EB10: FromTrade | ED10: YTD | EE10: FromTrade | EG10: YTD | EH10: FromTrade | EJ10: YTD | EK10: FromTrade | EM10: YTD | EN10: FromTrade | EP10: YTD | EQ10: FromTrade | ES10: YTD | ET10: FromTrade | EV10: YTD | EW10: FromTrade | EY10: YTD | EZ10: FromTrade | FB10: YTD | FC10: FromTrade | FE10: YTD | FF10: FromTrade | FH10: YTD | FI10: FromTrade | FK10: YTD | FL10: FromTrade | FN10: YTD | FO10: FromTrade | FQ10: YTD | FR10: FromTrade | FT10: YTD | FU10: FromTrade | FW10: YTD | FX10: FromTrade | FZ10: YTD | GA10: FromTrade | GC10: YTD | GD10: FromTrade | GF10: YTD | GG10: FromTrade | GI10: YTD | GJ10: FromTrade | GL10: YTD | GM10: FromTrade | GO10: YTD | GP10: FromTrade | GR10: YTD | GS10: FromTrade | GU10: YTD | GV10: FromTrade | GX10: YTD | GY10: FromTrade | HA10: YTD | HB10: FromTrade | HD10: YTD | HE10: FromTrade | HG10: YTD | HH10: FromTrade | HJ10: YTD | HK10: FromTrade | HM10: YTD | HN10: FromTrade | HP10: YTD | HQ10: FromTrade | HS10: YTD | HT10: FromTrade | HV10: YTD | HW10: FromTrade | HY10: YTD | HZ10: FromTrade | IB10: YTD | IC10: FromTrade | IE10: YTD | IF10: FromTrade | IH10: YTD | II10: FromTrade | IK10: YTD | IL10: FromTrade | IN10: YTD | IO10: FromTrade | IS10: Change | IT10: Value | IU10: Calc | IV10: Reduction | IW10: Gain/Loss | IX10: Gain/Loss | IY10: Fr. Trade | IZ10: Fr. Trade
A11: ='Investment Analysis'!A11 | B11: ='Investment Analysis'!B11 | C11: ='Investment Analysis'!C11 | D11: ='Investment Analysis'!D11 | E11: ='Investment Analysis'!E11 | F11: ='Investment Analysis'!G11 | G11: ='Investment Analysis'!H11 | H11: ='Investment Analysis'!I11 | I11: ='Investment Analysis'!K11 | J11: ='Investment Analysis'!L11 | K11: ='Investment Analysis'!M11 | L11: ='Investment Analysis'!T11 | M11: ='Investment Analysis'!V11 | N11: ='Investment Analysis'!W11 | P11: ='Investment Analysis'!Y11 | S11: 22394.73 | T11: =IF(S11>0,(S11-T$5)/T$5,0) | U11: ='Investment Analysis'!AF11 | V11: 17689.66 | W11: =IF(V11>0,(V11-W$5)/W$5,0) | X11: ='Investment Analysis'!AT11 | Y11: 9984.42 | Z11: =IF(Y11>0,(Y11-Z$5)/Z$5,0) | AA11: ='Investment Analysis'!GK11 | AB11: 2652.34 | AC11: =IF(AB11>0,(AB11-AC$5)/AC$5,0) | AD11: ='Investment Analysis'!AT11 | AE11: 22221.71 | AF11: =IF(AE11>0,(AE11-AF$5)/AF$5,0) | AG11: ='Investment Analysis'!BA11 | AI11: =IF(AH11>0,(AH11-AI$5)/AI$5,0) | AJ11: ='Investment Analysis'!BH11 | AK11: 18871.11 | AL11: =IF(AK11>0,(AK11-AL$5)/AL$5,0) | AM11: ='Investment Analysis'!BO11 | AN11: 14657.64 | AO11: =IF(AN11>0,(AN11-AO$5)/AO$5,0) | AP11: ='Investment Analysis'!BV11 | AR11: =IF(AQ11>0,(AQ11-AR$5)/AR$5,0) | AS11: ='Investment Analysis'!CC11 | AT11: 27039.97 | AU11: =IF(AT11>0,(AT11-AU$5)/AU$5,0) | AV11: ='Investment Analysis'!CJ11 | AW11: 19194.02 | AX11: =IF(AW11>0,(AW11-AX$5)/AX$5,0) | AY11: ='Investment Analysis'!CQ11 | AZ11: 16686.63 | BA11: =IF(AZ11>0,(AZ11-BA$5)/BA$5,0) | BB11: ='Investment Analysis'!CX11 | BC11: 9941.01 | BD11: =IF(BC11>0,(BC11-BD$5)/BD$5,0) | BE11: ='Investment Analysis'!DE11 | BF11: 4167.93 | BG11: =IF(BF11>0,(BF11-BG$5)/BG$5,0) | BH11: ='Investment Analysis'!DL11 | BI11: 2572.08 | BJ11: =IF(BI11>0,(BI11-BJ$5)/BJ$5,0) | BK11: ='Investment Analysis'!DZ11 | BL11: 4383.9 | BM11: =IF(BL11>0,(BL11-BM$5)/BM$5,0) | BN11: ='Investment Analysis'!EG11 | BP11: =IF(BO11>0,(BO11-BP$5)/BP$5,0) | BQ11: ='Investment Analysis'!DS11 | BR11: 5670.58 | BS11: =IF(BR11>0,(BR11-BS$5)/BS$5,0) | BT11: ='Investment Analysis'!EN11 | BU11: 14663.23 | BV11: =IF(BU11>0,(BU11-BV$5)/BV$5,0) | BW11: ='Investment Analysis'!EU11 | BY11: =IF(BX11>0,(BX11-BY$5)/BY$5,0) | BZ11: ='Investment Analysis'!FB11 | CA11: 3213.05 | CB11: =IF(CA11>0,(CA11-CB$5)/CB$5,0) | CC11: ='Investment Analysis'!FI11 | CD11: 18997.59 | CE11: =IF(CD11>0,(CD11-CE$5)/CE$5,0) | CF11: ='Investment Analysis'!FP11 | CG11: 5006.94 | CH11: =IF(CG11>0,(CG11-CH$5)/CH$5,0) | CI11: ='Investment Analysis'!FW11 | CK11: =IF(CJ11>0,(CJ11-CK$5)/CK$5,0) | CL11: ='Investment Analysis'!GD11 | CM11: 4964.99 | CN11: =IF(CM11>0,(CM11-CN$5)/CN$5,0) | CO11: ='Investment Analysis'!GT11 | CP11: 56892 | CQ11: =IF(CP11>0,(CP11-CQ$5)/CQ$5,0) | CR11: ='Investment Analysis'!HG11 | CS11: 6930 | CT11: =IF(CS11>0,(CS11-CT$5)/CT$5,0) | CU11: ='Investment Analysis'!HN11 | CW11: =IF(CV11>0,(CV11-CW$5)/CW$5,0) | CX11: ='Investment Analysis'!IB11 | CY11: 4639.6 | CZ11: =IF(CY11>0,(CY11-CZ$5)/CZ$5,0) | DA11: ='Investment Analysis'!II11 | DB11: 22092 | DC11: =IF(DB11>0,(DB11-DC$5)/DC$5,0) | DD11: ='Investment Analysis'!IP11 | DF11: =IF(DE11>0,(DE11-DF$5)/DF$5,0) | DG11: ='Investment Analysis'!IW11 | DH11: 2996.2 | DI11: =IF(DH11>0,(DH11-DI$5)/DI$5,0) | DJ11: ='Investment Analysis'!JD11 | DK11: 2092.9 | DL11: =IF(DK11>0,(DK11-DL$5)/DL$5,0) | DM11: ='Investment Analysis'!JK11 | DN11: 5365.5 | DO11: =IF(DN11>0,(DN11-DO$5)/DO$5,0) | DP11: ='Investment Analysis'!HU11 | DQ11: 23687.5 | DR11: =IF(DQ11>0,(DQ11-DR$5)/DR$5,0) | DS11: ='Investment Analysis'!JR11 | DT11: 3542 | DU11: =IF(DT11>0,(DT11-DU$5)/DU$5,0) | DV11: ='Investment Analysis'!JY11 | DW11: 22745.25 | DX11: =IF(DW11>0,(DW11-DX$5)/DX$5,0) | DY11: ='Investment Analysis'!KF11 | DZ11: 2311.2 | EA11: =IF(DZ11>0,(DZ11-EA$5)/EA$5,0) | EB11: ='Investment Analysis'!KM11 | EC11: 2438.5 | ED11: =IF(EC11>0,(EC11-ED$5)/ED$5,0) | EE11: ='Investment Analysis'!KT11 | EF11: 35512.5 | EG11: =IF(EF11>0,(EF11-EG$5)/EG$5,0) | EH11: ='Investment Analysis'!LH11 | EI11: 7625.07 | EJ11: =IF(EI11>0,(EI11-EJ$5)/EJ$5,0) | EK11: ='Investment Analysis'!LO11 | EM11: =IF(EL11>0,(EL11-EM$5)/EM$5,0) | EN11: ='Investment Analysis'!LV11 | EP11: =IF(EO11>0,(EO11-EP$5)/EP$5,0) | EQ11: ='Investment Analysis'!MC11 | ER11: 24249.82 | ES11: =IF(ER11>0,(ER11-ES$5)/ES$5,0) | ET11: ='Investment Analysis'!LA11 | EU11: 30590 | EV11: ='Investment Analysis'!ML11 | EW11: ='Investment Analysis'!MJ11 | EX11: 39018 | EY11: =IF(EX11>0,(EX11-EY$5)/EY$5,0) | EZ11: ='Investment Analysis'!MQ11 | FB11: =IF(FA11>0,(FA11-FB$5)/FB$5,0) | FC11: ='Investment Analysis'!MX11 | FD11: 4214.75 | FE11: =IF(FD11>0,(FD11-FE$5)/FE$5,0) | FF11: ='Investment Analysis'!NE11 | FH11: =IF(FG11>0,(FG11-FH$5)/FH$5,0) | FI11: ='Investment Analysis'!NL11 | FJ11: 8473.5 | FK11: =IF(FJ11>0,(FJ11-FK$5)/FK$5,0) | FL11: ='Investment Analysis'!NS11 | FM11: 30308.8 | FN11: =IF(FM11>0,(FM11-FN$5)/FN$5,0) | FO11: ='Investment Analysis'!NZ11 | FQ11: =IF(FP11>0,(FP11-FQ$5)/FQ$5,0) | FR11: ='Investment Analysis'!OG11 | FS11: 35173.75 | FT11: =IF(FS11>0,(FS11-FT$5)/FT$5,0) | FU11: ='Investment Analysis'!ON11 | FW11: =IF(FV11>0,(FV11-FW$5)/FW$5,0) | FX11: ='Investment Analysis'!OU11 | FZ11: =IF(FY11>0,(FY11-FZ$5)/FZ$5,0) | GC11: ='Investment Analysis'!PK11 | GD11: ='Investment Analysis'!PI11 | GE11: 6727 | GF11: ='Investment Analysis'!PY11 | GG11: ='Investment Analysis'!PW11 | GH11: 25175 | GI11: ='Investment Analysis'!QF11 | GJ11: ='Investment Analysis'!QD11 | GK11: 24220 | GL11: ='Investment Analysis'!QM11 | GM11: ='Investment Analysis'!QK11 | GN11: 9440.64 | GO11: ='Investment Analysis'!QT11 | GP11: ='Investment Analysis'!QR11 | GQ11: 17130.65 | GR11: ='Investment Analysis'!RA11 | GS11: ='Investment Analysis'!QY11 | GT11: 14966 | GU11: ='Investment Analysis'!RH11 | GV11: ='Investment Analysis'!RF11 | GX11: ='Investment Analysis'!RO11 | GY11: ='Investment Analysis'!RM11 | HA11: ='Investment Analysis'!RV11 | HB11: ='Investment Analysis'!RT11 | HD11: ='Investment Analysis'!SC11 | HE11: ='Investment Analysis'!SA11 | HG11: ='Investment Analysis'!SJ11 | HH11: ='Investment Analysis'!SH11 | HJ11: ='Investment Analysis'!SM11 | HK11: ='Investment Analysis'!SK11 | HM11: ='Investment Analysis'!SP11 | HN11: ='Investment Analysis'!SN11 | HP11: ='Investment Analysis'!TE11 | HQ11: ='Investment Analysis'!TC11 | HS11: ='Investment Analysis'!TL11 | HT11: ='Investment Analysis'!TJ11 | HV11: ='Investment Analysis'!TS11 | HW11: ='Investment Analysis'!TQ11 | HY11: ='Investment Analysis'!TZ11 | HZ11: ='Investment Analysis'!TX11 | IB11: ='Investment Analysis'!UG11 | IC11: ='Investment Analysis'!UE11 | IE11: ='Investment Analysis'!UN11 | IF11: ='Investment Analysis'!UL11 | IH11: ='Investment Analysis'!UU11 | II11: ='Investment Analysis'!US11 | IK11: ='Investment Analysis'!VB11 | IL11: ='Investment Analysis'!UZ11 | IN11: ='Investment Analysis'!VI11 | IO11: ='Investment Analysis'!VG11 | IS11: =IF(IT11>0,IT11-IS8,0) | IT11: =FY11+FV11+FS11+FP11+FM11+FJ11+FG11+FD11+FA11+EX11+EU11+ER11+EO11+EL11+EI11+EF11+EC11+DZ11+DW11+DT11+DQ11+DN11+DK11+DH11+DE11+DB11+CY11+CV11+CS11+CP11+CJ11+CG11+CD11+CA11+BX11+P11+CM11+GT11+GQ11+GN11+GK11+GH11+GE11+GB11+BU11+BR11+BO11+BL11+BI11+BF11+BC11+AZ11+AW11+AT11+AQ11+AN11+AK11+AH11+AE11+AB11+Y11+V11+S11+GW11+GZ11+HC11+HF11+HI11+HL11+HO11+HR11+HU11 | IU11: =IF(IT11>0,IV11,0) | IW11: =IF(IT11>0,(IT11+IV$11-I$2)/I$2,0) | IX11: =IF(IT11>0,IT11+IV$11-I$2,0) | IY11: =IF(IT11>0,(IT11+IV$11-IT$8)/IT$8,0) | IZ11: =IF(IT11>0,IT11+IV$11-IT$8,0)
A12: ='Investment Analysis'!A12 | B12: ='Investment Analysis'!B12 | C12: ='Investment Analysis'!C12 | D12: ='Investment Analysis'!D12 | E12: ='Investment Analysis'!E12 | F12: ='Investment Analysis'!G12 | G12: ='Investment Analysis'!H12 | H12: ='Investment Analysis'!I12 | I12: ='Investment Analysis'!K12 | J12: ='Investment Analysis'!L12 | K12: ='Investment Analysis'!M12 | L12: ='Investment Analysis'!T12 | M12: ='Investment Analysis'!V12 | N12: ='Investment Analysis'!W12 | P12: ='Investment Analysis'!Y12 | S12: 22807.18 | T12: =IF(S12>0,(S12-T$5)/T$5,0) | U12: ='Investment Analysis'!AF12 | V12: 17932.22 | W12: =IF(V12>0,(V12-W$5)/W$5,0) | X12: ='Investment Analysis'!AT12 | Y12: 10073.52 | Z12: =IF(Y12>0,(Y12-Z$5)/Z$5,0) | AA12: ='Investment Analysis'!GK12 | AB12: 2696.67 | AC12: =IF(AB12>0,(AB12-AC$5)/AC$5,0) | AD12: ='Investment Analysis'!AT12 | AE12: 22503.11 | AF12: =IF(AE12>0,(AE12-AF$5)/AF$5,0) | AG12: ='Investment Analysis'!BA12 | AI12: =IF(AH12>0,(AH12-AI$5)/AI$5,0) | AJ12: ='Investment Analysis'!BH12 | AK12: 19310.96 | AL12: =IF(AK12>0,(AK12-AL$5)/AL$5,0) | AM12: ='Investment Analysis'!BO12 | AN12: 14988.26 | AO12: =IF(AN12>0,(AN12-AO$5)/AO$5,0) | AP12: ='Investment Analysis'!BV12 | AR12: =IF(AQ12>0,(AQ12-AR$5)/AR$5,0) | AS12: ='Investment Analysis'!CC12 | AT12: 27535.62 | AU12: =IF(AT12>0,(AT12-AU$5)/AU$5,0) | AV12: ='Investment Analysis'!CJ12 | AW12: 19576.53 | AX12: =IF(AW12>0,(AW12-AX$5)/AX$5,0) | AY12: ='Investment Analysis'!CQ12 | AZ12: 16928.66 | BA12: =IF(AZ12>0,(AZ12-BA$5)/BA$5,0) | BB12: ='Investment Analysis'!CX12 | BC12: 10092.82 | BD12: =IF(BC12>0,(BC12-BD$5)/BD$5,0) | BE12: ='Investment Analysis'!DE12 | BF12: 4179.78 | BG12: =IF(BF12>0,(BF12-BG$5)/BG$5,0) | BH12: ='Investment Analysis'!DL12 | BI12: 2650.11 | BJ12: =IF(BI12>0,(BI12-BJ$5)/BJ$5,0) | BK12: ='Investment Analysis'!DZ12 | BL12: 4477.51 | BM12: =IF(BL12>0,(BL12-BM$5)/BM$5,0) | BN12: ='Investment Analysis'!EG12 | BP12: =IF(BO12>0,(BO12-BP$5)/BP$5,0) | BQ12: ='Investment Analysis'!DS12 | BR12: 5737.73 | BS12: =IF(BR12>0,(BR12-BS$5)/BS$5,0) | BT12: ='Investment Analysis'!EN12 | BU12: 14841.54 | BV12: =IF(BU12>0,(BU12-BV$5)/BV$5,0) | BW12: ='Investment Analysis'!EU12 | BY12: =IF(BX12>0,(BX12-BY$5)/BY$5,0) | BZ12: ='Investment Analysis'!FB12 | CA12: 3246.62 | CB12: =IF(CA12>0,(CA12-CB$5)/CB$5,0) | CC12: ='Investment Analysis'!FI12 | CD12: 19260.78 | CE12: =IF(CD12>0,(CD12-CE$5)/CE$5,0) | CF12: ='Investment Analysis'!FP12 | CG12: 5029.86 | CH12: =IF(CG12>0,(CG12-CH$5)/CH$5,0) | CI12: ='Investment Analysis'!FW12 | CK12: =IF(CJ12>0,(CJ12-CK$5)/CK$5,0) | CL12: ='Investment Analysis'!GD12 | CM12: 5018.73 | CN12: =IF(CM12>0,(CM12-CN$5)/CN$5,0) | CO12: ='Investment Analysis'!GT12 | CP12: 61566 | CQ12: =IF(CP12>0,(CP12-CQ$5)/CQ$5,0) | CR12: ='Investment Analysis'!HG12 | CS12: 7080 | CT12: =IF(CS12>0,(CS12-CT$5)/CT$5,0) | CU12: ='Investment Analysis'!HN12 | CW12: =IF(CV12>0,(CV12-CW$5)/CW$5,0) | CX12: ='Investment Analysis'!IB12 | CY12: 4651 | CZ12: =IF(CY12>0,(CY12-CZ$5)/CZ$5,0) | DA12: ='Investment Analysis'!II12 | DB12: 22215.2 | DC12: =IF(DB12>0,(DB12-DC$5)/DC$5,0) | DD12: ='Investment Analysis'!IP12 | DF12: =IF(DE12>0,(DE12-DF$5)/DF$5,0) | DG12: ='Investment Analysis'!IW12 | DH12: 3023.15 | DI12: =IF(DH12>0,(DH12-DI$5)/DI$5,0) | DJ12: ='Investment Analysis'!JD12 | DK12: 2116.75 | DL12: =IF(DK12>0,(DK12-DL$5)/DL$5,0) | DM12: ='Investment Analysis'!JK12 | DN12: 5393 | DO12: =IF(DN12>0,(DN12-DO$5)/DO$5,0) | DP12: ='Investment Analysis'!HU12 | DQ12: 24367.5 | DR12: =IF(DQ12>0,(DQ12-DR$5)/DR$5,0) | DS12: ='Investment Analysis'!JR12 | DT12: 4170 | DU12: =IF(DT12>0,(DT12-DU$5)/DU$5,0) | DV12: ='Investment Analysis'!JY12 | DW12: 22914.5 | DX12: =IF(DW12>0,(DW12-DX$5)/DX$5,0) | DY12: ='Investment Analysis'!KF12 | DZ12: 2300.4 | EA12: =IF(DZ12>0,(DZ12-EA$5)/EA$5,0) | EB12: ='Investment Analysis'!KM12 | EC12: 2433.6 | ED12: =IF(EC12>0,(EC12-ED$5)/ED$5,0) | EE12: ='Investment Analysis'!KT12 | EF12: 35265 | EG12: =IF(EF12>0,(EF12-EG$5)/EG$5,0) | EH12: ='Investment Analysis'!LH12 | EI12: 7540.44 | EJ12: =IF(EI12>0,(EI12-EJ$5)/EJ$5,0) | EK12: ='Investment Analysis'!LO12 | EM12: =IF(EL12>0,(EL12-EM$5)/EM$5,0) | EN12: ='Investment Analysis'!LV12 | EP12: =IF(EO12>0,(EO12-EP$5)/EP$5,0) | EQ12: ='Investment Analysis'!MC12 | ER12: 24696.71 | ES12: =IF(ER12>0,(ER12-ES$5)/ES$5,0) | ET12: ='Investment Analysis'!LA12 | EU12: 38150 | EV12: ='Investment Analysis'!ML12 | EW12: ='Investment Analysis'!MJ12 | EX12: 39725 | EY12: =IF(EX12>0,(EX12-EY$5)/EY$5,0) | EZ12: ='Investment Analysis'!MQ12 | FB12: =IF(FA12>0,(FA12-FB$5)/FB$5,0) | FC12: ='Investment Analysis'!MX12 | FD12: 4299 | FE12: =IF(FD12>0,(FD12-FE$5)/FE$5,0) | FF12: ='Investment Analysis'!NE12 | FH12: =IF(FG12>0,(FG12-FH$5)/FH$5,0) | FI12: ='Investment Analysis'!NL12 | FJ12: 8850.75 | FK12: =IF(FJ12>0,(FJ12-FK$5)/FK$5,0) | FL12: ='Investment Analysis'!NS12 | FM12: 30686.4 | FN12: =IF(FM12>0,(FM12-FN$5)/FN$5,0) | FO12: ='Investment Analysis'!NZ12 | FQ12: =IF(FP12>0,(FP12-FQ$5)/FQ$5,0) | FR12: ='Investment Analysis'!OG12 | FS12: 38380 | FT12: =IF(FS12>0,(FS12-FT$5)/FT$5,0) | FU12: ='Investment Analysis'!ON12 | FW12: =IF(FV12>0,(FV12-FW$5)/FW$5,0) | FX12: ='Investment Analysis'!OU12 | FZ12: =IF(FY12>0,(FY12-FZ$5)/FZ$5,0) | GA12: ='Investment Analysis'!PB12 | GC12: ='Investment Analysis'!PK12 | GD12: ='Investment Analysis'!PI12 | GE12: 6722 | GF12: ='Investment Analysis'!PY12 | GG12: ='Investment Analysis'!PW12 | GH12: 25436 | GI12: ='Investment Analysis'!QF12 | GJ12: ='Investment Analysis'!QD12 | GK12: 24404 | GL12: ='Investment Analysis'!QM12 | GM12: ='Investment Analysis'!QK12 | GN12: 9688.24 | GO12: ='Investment Analysis'!QT12 | GP12: ='Investment Analysis'!QR12 | GQ12: 16974.3 | GR12: ='Investment Analysis'!RA12 | GS12: ='Investment Analysis'!QY12 | GT12: 16236 | GU12: ='Investment Analysis'!RH12 | GV12: ='Investment Analysis'!RF12 | GX12: ='Investment Analysis'!RO12 | GY12: ='Investment Analysis'!RM12 | HA12: ='Investment Analysis'!RV12 | HB12: ='Investment Analysis'!RT12 | HD12: ='Investment Analysis'!SC12 | HE12: ='Investment Analysis'!SA12 | HG12: ='Investment Analysis'!SJ12 | HH12: ='Investment Analysis'!SH12 | HJ12: ='Investment Analysis'!SM12 | HK12: ='Investment Analysis'!SK12 | HM12: ='Investment Analysis'!SP12 | HN12: ='Investment Analysis'!SN12 | HO12: ='Investment Analysis'!SZ257 | HP12: ='Investment Analysis'!TE12 | HQ12: ='Investment Analysis'!TC12 | HS12: ='Investment Analysis'!TL12 | HT12: ='Investment Analysis'!TJ12 | HV12: ='Investment Analysis'!TS12 | HW12: ='Investment Analysis'!TQ12 | HY12: ='Investment Analysis'!TZ12 | HZ12: ='Investment Analysis'!TX12 | IB12: ='Investment Analysis'!UG12 | IC12: ='Investment Analysis'!UE12 | IE12: ='Investment Analysis'!UN12 | IF12: ='Investment Analysis'!UL12 | IH12: ='Investment Analysis'!UU12 | II12: ='Investment Analysis'!US12 | IK12: ='Investment Analysis'!VB12 | IL12: ='Investment Analysis'!UZ12 | IN12: ='Investment Analysis'!VI12 | IO12: ='Investment Analysis'!VG12 | IS12: =IF(IT12>0,IT12-IT11,0) | IT12: =FY12+FV12+FS12+FP12+FM12+FJ12+FG12+FD12+FA12+EX12+EU12+ER12+EO12+EL12+EI12+EF12+EC12+DZ12+DW12+DT12+DQ12+DN12+DK12+DH12+DE12+DB12+CY12+CV12+CS12+CP12+CJ12+CG12+CD12+CA12+BX12+P12+CM12+GT12+GQ12+GN12+GK12+GH12+GE12+GB12+BU12+BR12+BO12+BL12+BI12+BF12+BC12+AZ12+AW12+AT12+AQ12+AN12+AK12+AH12+AE12+AB12+Y12+V12+S12+GW12+GZ12+HC12+HF12+HI12+HL12+HO12+HR12+HU12+HX12+IA12+ID12+IG12+IJ12+IM12 | IU12: =IF(IT12>0,IV12,0) | IV12: 3600 | IW12: =IF(IT12>0,(IT12+IV$11-I$2)/I$2,0) | IX12: =IF(IT12>0,IT12+IV$11-I$2,0) | IY12: =IF(IT12>0,(IT12+IV$11-IT$8)/IT$8,0) | IZ12: =IF(IT12>0,IT12+IV$11-IT$8,0)
A13: ='Investment Analysis'!A13 | B13: ='Investment Analysis'!B13 | C13: ='Investment Analysis'!C13 | D13: ='Investment Analysis'!D13 | E13: ='Investment Analysis'!E13 | F13: ='Investment Analysis'!G13 | G13: ='Investment Analysis'!H13 | H13: ='Investment Analysis'!I13 | I13: ='Investment Analysis'!K13 | J13: ='Investment Analysis'!L13 | K13: ='Investment Analysis'!M13 | L13: ='Investment Analysis'!T13 | M13: ='Investment Analysis'!V13 | N13: ='Investment Analysis'!W13 | P13: ='Investment Analysis'!Y13 | S13: 23167.57 | T13: =IF(S13>0,(S13-T$5)/T$5,0) | U13: ='Investment Analysis'!AF13 | V13: 18174.77 | W13: =IF(V13>0,(V13-W$5)/W$5,0) | X13: ='Investment Analysis'!AT13 | Y13: 9979.18 | Z13: =IF(Y13>0,(Y13-Z$5)/Z$5,0) | AA13: ='Investment Analysis'!GK13 | AB13: 2742.23 | AC13: =IF(AB13>0,(AB13-AC$5)/AC$5,0) | AD13: ='Investment Analysis'!AT13 | AE13: 22629.63 | AF13: =IF(AE13>0,(AE13-AF$5)/AF$5,0) | AG13: ='Investment Analysis'!BA13 | AI13: =IF(AH13>0,(AH13-AI$5)/AI$5,0) | AJ13: ='Investment Analysis'!BH13 | AK13: 19327.87 | AL13: =IF(AK13>0,(AK13-AL$5)/AL$5,0) | AM13: ='Investment Analysis'!BO13 | AN13: 15201.08 | AO13: =IF(AN13>0,(AN13-AO$5)/AO$5,0) | AP13: ='Investment Analysis'!BV13 | AR13: =IF(AQ13>0,(AQ13-AR$5)/AR$5,0) | AS13: ='Investment Analysis'!CC13 | AT13: 27685.09 | AU13: =IF(AT13>0,(AT13-AU$5)/AU$5,0) | AV13: ='Investment Analysis'!CJ13 | AW13: 19610.79 | AX13: =IF(AW13>0,(AW13-AX$5)/AX$5,0) | AY13: ='Investment Analysis'!CQ13 | AZ13: 16973.48 | BA13: =IF(AZ13>0,(AZ13-BA$5)/BA$5,0) | BB13: ='Investment Analysis'!CX13 | BC13: 10102.61 | BD13: =IF(BC13>0,(BC13-BD$5)/BD$5,0) | BE13: ='Investment Analysis'!DE13 | BF13: 4231.17 | BG13: =IF(BF13>0,(BF13-BG$5)/BG$5,0) | BH13: ='Investment Analysis'!DL13 | BI13: 2734.97 | BJ13: =IF(BI13>0,(BI13-BJ$5)/BJ$5,0) | BK13: ='Investment Analysis'!DZ13 | BL13: 4565.18 | BM13: =IF(BL13>0,(BL13-BM$5)/BM$5,0) | BN13: ='Investment Analysis'!EG13 | BP13: =IF(BO13>0,(BO13-BP$5)/BP$5,0) | BQ13: ='Investment Analysis'!DS13 | BR13: 5866.47 | BS13: =IF(BR13>0,(BR13-BS$5)/BS$5,0) | BT13: ='Investment Analysis'!EN13 | BU13: 14796.01 | BV13: =IF(BU13>0,(BU13-BV$5)/BV$5,0) | BW13: ='Investment Analysis'!EU13 | BY13: =IF(BX13>0,(BX13-BY$5)/BY$5,0) | BZ13: ='Investment Analysis'!FB13 | CA13: 3252.78 | CB13: =IF(CA13>0,(CA13-CB$5)/CB$5,0) | CC13: ='Investment Analysis'!FI13 | CD13: 19226.45 | CE13: =IF(CD13>0,(CD13-CE$5)/CE$5,0) | CF13: ='Investment Analysis'!FP13 | CG13: 4977.87 | CH13: =IF(CG13>0,(CG13-CH$5)/CH$5,0) | CI13: ='Investment Analysis'!FW13 | CK13: =IF(CJ13>0,(CJ13-CK$5)/CK$5,0) | CL13: ='Investment Analysis'!GD13 | CM13: 5004.4 | CN13: =IF(CM13>0,(CM13-CN$5)/CN$5,0) | CO13: ='Investment Analysis'!GT13 | CP13: 61657.5 | CQ13: =IF(CP13>0,(CP13-CQ$5)/CQ$5,0) | CR13: ='Investment Analysis'!HG13 | CS13: 6930 | CT13: =IF(CS13>0,(CS13-CT$5)/CT$5,0) | CU13: ='Investment Analysis'!HN13 | CW13: =IF(CV13>0,(CV13-CW$5)/CW$5,0) | CX13: ='Investment Analysis'!IB13 | CY13: 4728.2 | CZ13: =IF(CY13>0,(CY13-CZ$5)/CZ$5,0) | DA13: ='Investment Analysis'!II13 | DB13: 22308.8 | DC13: =IF(DB13>0,(DB13-DC$5)/DC$5,0) | DD13: ='Investment Analysis'!IP13 | DF13: =IF(DE13>0,(DE13-DF$5)/DF$5,0) | DG13: ='Investment Analysis'!IW13 | DH13: 3151 | DI13: =IF(DH13>0,(DH13-DI$5)/DI$5,0) | DJ13: ='Investment Analysis'!JD13 | DK13: 2139.25 | DL13: =IF(DK13>0,(DK13-DL$5)/DL$5,0) | DM13: ='Investment Analysis'!JK13 | DN13: 5387 | DO13: =IF(DN13>0,(DN13-DO$5)/DO$5,0) | DP13: ='Investment Analysis'!HU13 | DQ13: 24485 | DR13: =IF(DQ13>0,(DQ13-DR$5)/DR$5,0) | DS13: ='Investment Analysis'!JR13 | DT13: 4732 | DU13: =IF(DT13>0,(DT13-DU$5)/DU$5,0) | DV13: ='Investment Analysis'!JY13 | DW13: 23067.75 | DX13: =IF(DW13>0,(DW13-DX$5)/DX$5,0) | DY13: ='Investment Analysis'!KF13 | DZ13: 2242.8 | EA13: =IF(DZ13>0,(DZ13-EA$5)/EA$5,0) | EB13: ='Investment Analysis'!KM13 | EC13: 2450 | ED13: =IF(EC13>0,(EC13-ED$5)/ED$5,0) | EE13: ='Investment Analysis'!KT13 | EF13: 35730 | EG13: =IF(EF13>0,(EF13-EG$5)/EG$5,0) | EH13: ='Investment Analysis'!LH13 | EI13: 7408.38 | EJ13: =IF(EI13>0,(EI13-EJ$5)/EJ$5,0) | EK13: ='Investment Analysis'!LO13 | EM13: =IF(EL13>0,(EL13-EM$5)/EM$5,0) | EN13: ='Investment Analysis'!LV13 | EP13: =IF(EO13>0,(EO13-EP$5)/EP$5,0) | EQ13: ='Investment Analysis'!MC13 | ER13: 24772.15 | ES13: =IF(ER13>0,(ER13-ES$5)/ES$5,0) | ET13: ='Investment Analysis'!LA13 | EU13: 42000 | EV13: ='Investment Analysis'!ML13 | EW13: ='Investment Analysis'!MJ13 | EX13: 40173 | EY13: =IF(EX13>0,(EX13-EY$5)/EY$5,0) | EZ13: ='Investment Analysis'!MQ13 | FB13: =IF(FA13>0,(FA13-FB$5)/FB$5,0) | FC13: ='Investment Analysis'!MX13 | FD13: 4311.25 | FE13: =IF(FD13>0,(FD13-FE$5)/FE$5,0) | FF13: ='Investment Analysis'!NE13 | FH13: =IF(FG13>0,(FG13-FH$5)/FH$5,0) | FI13: ='Investment Analysis'!NL13 | FJ13: 9283 | FK13: =IF(FJ13>0,(FJ13-FK$5)/FK$5,0) | FL13: ='Investment Analysis'!NS13 | FM13: 31499.2 | FN13: =IF(FM13>0,(FM13-FN$5)/FN$5,0) | FO13: ='Investment Analysis'!NZ13 | FQ13: =IF(FP13>0,(FP13-FQ$5)/FQ$5,0) | FR13: ='Investment Analysis'!OG13 | FS13: 38750.5 | FT13: =IF(FS13>0,(FS13-FT$5)/FT$5,0) | FU13: ='Investment Analysis'!ON13 | FW13: =IF(FV13>0,(FV13-FW$5)/FW$5,0) | FX13: ='Investment Analysis'!OU13 | FZ13: =IF(FY13>0,(FY13-FZ$5)/FZ$5,0) | GA13: ='Investment Analysis'!PB13 | GC13: ='Investment Analysis'!PK13 | GD13: ='Investment Analysis'!PI13 | GE13: 6627.5 | GF13: ='Investment Analysis'!PY13 | GG13: ='Investment Analysis'!PW13 | GH13: 25970 | GI13: ='Investment Analysis'!QF13 | GJ13: ='Investment Analysis'!QD13 | GK13: 24200 | GL13: ='Investment Analysis'!QM13 | GM13: ='Investment Analysis'!QK13 | GN13: 9813.04 | GO13: ='Investment Analysis'!QT13 | GP13: ='Investment Analysis'!QR13 | GQ13: 16649.8 | GR13: ='Investment Analysis'!RA13 | GS13: ='Investment Analysis'!QY13 | GT13: 16395 | GU13: ='Investment Analysis'!RH13 | GV13: ='Investment Analysis'!RF13 | GX13: ='Investment Analysis'!RO13 | GY13: ='Investment Analysis'!RM13 | HA13: ='Investment Analysis'!RV13 | HB13: ='Investment Analysis'!RT13 | HD13: ='Investment Analysis'!SC13 | HE13: ='Investment Analysis'!SA13 | HG13: ='Investment Analysis'!SJ13 | HH13: ='Investment Analysis'!SH13 | HJ13: ='Investment Analysis'!SM13 | HK13: ='Investment Analysis'!SK13 | HM13: ='Investment Analysis'!SP13 | HN13: ='Investment Analysis'!SN13 | HP13: ='Investment Analysis'!TE13 | HQ13: ='Investment Analysis'!TC13 | HS13: ='Investment Analysis'!TL13 | HT13: ='Investment Analysis'!TJ13 | HV13: ='Investment Analysis'!TS13 | HW13: ='Investment Analysis'!TQ13 | HY13: ='Investment Analysis'!TZ13 | HZ13: ='Investment Analysis'!TX13 | IB13: ='Investment Analysis'!UG13 | IC13: ='Investment Analysis'!UE13 | IE13: ='Investment Analysis'!UN13 | IF13: ='Investment Analysis'!UL13 | IH13: ='Investment Analysis'!UU13 | II13: ='Investment Analysis'!US13 | IK13: ='Investment Analysis'!VB13 | IL13: ='Investment Analysis'!UZ13 | IN13: ='Investment Analysis'!VI13 | IO13: ='Investment Analysis'!VG13 | IS13: =IF(IT13>0,IT13-IT12,0) | IT13: =FY13+FV13+FS13+FP13+FM13+FJ13+FG13+FD13+FA13+EX13+EU13+ER13+EO13+EL13+EI13+EF13+EC13+DZ13+DW13+DT13+DQ13+DN13+DK13+DH13+DE13+DB13+CY13+CV13+CS13+CP13+CJ13+CG13+CD13+CA13+BX13+P13+CM13+GT13+GQ13+GN13+GK13+GH13+GE13+GB13+BU13+BR13+BO13+BL13+BI13+BF13+BC13+AZ13+AW13+AT13+AQ13+AN13+AK13+AH13+AE13+AB13+Y13+V13+S13+GW13+GZ13+HC13+HF13+HI13+HL13+HO13+HR13+HU13 | IU13: =IF(IT13>0,IV13,0) | IW13: =IF(IT13>0,(IT13+IV$11-I$2)/I$2,0) | IX13: =IF(IT13>0,IT13+IV$11-I$2,0) | IY13: =IF(IT13>0,(IT13+IV$11-IT$8)/IT$8,0) | IZ13: =IF(IT13>0,IT13+IV$11-IT$8,0)
A14: ='Investment Analysis'!A14 | B14: ='Investment Analysis'!B14 | C14: ='Investment Analysis'!C14 | D14: ='Investment Analysis'!D14 | E14: ='Investment Analysis'!E14 | F14: ='Investment Analysis'!G14 | G14: ='Investment Analysis'!H14 | H14: ='Investment Analysis'!I14 | I14: ='Investment Analysis'!K14 | J14: ='Investment Analysis'!L14 | K14: ='Investment Analysis'!M14 | L14: ='Investment Analysis'!T14 | M14: ='Investment Analysis'!V14 | N14: ='Investment Analysis'!W14 | P14: ='Investment Analysis'!Y14 | S14: 22684.43 | T14: =IF(S14>0,(S14-T$5)/T$5,0) | U14: ='Investment Analysis'!AF14 | V14: 17932.22 | W14: =IF(V14>0,(V14-W$5)/W$5,0) | X14: ='Investment Analysis'!AT14 | Y14: 10052.56 | Z14: =IF(Y14>0,(Y14-Z$5)/Z$5,0) | AA14: ='Investment Analysis'!GK14 | AB14: 2690.52 | AC14: =IF(AB14>0,(AB14-AC$5)/AC$5,0) | AD14: ='Investment Analysis'!AT14 | AE14: 22378.77 | AF14: =IF(AE14>0,(AE14-AF$5)/AF$5,0) | AG14: ='Investment Analysis'!BA14 | AI14: =IF(AH14>0,(AH14-AI$5)/AI$5,0) | AJ14: ='Investment Analysis'!BH14 | AK14: 18975.43 | AL14: =IF(AK14>0,(AK14-AL$5)/AL$5,0) | AM14: ='Investment Analysis'!BO14 | AN14: 14954.06 | AO14: =IF(AN14>0,(AN14-AO$5)/AO$5,0) | AP14: ='Investment Analysis'!BV14 | AR14: =IF(AQ14>0,(AQ14-AR$5)/AR$5,0) | AS14: ='Investment Analysis'!CC14 | AT14: 27519.88 | AU14: =IF(AT14>0,(AT14-AU$5)/AU$5,0) | AV14: ='Investment Analysis'!CJ14 | AW14: 19450.93 | AX14: =IF(AW14>0,(AW14-AX$5)/AX$5,0) | AY14: ='Investment Analysis'!CQ14 | AZ14: 16874.88 | BA14: =IF(AZ14>0,(AZ14-BA$5)/BA$5,0) | BB14: ='Investment Analysis'!CX14 | BC14: 10058.54 | BD14: =IF(BC14>0,(BC14-BD$5)/BD$5,0) | BE14: ='Investment Analysis'!DE14 | BF14: 4219.31 | BG14: =IF(BF14>0,(BF14-BG$5)/BG$5,0) | BH14: ='Investment Analysis'!DL14 | BI14: 2657.69 | BJ14: =IF(BI14>0,(BI14-BJ$5)/BJ$5,0) | BK14: ='Investment Analysis'!DZ14 | BL14: 4447.88 | BM14: =IF(BL14>0,(BL14-BM$5)/BM$5,0) | BN14: ='Investment Analysis'!EG14 | BP14: =IF(BO14>0,(BO14-BP$5)/BP$5,0) | BQ14: ='Investment Analysis'!DS14 | BR14: 5776.1 | BS14: =IF(BR14>0,(BR14-BS$5)/BS$5,0) | BT14: ='Investment Analysis'!EN14 | BU14: 14640.46 | BV14: =IF(BU14>0,(BU14-BV$5)/BV$5,0) | BW14: ='Investment Analysis'!EU14 | BY14: =IF(BX14>0,(BX14-BY$5)/BY$5,0) | BZ14: ='Investment Analysis'!FB14 | CA14: 3285.79 | CB14: =IF(CA14>0,(CA14-CB$5)/CB$5,0) | CC14: ='Investment Analysis'!FI14 | CD14: 18864.43 | CE14: =IF(CD14>0,(CD14-CE$5)/CE$5,0) | CF14: ='Investment Analysis'!FP14 | CG14: 5004.7 | CH14: =IF(CG14>0,(CG14-CH$5)/CH$5,0) | CI14: ='Investment Analysis'!FW14 | CK14: =IF(CJ14>0,(CJ14-CK$5)/CK$5,0) | CL14: ='Investment Analysis'!GD14 | CM14: 4982.9 | CN14: =IF(CM14>0,(CM14-CN$5)/CN$5,0) | CO14: ='Investment Analysis'!GT14 | CP14: 59154 | CQ14: =IF(CP14>0,(CP14-CQ$5)/CQ$5,0) | CR14: ='Investment Analysis'!HG14 | CS14: 6960 | CT14: =IF(CS14>0,(CS14-CT$5)/CT$5,0) | CU14: ='Investment Analysis'!HN14 | CV14: 0 | CW14: =IF(CV14>0,(CV14-CW$5)/CW$5,0) | CX14: ='Investment Analysis'!IB14 | CY14: 4572.8 | CZ14: =IF(CY14>0,(CY14-CZ$5)/CZ$5,0) | DA14: ='Investment Analysis'!II14 | DB14: 21981.6 | DC14: =IF(DB14>0,(DB14-DC$5)/DC$5,0) | DD14: ='Investment Analysis'!IP14 | DF14: =IF(DE14>0,(DE14-DF$5)/DF$5,0) | DG14: ='Investment Analysis'!IW14 | DH14: 3089.45 | DI14: =IF(DH14>0,(DH14-DI$5)/DI$5,0) | DJ14: ='Investment Analysis'!JD14 | DK14: 2111.85 | DL14: =IF(DK14>0,(DK14-DL$5)/DL$5,0) | DM14: ='Investment Analysis'!JK14 | DN14: 5437.5 | DO14: =IF(DN14>0,(DN14-DO$5)/DO$5,0) | DP14: ='Investment Analysis'!HU14 | DQ14: 23982.5 | DR14: =IF(DQ14>0,(DQ14-DR$5)/DR$5,0) | DS14: ='Investment Analysis'!JR14 | DT14: 4344 | DU14: =IF(DT14>0,(DT14-DU$5)/DU$5,0) | DV14: ='Investment Analysis'!JY14 | DW14: 23034.25 | DX14: =IF(DW14>0,(DW14-DX$5)/DX$5,0) | DY14: ='Investment Analysis'!KF14 | DZ14: 2247.6 | EA14: =IF(DZ14>0,(DZ14-EA$5)/EA$5,0) | EB14: ='Investment Analysis'!KM14 | EC14: 2422.1 | ED14: =IF(EC14>0,(EC14-ED$5)/ED$5,0) | EE14: ='Investment Analysis'!KT14 | EF14: 36112.5 | EG14: =IF(EF14>0,(EF14-EG$5)/EG$5,0) | EH14: ='Investment Analysis'!LH14 | EI14: 7546.95 | EJ14: =IF(EI14>0,(EI14-EJ$5)/EJ$5,0) | EK14: ='Investment Analysis'!LO14 | EM14: =IF(EL14>0,(EL14-EM$5)/EM$5,0) | EN14: ='Investment Analysis'!LV14 | EP14: =IF(EO14>0,(EO14-EP$5)/EP$5,0) | EQ14: ='Investment Analysis'!MC14 | ER14: 24245.45 | ES14: =IF(ER14>0,(ER14-ES$5)/ES$5,0) | ET14: ='Investment Analysis'!LA14 | EU14: 41300 | EV14: ='Investment Analysis'!ML14 | EW14: ='Investment Analysis'!MJ14 | EX14: 40295.5 | EY14: =IF(EX14>0,(EX14-EY$5)/EY$5,0) | EZ14: ='Investment Analysis'!MQ14 | FB14: =IF(FA14>0,(FA14-FB$5)/FB$5,0) | FC14: ='Investment Analysis'!MX14 | FD14: 4307.75 | FE14: =IF(FD14>0,(FD14-FE$5)/FE$5,0) | FF14: ='Investment Analysis'!NE14 | FH14: =IF(FG14>0,(FG14-FH$5)/FH$5,0) | FI14: ='Investment Analysis'!NL14 | FJ14: 9213 | FK14: =IF(FJ14>0,(FJ14-FK$5)/FK$5,0) | FL14: ='Investment Analysis'!NS14 | FM14: 31278.4 | FN14: =IF(FM14>0,(FM14-FN$5)/FN$5,0) | FO14: ='Investment Analysis'!NZ14 | FQ14: =IF(FP14>0,(FP14-FQ$5)/FQ$5,0) | FR14: ='Investment Analysis'!OG14 | FS14: 34983.75 | FT14: =IF(FS14>0,(FS14-FT$5)/FT$5,0) | FU14: ='Investment Analysis'!ON14 | FW14: =IF(FV14>0,(FV14-FW$5)/FW$5,0) | FX14: ='Investment Analysis'!OU14 | FZ14: =IF(FY14>0,(FY14-FZ$5)/FZ$5,0) | GA14: ='Investment Analysis'!PB14 | GC14: ='Investment Analysis'!PK14 | GD14: ='Investment Analysis'!PI14 | GE14: 6681.5 | GF14: ='Investment Analysis'!PY14 | GG14: ='Investment Analysis'!PW14 | GH14: 25729 | GI14: ='Investment Analysis'!QF14 | GJ14: ='Investment Analysis'!QD14 | GK14: 24280 | GL14: ='Investment Analysis'!QM14 | GM14: ='Investment Analysis'!QK14 | GN14: 10066.32 | GO14: ='Investment Analysis'!QT14 | GP14: ='Investment Analysis'!QR14 | GQ14: 16767.8 | GR14: ='Investment Analysis'!RA14 | GS14: ='Investment Analysis'!QY14 | GT14: 16337 | GU14: ='Investment Analysis'!RH14 | GV14: ='Investment Analysis'!RF14 | GX14: ='Investment Analysis'!RO14 | GY14: ='Investment Analysis'!RM14 | HA14: ='Investment Analysis'!RV14 | HB14: ='Investment Analysis'!RT14 | HD14: ='Investment Analysis'!SC14 | HE14: ='Investment Analysis'!SA14 | HG14: ='Investment Analysis'!SJ14 | HH14: ='Investment Analysis'!SH14 | HJ14: ='Investment Analysis'!SM14 | HK14: ='Investment Analysis'!SK14 | HM14: ='Investment Analysis'!SP14 | HN14: ='Investment Analysis'!SN14 | HP14: ='Investment Analysis'!TE14 | HQ14: ='Investment Analysis'!TC14 | HS14: ='Investment Analysis'!TL14 | HT14: ='Investment Analysis'!TJ14 | HV14: ='Investment Analysis'!TS14 | HW14: ='Investment Analysis'!TQ14 | HY14: ='Investment Analysis'!TZ14 | HZ14: ='Investment Analysis'!TX14 | IB14: ='Investment Analysis'!UG14 | IC14: ='Investment Analysis'!UE14 | IE14: ='Investment Analysis'!UN14 | IF14: ='Investment Analysis'!UL14 | IH14: ='Investment Analysis'!UU14 | II14: ='Investment Analysis'!US14 | IK14: ='Investment Analysis'!VB14 | IL14: ='Investment Analysis'!UZ14 | IN14: ='Investment Analysis'!VI14 | IO14: ='Investment Analysis'!VG14 | IS14: =IF(IT14>0,IT14-IT13,0) | IT14: =FY14+FV14+FS14+FP14+FM14+FJ14+FG14+FD14+FA14+EX14+EU14+ER14+EO14+EL14+EI14+EF14+EC14+DZ14+DW14+DT14+DQ14+DN14+DK14+DH14+DE14+DB14+CY14+CV14+CS14+CP14+CJ14+CG14+CD14+CA14+BX14+P14+CM14+GT14+GQ14+GN14+GK14+GH14+GE14+GB14+BU14+BR14+BO14+BL14+BI14+BF14+BC14+AZ14+AW14+AT14+AQ14+AN14+AK14+AH14+AE14+AB14+Y14+V14+S14+GW14+GZ14+HC14+HF14+HI14+HL14+HO14+HR14+HU14 | IU14: =IF(IT14>0,IV14,0) | IW14: =IF(IT14>0,(IT14+IV$11-I$2)/I$2,0) | IX14: =IF(IT14>0,IT14+IV$11-I$2,0) | IY14: =IF(IT14>0,(IT14+IV$11-IT$8)/IT$8,0) | IZ14: =IF(IT14>0,IT14+IV$11-IT$8,0)
A15: ='Investment Analysis'!A15 | B15: ='Investment Analysis'!B15 | C15: ='Investment Analysis'!C15 | D15: ='Investment Analysis'!D15 | E15: ='Investment Analysis'!E15 | F15: ='Investment Analysis'!G15 | G15: ='Investment Analysis'!H15 | H15: ='Investment Analysis'!I15 | I15: ='Investment Analysis'!K15 | J15: ='Investment Analysis'!L15 | K15: ='Investment Analysis'!M15 | L15: ='Investment Analysis'!T15 | M15: ='Investment Analysis'!V15 | N15: ='Investment Analysis'!W15 | P15: ='Investment Analysis'!Y15 | S15: 22686.39 | T15: =IF(S15>0,(S15-T$5)/T$5,0) | U15: ='Investment Analysis'!AF15 | V15: 17923.85 | W15: =IF(V15>0,(V15-W$5)/W$5,0) | X15: ='Investment Analysis'!AT15 | Y15: 9963.46 | Z15: =IF(Y15>0,(Y15-Z$5)/Z$5,0) | AA15: ='Investment Analysis'!GK15 | AB15: 2690.52 | AC15: =IF(AB15>0,(AB15-AC$5)/AC$5,0) | AD15: ='Investment Analysis'!AT15 | AE15: 22414.77 | AF15: =IF(AE15>0,(AE15-AF$5)/AF$5,0) | AG15: ='Investment Analysis'!BA15 | AI15: =IF(AH15>0,(AH15-AI$5)/AI$5,0) | AJ15: ='Investment Analysis'!BH15 | AK15: 19020.54 | AL15: =IF(AK15>0,(AK15-AL$5)/AL$5,0) | AM15: ='Investment Analysis'!BO15 | AN15: 14923.66 | AO15: =IF(AN15>0,(AN15-AO$5)/AO$5,0) | AP15: ='Investment Analysis'!BV15 | AR15: =IF(AQ15>0,(AQ15-AR$5)/AR$5,0) | AS15: ='Investment Analysis'!CC15 | AT15: 27456.94 | AU15: =IF(AT15>0,(AT15-AU$5)/AU$5,0) | AV15: ='Investment Analysis'!CJ15 | AW15: 19410.97 | AX15: =IF(AW15>0,(AW15-AX$5)/AX$5,0) | AY15: ='Investment Analysis'!CQ15 | AZ15: 16861.43 | BA15: =IF(AZ15>0,(AZ15-BA$5)/BA$5,0) | BB15: ='Investment Analysis'!CX15 | BC15: 10073.23 | BD15: =IF(BC15>0,(BC15-BD$5)/BD$5,0) | BE15: ='Investment Analysis'!DE15 | BF15: 4221.29 | BG15: =IF(BF15>0,(BF15-BG$5)/BG$5,0) | BH15: ='Investment Analysis'!DL15 | BI15: 2631.17 | BJ15: =IF(BI15>0,(BI15-BJ$5)/BJ$5,0) | BK15: ='Investment Analysis'!DZ15 | BL15: 4433.67 | BM15: =IF(BL15>0,(BL15-BM$5)/BM$5,0) | BN15: ='Investment Analysis'!EG15 | BP15: =IF(BO15>0,(BO15-BP$5)/BP$5,0) | BQ15: ='Investment Analysis'!DS15 | BR15: 5736.21 | BS15: =IF(BR15>0,(BR15-BS$5)/BS$5,0) | BT15: ='Investment Analysis'!EN15 | BU15: 14792.22 | BV15: =IF(BU15>0,(BU15-BV$5)/BV$5,0) | BW15: ='Investment Analysis'!EU15 | BY15: =IF(BX15>0,(BX15-BY$5)/BY$5,0) | BZ15: ='Investment Analysis'!FB15 | CA15: 3276.84 | CB15: =IF(CA15>0,(CA15-CB$5)/CB$5,0) | CC15: ='Investment Analysis'!FI15 | CD15: 19038.16 | CE15: =IF(CD15>0,(CD15-CE$5)/CE$5,0) | CF15: ='Investment Analysis'!FP15 | CG15: 5030.98 | CH15: =IF(CG15>0,(CG15-CH$5)/CH$5,0) | CI15: ='Investment Analysis'!FW15 | CK15: =IF(CJ15>0,(CJ15-CK$5)/CK$5,0) | CL15: ='Investment Analysis'!GD15 | CM15: 4979.32 | CN15: =IF(CM15>0,(CM15-CN$5)/CN$5,0) | CO15: ='Investment Analysis'!GT15 | CP15: 59241 | CQ15: =IF(CP15>0,(CP15-CQ$5)/CQ$5,0) | CR15: ='Investment Analysis'!HG15 | CS15: 6900 | CT15: =IF(CS15>0,(CS15-CT$5)/CT$5,0) | CU15: ='Investment Analysis'!HN15 | CV15: 21016.5 | CW15: =IF(CV15>0,(CV15-CW$5)/CW$5,0) | CX15: ='Investment Analysis'!IB15 | CY15: 22931 | CZ15: =IF(CY15>0,(CY15-CZ$5)/CZ$5,0) | DA15: ='Investment Analysis'!II15 | DB15: 21945.6 | DC15: =IF(DB15>0,(DB15-DC$5)/DC$5,0) | DD15: ='Investment Analysis'!IP15 | DF15: =IF(DE15>0,(DE15-DF$5)/DF$5,0) | DG15: ='Investment Analysis'!IW15 | DH15: 12214.4 | DI15: =IF(DH15>0,(DH15-DI$5)/DI$5,0) | DJ15: ='Investment Analysis'!JD15 | DK15: 2122.8 | DL15: =IF(DK15>0,(DK15-DL$5)/DL$5,0) | DM15: ='Investment Analysis'!JK15 | DN15: 5346.5 | DO15: =IF(DN15>0,(DN15-DO$5)/DO$5,0) | DP15: ='Investment Analysis'!HU15 | DQ15: 28812 | DR15: =IF(DQ15>0,(DQ15-DR$5)/DR$5,0) | DS15: ='Investment Analysis'!JR15 | DT15: 3936 | DU15: =IF(DT15>0,(DT15-DU$5)/DU$5,0) | DV15: ='Investment Analysis'!JY15 | DW15: 23184.25 | DX15: =IF(DW15>0,(DW15-DX$5)/DX$5,0) | DY15: ='Investment Analysis'!KF15 | DZ15: 2319.6 | EA15: =IF(DZ15>0,(DZ15-EA$5)/EA$5,0) | EB15: ='Investment Analysis'!KM15 | EC15: 2427 | ED15: =IF(EC15>0,(EC15-ED$5)/ED$5,0) | EE15: ='Investment Analysis'!KT15 | EF15: 36750 | EG15: =IF(EF15>0,(EF15-EG$5)/EG$5,0) | EH15: ='Investment Analysis'!LH15 | EI15: 7752.48 | EJ15: =IF(EI15>0,(EI15-EJ$5)/EJ$5,0) | EK15: ='Investment Analysis'!LO15 | EM15: =IF(EL15>0,(EL15-EM$5)/EM$5,0) | EN15: ='Investment Analysis'!LV15 | EP15: =IF(EO15>0,(EO15-EP$5)/EP$5,0) | EQ15: ='Investment Analysis'!MC15 | ER15: 24128.84 | ES15: =IF(ER15>0,(ER15-ES$5)/ES$5,0) | ET15: ='Investment Analysis'!LA15 | EU15: 36568 | EV15: ='Investment Analysis'!ML15 | EW15: ='Investment Analysis'!MJ15 | EX15: 40085.5 | EY15: =IF(EX15>0,(EX15-EY$5)/EY$5,0) | EZ15: ='Investment Analysis'!MQ15 | FB15: =IF(FA15>0,(FA15-FB$5)/FB$5,0) | FC15: ='Investment Analysis'!MX15 | FD15: 4322.25 | FE15: =IF(FD15>0,(FD15-FE$5)/FE$5,0) | FF15: ='Investment Analysis'!NE15 | FH15: =IF(FG15>0,(FG15-FH$5)/FH$5,0) | FI15: ='Investment Analysis'!NL15 | FJ15: 9162 | FK15: =IF(FJ15>0,(FJ15-FK$5)/FK$5,0) | FL15: ='Investment Analysis'!NS15 | FM15: 31032 | FN15: =IF(FM15>0,(FM15-FN$5)/FN$5,0) | FO15: ='Investment Analysis'!NZ15 | FQ15: =IF(FP15>0,(FP15-FQ$5)/FQ$5,0) | FR15: ='Investment Analysis'!OG15 | FS15: 34399.5 | FT15: =IF(FS15>0,(FS15-FT$5)/FT$5,0) | FU15: ='Investment Analysis'!ON15 | FW15: =IF(FV15>0,(FV15-FW$5)/FW$5,0) | FX15: ='Investment Analysis'!OU15 | FZ15: =IF(FY15>0,(FY15-FZ$5)/FZ$5,0) | GA15: ='Investment Analysis'!PB15 | GC15: ='Investment Analysis'!PK15 | GD15: ='Investment Analysis'!PI15 | GE15: 6812.5 | GF15: ='Investment Analysis'!PY15 | GG15: ='Investment Analysis'!PW15 | GH15: 32355 | GI15: ='Investment Analysis'!QF15 | GJ15: ='Investment Analysis'!QD15 | GK15: 24372 | GL15: ='Investment Analysis'!QM15 | GM15: ='Investment Analysis'!QK15 | GN15: 10207.52 | GO15: ='Investment Analysis'!QT15 | GP15: ='Investment Analysis'!QR15 | GQ15: 17053.95 | GR15: ='Investment Analysis'!RA15 | GS15: ='Investment Analysis'!QY15 | GT15: 16081 | GU15: ='Investment Analysis'!RH15 | GV15: ='Investment Analysis'!RF15 | GX15: ='Investment Analysis'!RO15 | GY15: ='Investment Analysis'!RM15 | HA15: ='Investment Analysis'!RV15 | HB15: ='Investment Analysis'!RT15 | HD15: ='Investment Analysis'!SC15 | HE15: ='Investment Analysis'!SA15 | HG15: ='Investment Analysis'!SJ15 | HH15: ='Investment Analysis'!SH15 | HJ15: ='Investment Analysis'!SM15 | HK15: ='Investment Analysis'!SK15 | HM15: ='Investment Analysis'!SP15 | HN15: ='Investment Analysis'!SN15 | HP15: ='Investment Analysis'!TE15 | HQ15: ='Investment Analysis'!TC15 | HS15: ='Investment Analysis'!TL15 | HT15: ='Investment Analysis'!TJ15 | HV15: ='Investment Analysis'!TS15 | HW15: ='Investment Analysis'!TQ15 | HY15: ='Investment Analysis'!TZ15 | HZ15: ='Investment Analysis'!TX15 | IB15: ='Investment Analysis'!UG15 | IC15: ='Investment Analysis'!UE15 | IE15: ='Investment Analysis'!UN15 | IF15: ='Investment Analysis'!UL15 | IH15: ='Investment Analysis'!UU15 | II15: ='Investment Analysis'!US15 | IK15: ='Investment Analysis'!VB15 | IL15: ='Investment Analysis'!UZ15 | IN15: ='Investment Analysis'!VI15 | IO15: ='Investment Analysis'!VG15 | IS15: =IF(IT15>0,IT15-IT14,0) | IT15: =FY15+FV15+FS15+FP15+FM15+FJ15+FG15+FD15+FA15+EX15+EU15+ER15+EO15+EL15+EI15+EF15+EC15+DZ15+DW15+DT15+DQ15+DN15+DK15+DH15+DE15+DB15+CY15+CV15+CS15+CP15+CJ15+CG15+CD15+CA15+BX15+P15+CM15+GT15+GQ15+GN15+GK15+GH15+GE15+GB15+BU15+BR15+BO15+BL15+BI15+BF15+BC15+AZ15+AW15+AT15+AQ15+AN15+AK15+AH15+AE15+AB15+Y15+V15+S15+GW15+GZ15+HC15+HF15+HI15+HL15+HO15+HR15+HU15 | IU15: =IF(IT15>0,IV15,0) | IW15: =IF(IT15>0,(IT15+IV$11-I$2)/I$2,0) | IX15: =IF(IT15>0,IT15+IV$11-I$2,0) | IY15: =IF(IT15>0,(IT15+IV$11-IT$8)/IT$8,0) | IZ15: =IF(IT15>0,IT15+IV$11-IT$8,0)
A16: ='Investment Analysis'!A16 | B16: ='Investment Analysis'!B16 | C16: ='Investment Analysis'!C16 | D16: ='Investment Analysis'!D16 | E16: ='Investment Analysis'!E16 | F16: ='Investment Analysis'!G16 | G16: ='Investment Analysis'!H16 | H16: ='Investment Analysis'!I16 | I16: ='Investment Analysis'!K16 | J16: ='Investment Analysis'!L16 | K16: ='Investment Analysis'!M16 | L16: ='Investment Analysis'!T16 | M16: ='Investment Analysis'!V16 | N16: ='Investment Analysis'!W16 | P16: ='Investment Analysis'!Y16 | S16: 22369.2 | T16: =IF(S16>0,(S16-T$5)/T$5,0) | U16: ='Investment Analysis'!AF16 | V16: 17731.48 | W16: =IF(V16>0,(V16-W$5)/W$5,0) | X16: ='Investment Analysis'!AT16 | Y16: 9685.68 | Z16: =IF(Y16>0,(Y16-Z$5)/Z$5,0) | AA16: ='Investment Analysis'!GK16 | AB16: 2647.42 | AC16: =IF(AB16>0,(AB16-AC$5)/AC$5,0) | AD16: ='Investment Analysis'!AT16 | AE16: 22073.38 | AF16: =IF(AE16>0,(AE16-AF$5)/AF$5,0) | AG16: ='Investment Analysis'!BA16 | AI16: =IF(AH16>0,(AH16-AI$5)/AI$5,0) | AJ16: ='Investment Analysis'!BH16 | AK16: 18732.95 | AL16: =IF(AK16>0,(AK16-AL$5)/AL$5,0) | AM16: ='Investment Analysis'!BO16 | AN16: 14783.05 | AO16: =IF(AN16>0,(AN16-AO$5)/AO$5,0) | AP16: ='Investment Analysis'!BV16 | AR16: =IF(AQ16>0,(AQ16-AR$5)/AR$5,0) | AS16: ='Investment Analysis'!CC16 | AT16: 27047.84 | AU16: =IF(AT16>0,(AT16-AU$5)/AU$5,0) | AV16: ='Investment Analysis'!CJ16 | AW16: 19057 | AX16: =IF(AW16>0,(AW16-AX$5)/AX$5,0) | AY16: ='Investment Analysis'!CQ16 | AZ16: 16583.54 | BA16: =IF(AZ16>0,(AZ16-BA$5)/BA$5,0) | BB16: ='Investment Analysis'!CX16 | BC16: 9901.83 | BD16: =IF(BC16>0,(BC16-BD$5)/BD$5,0) | BE16: ='Investment Analysis'!DE16 | BF16: 4162.99 | BG16: =IF(BF16>0,(BF16-BG$5)/BG$5,0) | BH16: ='Investment Analysis'!DL16 | BI16: 2567.54 | BJ16: =IF(BI16>0,(BI16-BJ$5)/BJ$5,0) | BK16: ='Investment Analysis'!DZ16 | BL16: 4337.69 | BM16: =IF(BL16>0,(BL16-BM$5)/BM$5,0) | BN16: ='Investment Analysis'!EG16 | BP16: =IF(BO16>0,(BO16-BP$5)/BP$5,0) | BQ16: ='Investment Analysis'!DS16 | BR16: 5685.73 | BS16: =IF(BR16>0,(BR16-BS$5)/BS$5,0) | BT16: ='Investment Analysis'!EN16 | BU16: 14299.02 | BV16: =IF(BU16>0,(BU16-BV$5)/BV$5,0) | BW16: ='Investment Analysis'!EU16 | BY16: =IF(BX16>0,(BX16-BY$5)/BY$5,0) | BZ16: ='Investment Analysis'!FB16 | CA16: 3285.79 | CB16: =IF(CA16>0,(CA16-CB$5)/CB$5,0) | CC16: ='Investment Analysis'!FI16 | CD16: 18431.68 | CE16: =IF(CD16>0,(CD16-CE$5)/CE$5,0) | CF16: ='Investment Analysis'!FP16 | CG16: 4909.66 | CH16: =IF(CG16>0,(CG16-CH$5)/CH$5,0) | CI16: ='Investment Analysis'!FW16 | CK16: =IF(CJ16>0,(CJ16-CK$5)/CK$5,0) | CL16: ='Investment Analysis'!GD16 | CM16: 4914.84 | CN16: =IF(CM16>0,(CM16-CN$5)/CN$5,0) | CO16: ='Investment Analysis'!GT16 | CP16: 59211 | CQ16: =IF(CP16>0,(CP16-CQ$5)/CQ$5,0) | CR16: ='Investment Analysis'!HG16 | CS16: 6810 | CT16: =IF(CS16>0,(CS16-CT$5)/CT$5,0) | CU16: ='Investment Analysis'!HN16 | CV16: 20386.5 | CW16: =IF(CV16>0,(CV16-CW$5)/CW$5,0) | CX16: ='Investment Analysis'!IB16 | CY16: 22431 | CZ16: =IF(CY16>0,(CY16-CZ$5)/CZ$5,0) | DA16: ='Investment Analysis'!II16 | DB16: 0 | DC16: =IF(DB16>0,(DB16-DC$5)/DC$5,0) | DD16: ='Investment Analysis'!IP16 | DF16: =IF(DE16>0,(DE16-DF$5)/DF$5,0) | DG16: ='Investment Analysis'!IW16 | DH16: 12317.2 | DI16: =IF(DH16>0,(DH16-DI$5)/DI$5,0) | DJ16: ='Investment Analysis'!JD16 | DK16: 2094.75 | DL16: =IF(DK16>0,(DK16-DL$5)/DL$5,0) | DM16: ='Investment Analysis'!JK16 | DN16: 5327 | DO16: =IF(DN16>0,(DN16-DO$5)/DO$5,0) | DP16: ='Investment Analysis'!HU16 | DQ16: 28368 | DR16: =IF(DQ16>0,(DQ16-DR$5)/DR$5,0) | DS16: ='Investment Analysis'!JR16 | DT16: 4026 | DU16: =IF(DT16>0,(DT16-DU$5)/DU$5,0) | DV16: ='Investment Analysis'!JY16 | DW16: 23423.5 | DX16: =IF(DW16>0,(DW16-DX$5)/DX$5,0) | DY16: ='Investment Analysis'!KF16 | DZ16: 2341.2 | EA16: =IF(DZ16>0,(DZ16-EA$5)/EA$5,0) | EB16: ='Investment Analysis'!KM16 | EC16: 2368.5 | ED16: =IF(EC16>0,(EC16-ED$5)/ED$5,0) | EE16: ='Investment Analysis'!KT16 | EF16: 36750 | EG16: =IF(EF16>0,(EF16-EG$5)/EG$5,0) | EH16: ='Investment Analysis'!LH16 | EI16: 7839.9 | EJ16: =IF(EI16>0,(EI16-EJ$5)/EJ$5,0) | EK16: ='Investment Analysis'!LO16 | EM16: =IF(EL16>0,(EL16-EM$5)/EM$5,0) | EN16: ='Investment Analysis'!LV16 | EP16: =IF(EO16>0,(EO16-EP$5)/EP$5,0) | EQ16: ='Investment Analysis'!MC16 | ER16: 23565.11 | ES16: =IF(ER16>0,(ER16-ES$5)/ES$5,0) | ET16: ='Investment Analysis'!LA16 | EU16: 35336 | EV16: ='Investment Analysis'!ML16 | EW16: ='Investment Analysis'!MJ16 | EX16: 40141.5 | EY16: =IF(EX16>0,(EX16-EY$5)/EY$5,0) | EZ16: ='Investment Analysis'!MQ16 | FB16: =IF(FA16>0,(FA16-FB$5)/FB$5,0) | FC16: ='Investment Analysis'!MX16 | FD16: 4292.25 | FE16: =IF(FD16>0,(FD16-FE$5)/FE$5,0) | FF16: ='Investment Analysis'!NE16 | FH16: =IF(FG16>0,(FG16-FH$5)/FH$5,0) | FI16: ='Investment Analysis'!NL16 | FJ16: 9177.5 | FK16: =IF(FJ16>0,(FJ16-FK$5)/FK$5,0) | FL16: ='Investment Analysis'!NS16 | FM16: 30726.4 | FN16: =IF(FM16>0,(FM16-FN$5)/FN$5,0) | FO16: ='Investment Analysis'!NZ16 | FQ16: =IF(FP16>0,(FP16-FQ$5)/FQ$5,0) | FR16: ='Investment Analysis'!OG16 | FS16: 33644.25 | FT16: =IF(FS16>0,(FS16-FT$5)/FT$5,0) | FU16: ='Investment Analysis'!ON16 | FW16: =IF(FV16>0,(FV16-FW$5)/FW$5,0) | FX16: ='Investment Analysis'!OU16 | FZ16: =IF(FY16>0,(FY16-FZ$5)/FZ$5,0) | GA16: ='Investment Analysis'!PB16 | GC16: ='Investment Analysis'!PK16 | GD16: ='Investment Analysis'!PI16 | GE16: 6734 | GF16: ='Investment Analysis'!PY16 | GG16: ='Investment Analysis'!PW16 | GH16: 31790 | GI16: ='Investment Analysis'!QF16 | GJ16: ='Investment Analysis'!QD16 | GK16: 23430 | GL16: ='Investment Analysis'!QM16 | GM16: ='Investment Analysis'!QK16 | GN16: 10407.44 | GO16: ='Investment Analysis'!QT16 | GP16: ='Investment Analysis'!QR16 | GQ16: 16865.15 | GR16: ='Investment Analysis'!RA16 | GS16: ='Investment Analysis'!QY16 | GT16: 16673 | GU16: ='Investment Analysis'!RH16 | GV16: ='Investment Analysis'!RF16 | GX16: ='Investment Analysis'!RO16 | GY16: ='Investment Analysis'!RM16 | HA16: ='Investment Analysis'!RV16 | HB16: ='Investment Analysis'!RT16 | HD16: ='Investment Analysis'!SC16 | HE16: ='Investment Analysis'!SA16 | HG16: ='Investment Analysis'!SJ16 | HH16: ='Investment Analysis'!SH16 | HJ16: ='Investment Analysis'!SM16 | HK16: ='Investment Analysis'!SK16 | HM16: ='Investment Analysis'!SP16 | HN16: ='Investment Analysis'!SN16 | HP16: ='Investment Analysis'!TE16 | HQ16: ='Investment Analysis'!TC16 | HS16: ='Investment Analysis'!TL16 | HT16: ='Investment Analysis'!TJ16 | HV16: ='Investment Analysis'!TS16 | HW16: ='Investment Analysis'!TQ16 | HY16: ='Investment Analysis'!TZ16 | HZ16: ='Investment Analysis'!TX16 | IB16: ='Investment Analysis'!UG16 | IC16: ='Investment Analysis'!UE16 | IE16: ='Investment Analysis'!UN16 | IF16: ='Investment Analysis'!UL16 | IH16: ='Investment Analysis'!UU16 | II16: ='Investment Analysis'!US16 | IK16: ='Investment Analysis'!VB16 | IL16: ='Investment Analysis'!UZ16 | IN16: ='Investment Analysis'!VI16 | IO16: ='Investment Analysis'!VG16 | IS16: =IF(IT16>0,IT16-IT15,0) | IT16: =FY16+FV16+FS16+FP16+FM16+FJ16+FG16+FD16+FA16+EX16+EU16+ER16+EO16+EL16+EI16+EF16+EC16+DZ16+DW16+DT16+DQ16+DN16+DK16+DH16+DE16+DB16+CY16+CV16+CS16+CP16+CJ16+CG16+CD16+CA16+BX16+P16+CM16+GT16+GQ16+GN16+GK16+GH16+GE16+GB16+BU16+BR16+BO16+BL16+BI16+BF16+BC16+AZ16+AW16+AT16+AQ16+AN16+AK16+AH16+AE16+AB16+Y16+V16+S16+GW16+GZ16+HC16+HF16+HI16+HL16+HO16+HR16+HU16 | IU16: =IF(IT16>0,IV16,0) | IW16: =IF(IT16>0,(IT16+IV$11-I$2)/I$2,0) | IX16: =IF(IT16>0,IT16+IV$11-I$2,0) | IY16: =IF(IT16>0,(IT16+IV$11-IT$8)/IT$8,0) | IZ16: =IF(IT16>0,IT16+IV$11-IT$8,0)
A17: ='Investment Analysis'!A17 | B17: ='Investment Analysis'!B17 | C17: ='Investment Analysis'!C17 | D17: ='Investment Analysis'!D17 | E17: ='Investment Analysis'!E17 | F17: ='Investment Analysis'!G17 | G17: ='Investment Analysis'!H17 | H17: ='Investment Analysis'!I17 | I17: ='Investment Analysis'!K17 | J17: ='Investment Analysis'!L17 | K17: ='Investment Analysis'!M17 | L17: ='Investment Analysis'!T17 | M17: ='Investment Analysis'!V17 | N17: ='Investment Analysis'!W17 | P17: ='Investment Analysis'!Y17 | S17: 22216.99 | T17: =IF(S17>0,(S17-T$5)/T$5,0) | U17: ='Investment Analysis'!AF17 | V17: 17656.21 | W17: =IF(V17>0,(V17-W$5)/W$5,0) | X17: ='Investment Analysis'!AT17 | Y17: 9722.37 | Z17: =IF(Y17>0,(Y17-Z$5)/Z$5,0) | AA17: ='Investment Analysis'!GK17 | AB17: 2632.64 | AC17: =IF(AB17>0,(AB17-AC$5)/AC$5,0) | AD17: ='Investment Analysis'!AT17 | AE17: 22108.28 | AF17: =IF(AE17>0,(AE17-AF$5)/AF$5,0) | AG17: ='Investment Analysis'!BA17 | AI17: =IF(AH17>0,(AH17-AI$5)/AI$5,0) | AJ17: ='Investment Analysis'!BH17 | AK17: 18727.31 | AL17: =IF(AK17>0,(AK17-AL$5)/AL$5,0) | AM17: ='Investment Analysis'!BO17 | AN17: 14676.64 | AO17: =IF(AN17>0,(AN17-AO$5)/AO$5,0) | AP17: ='Investment Analysis'!BV17 | AR17: =IF(AQ17>0,(AQ17-AR$5)/AR$5,0) | AS17: ='Investment Analysis'!CC17 | AT17: 27228.79 | AU17: =IF(AT17>0,(AT17-AU$5)/AU$5,0) | AV17: ='Investment Analysis'!CJ17 | AW17: 18959.95 | AX17: =IF(AW17>0,(AW17-AX$5)/AX$5,0) | AY17: ='Investment Analysis'!CQ17 | AZ17: 16601.47 | BA17: =IF(AZ17>0,(AZ17-BA$5)/BA$5,0) | BB17: ='Investment Analysis'!CX17 | BC17: 9970.39 | BD17: =IF(BC17>0,(BC17-BD$5)/BD$5,0) | BE17: ='Investment Analysis'!DE17 | BF17: 4136.31 | BG17: =IF(BF17>0,(BF17-BG$5)/BG$5,0) | BH17: ='Investment Analysis'!DL17 | BI17: 2544.05 | BJ17: =IF(BI17>0,(BI17-BJ$5)/BJ$5,0) | BK17: ='Investment Analysis'!DZ17 | BL17: 4308.07 | BM17: =IF(BL17>0,(BL17-BM$5)/BM$5,0) | BN17: ='Investment Analysis'!EG17 | BP17: =IF(BO17>0,(BO17-BP$5)/BP$5,0) | BQ17: ='Investment Analysis'!DS17 | BR17: 5655.94 | BS17: =IF(BR17>0,(BR17-BS$5)/BS$5,0) | BT17: ='Investment Analysis'!EN17 | BU17: 14230.73 | BV17: =IF(BU17>0,(BU17-BV$5)/BV$5,0) | BW17: ='Investment Analysis'!EU17 | BY17: =IF(BX17>0,(BX17-BY$5)/BY$5,0) | BZ17: ='Investment Analysis'!FB17 | CA17: 3335.59 | CB17: =IF(CA17>0,(CA17-CB$5)/CB$5,0) | CC17: ='Investment Analysis'!FI17 | CD17: 18409.83 | CE17: =IF(CD17>0,(CD17-CE$5)/CE$5,0) | CF17: ='Investment Analysis'!FP17 | CG17: 4943.76 | CH17: =IF(CG17>0,(CG17-CH$5)/CH$5,0) | CI17: ='Investment Analysis'!FW17 | CK17: =IF(CJ17>0,(CJ17-CK$5)/CK$5,0) | CL17: ='Investment Analysis'!GD17 | CM17: 4911.26 | CN17: =IF(CM17>0,(CM17-CN$5)/CN$5,0) | CO17: ='Investment Analysis'!GT17 | CP17: 60496.5 | CQ17: =IF(CP17>0,(CP17-CQ$5)/CQ$5,0) | CR17: ='Investment Analysis'!HG17 | CS17: 6840 | CT17: =IF(CS17>0,(CS17-CT$5)/CT$5,0) | CU17: ='Investment Analysis'!HN17 | CV17: 19984.5 | CW17: =IF(CV17>0,(CV17-CW$5)/CW$5,0) | CX17: ='Investment Analysis'!IB17 | CY17: 22529 | CZ17: =IF(CY17>0,(CY17-CZ$5)/CZ$5,0) | DA17: ='Investment Analysis'!II17 | DC17: =IF(DB17>0,(DB17-DC$5)/DC$5,0) | DD17: ='Investment Analysis'!IP17 | DF17: =IF(DE17>0,(DE17-DF$5)/DF$5,0) | DG17: ='Investment Analysis'!IW17 | DH17: 12166.6 | DI17: =IF(DH17>0,(DH17-DI$5)/DI$5,0) | DJ17: ='Investment Analysis'!JD17 | DK17: 2085.95 | DL17: =IF(DK17>0,(DK17-DL$5)/DL$5,0) | DM17: ='Investment Analysis'!JK17 | DN17: 5464.5 | DO17: =IF(DN17>0,(DN17-DO$5)/DO$5,0) | DP17: ='Investment Analysis'!HU17 | DQ17: 28149 | DR17: =IF(DQ17>0,(DQ17-DR$5)/DR$5,0) | DS17: ='Investment Analysis'!JR17 | DT17: 3760 | DU17: =IF(DT17>0,(DT17-DU$5)/DU$5,0) | DV17: ='Investment Analysis'!JY17 | DW17: 23117.5 | DX17: =IF(DW17>0,(DW17-DX$5)/DX$5,0) | DY17: ='Investment Analysis'!KF17 | DZ17: 2299.2 | EA17: =IF(DZ17>0,(DZ17-EA$5)/EA$5,0) | EB17: ='Investment Analysis'!KM17 | EC17: 2344 | ED17: =IF(EC17>0,(EC17-ED$5)/ED$5,0) | EE17: ='Investment Analysis'!KT17 | EF17: 37560 | EG17: =IF(EF17>0,(EF17-EG$5)/EG$5,0) | EH17: ='Investment Analysis'!LH17 | EI17: 7659.48 | EJ17: =IF(EI17>0,(EI17-EJ$5)/EJ$5,0) | EK17: ='Investment Analysis'!LO17 | EM17: =IF(EL17>0,(EL17-EM$5)/EM$5,0) | EN17: ='Investment Analysis'!LV17 | EP17: =IF(EO17>0,(EO17-EP$5)/EP$5,0) | EQ17: ='Investment Analysis'!MC17 | ER17: 23362.02 | ES17: =IF(ER17>0,(ER17-ES$5)/ES$5,0) | ET17: ='Investment Analysis'!LA17 | EU17: 32032 | EV17: ='Investment Analysis'!ML17 | EW17: ='Investment Analysis'!MJ17 | EX17: 40089 | EY17: =IF(EX17>0,(EX17-EY$5)/EY$5,0) | EZ17: ='Investment Analysis'!MQ17 | FB17: =IF(FA17>0,(FA17-FB$5)/FB$5,0) | FC17: ='Investment Analysis'!MX17 | FD17: 4289.25 | FE17: =IF(FD17>0,(FD17-FE$5)/FE$5,0) | FF17: ='Investment Analysis'!NE17 | FH17: =IF(FG17>0,(FG17-FH$5)/FH$5,0) | FI17: ='Investment Analysis'!NL17 | FJ17: 9170.25 | FK17: =IF(FJ17>0,(FJ17-FK$5)/FK$5,0) | FL17: ='Investment Analysis'!NS17 | FM17: 30561.6 | FN17: =IF(FM17>0,(FM17-FN$5)/FN$5,0) | FO17: ='Investment Analysis'!NZ17 | FQ17: =IF(FP17>0,(FP17-FQ$5)/FQ$5,0) | FR17: ='Investment Analysis'!OG17 | FS17: 33136 | FT17: =IF(FS17>0,(FS17-FT$5)/FT$5,0) | FU17: ='Investment Analysis'!ON17 | FW17: =IF(FV17>0,(FV17-FW$5)/FW$5,0) | FX17: ='Investment Analysis'!OU17 | FZ17: =IF(FY17>0,(FY17-FZ$5)/FZ$5,0) | GA17: ='Investment Analysis'!PB17 | GC17: ='Investment Analysis'!PK17 | GD17: ='Investment Analysis'!PI17 | GE17: 6701.5 | GF17: ='Investment Analysis'!PY17 | GG17: ='Investment Analysis'!PW17 | GH17: 31895 | GI17: ='Investment Analysis'!QF17 | GJ17: ='Investment Analysis'!QD17 | GK17: 23510 | GL17: ='Investment Analysis'!QM17 | GM17: ='Investment Analysis'!QK17 | GN17: 10404.56 | GO17: ='Investment Analysis'!QT17 | GP17: ='Investment Analysis'!QR17 | GQ17: 16446.25 | GR17: ='Investment Analysis'!RA17 | GS17: ='Investment Analysis'!QY17 | GT17: 16213 | GU17: ='Investment Analysis'!RH17 | GV17: ='Investment Analysis'!RF17 | GX17: ='Investment Analysis'!RO17 | GY17: ='Investment Analysis'!RM17 | HA17: ='Investment Analysis'!RV17 | HB17: ='Investment Analysis'!RT17 | HD17: ='Investment Analysis'!SC17 | HE17: ='Investment Analysis'!SA17 | HG17: ='Investment Analysis'!SJ17 | HH17: ='Investment Analysis'!SH17 | HJ17: ='Investment Analysis'!SM17 | HK17: ='Investment Analysis'!SK17 | HM17: ='Investment Analysis'!SP17 | HN17: ='Investment Analysis'!SN17 | HP17: ='Investment Analysis'!TE17 | HQ17: ='Investment Analysis'!TC17 | HS17: ='Investment Analysis'!TL17 | HT17: ='Investment Analysis'!TJ17 | HV17: ='Investment Analysis'!TS17 | HW17: ='Investment Analysis'!TQ17 | HY17: ='Investment Analysis'!TZ17 | HZ17: ='Investment Analysis'!TX17 | IB17: ='Investment Analysis'!UG17 | IC17: ='Investment Analysis'!UE17 | IE17: ='Investment Analysis'!UN17 | IF17: ='Investment Analysis'!UL17 | IH17: ='Investment Analysis'!UU17 | II17: ='Investment Analysis'!US17 | IK17: ='Investment Analysis'!VB17 | IL17: ='Investment Analysis'!UZ17 | IN17: ='Investment Analysis'!VI17 | IO17: ='Investment Analysis'!VG17 | IS17: =IF(IT17>0,IT17-IT16,0) | IT17: =FY17+FV17+FS17+FP17+FM17+FJ17+FG17+FD17+FA17+EX17+EU17+ER17+EO17+EL17+EI17+EF17+EC17+DZ17+DW17+DT17+DQ17+DN17+DK17+DH17+DE17+DB17+CY17+CV17+CS17+CP17+CJ17+CG17+CD17+CA17+BX17+P17+CM17+GT17+GQ17+GN17+GK17+GH17+GE17+GB17+BU17+BR17+BO17+BL17+BI17+BF17+BC17+AZ17+AW17+AT17+AQ17+AN17+AK17+AH17+AE17+AB17+Y17+V17+S17+GW17+GZ17+HC17+HF17+HI17+HL17+HO17+HR17+HU17 | IU17: =IF(IT17>0,IV17,0) | IW17: =IF(IT17>0,(IT17+IV$11-I$2)/I$2,0) | IX17: =IF(IT17>0,IT17+IV$11-I$2,0) | IY17: =IF(IT17>0,(IT17+IV$11-IT$8)/IT$8,0) | IZ17: =IF(IT17>0,IT17+IV$11-IT$8,0)
A18: ='Investment Analysis'!A18 | B18: ='Investment Analysis'!B18 | C18: ='Investment Analysis'!C18 | D18: ='Investment Analysis'!D18 | E18: ='Investment Analysis'!E18 | F18: ='Investment Analysis'!G18 | G18: ='Investment Analysis'!H18 | H18: ='Investment Analysis'!I18 | I18: ='Investment Analysis'!K18 | J18: ='Investment Analysis'!L18 | K18: ='Investment Analysis'!M18 | L18: ='Investment Analysis'!T18 | M18: ='Investment Analysis'!V18 | N18: ='Investment Analysis'!W18 | P18: ='Investment Analysis'!Y18 | S18: 22090.31 | T18: =IF(S18>0,(S18-T$5)/T$5,0) | U18: ='Investment Analysis'!AF18 | V18: 17597.66 | W18: =IF(V18>0,(V18-W$5)/W$5,0) | X18: ='Investment Analysis'!AT18 | Y18: 9528.44 | Z18: =IF(Y18>0,(Y18-Z$5)/Z$5,0) | AA18: ='Investment Analysis'!GK18 | AB18: 2619.1 | AC18: =IF(AB18>0,(AB18-AC$5)/AC$5,0) | AD18: ='Investment Analysis'!AT18 | AE18: 22133.37 | AF18: =IF(AE18>0,(AE18-AF$5)/AF$5,0) | AG18: ='Investment Analysis'!BA18 | AI18: =IF(AH18>0,(AH18-AI$5)/AI$5,0) | AJ18: ='Investment Analysis'!BH18 | AK18: 19043.1 | AL18: =IF(AK18>0,(AK18-AL$5)/AL$5,0) | AM18: ='Investment Analysis'!BO18 | AN18: 14840.05 | AO18: =IF(AN18>0,(AN18-AO$5)/AO$5,0) | AP18: ='Investment Analysis'!BV18 | AR18: =IF(AQ18>0,(AQ18-AR$5)/AR$5,0) | AS18: ='Investment Analysis'!CC18 | AT18: 27370.4 | AU18: =IF(AT18>0,(AT18-AU$5)/AU$5,0) | AV18: ='Investment Analysis'!CJ18 | AW18: 19108.39 | AX18: =IF(AW18>0,(AW18-AX$5)/AX$5,0) | AY18: ='Investment Analysis'!CQ18 | AZ18: 16816.61 | BA18: =IF(AZ18>0,(AZ18-BA$5)/BA$5,0) | BB18: ='Investment Analysis'!CX18 | BC18: 10107.51 | BD18: =IF(BC18>0,(BC18-BD$5)/BD$5,0) | BE18: ='Investment Analysis'!DE18 | BF18: 4157.06 | BG18: =IF(BF18>0,(BF18-BG$5)/BG$5,0) | BH18: ='Investment Analysis'!DL18 | BI18: 2550.11 | BJ18: =IF(BI18>0,(BI18-BJ$5)/BJ$5,0) | BK18: ='Investment Analysis'!DZ18 | BL18: 4306.89 | BM18: =IF(BL18>0,(BL18-BM$5)/BM$5,0) | BN18: ='Investment Analysis'!EG18 | BP18: =IF(BO18>0,(BO18-BP$5)/BP$5,0) | BQ18: ='Investment Analysis'!DS18 | BR18: 5607.98 | BS18: =IF(BR18>0,(BR18-BS$5)/BS$5,0) | BT18: ='Investment Analysis'!EN18 | BU18: 14424.21 | BV18: =IF(BU18>0,(BU18-BV$5)/BV$5,0) | BW18: ='Investment Analysis'!EU18 | BY18: =IF(BX18>0,(BX18-BY$5)/BY$5,0) | BZ18: ='Investment Analysis'!FB18 | CA18: 3370.84 | CB18: =IF(CA18>0,(CA18-CB$5)/CB$5,0) | CC18: ='Investment Analysis'!FI18 | CD18: 18650.13 | CE18: =IF(CD18>0,(CD18-CE$5)/CE$5,0) | CF18: ='Investment Analysis'!FP18 | CG18: 5027.06 | CH18: =IF(CG18>0,(CG18-CH$5)/CH$5,0) | CI18: ='Investment Analysis'!FW18 | CK18: =IF(CJ18>0,(CJ18-CK$5)/CK$5,0) | CL18: ='Investment Analysis'!GD18 | CM18: 4979.32 | CN18: =IF(CM18>0,(CM18-CN$5)/CN$5,0) | CO18: ='Investment Analysis'!GT18 | CP18: 59454 | CQ18: =IF(CP18>0,(CP18-CQ$5)/CQ$5,0) | CR18: ='Investment Analysis'!HG18 | CS18: 6990 | CT18: =IF(CS18>0,(CS18-CT$5)/CT$5,0) | CU18: ='Investment Analysis'!HN18 | CV18: 19764 | CW18: =IF(CV18>0,(CV18-CW$5)/CW$5,0) | CX18: ='Investment Analysis'!IB18 | CY18: 22470 | CZ18: =IF(CY18>0,(CY18-CZ$5)/CZ$5,0) | DA18: ='Investment Analysis'!II18 | DC18: =IF(DB18>0,(DB18-DC$5)/DC$5,0) | DD18: ='Investment Analysis'!IP18 | DF18: =IF(DE18>0,(DE18-DF$5)/DF$5,0) | DG18: ='Investment Analysis'!IW18 | DH18: 11885 | DI18: =IF(DH18>0,(DH18-DI$5)/DI$5,0) | DJ18: ='Investment Analysis'!JD18 | DK18: 2078.35 | DL18: =IF(DK18>0,(DK18-DL$5)/DL$5,0) | DM18: ='Investment Analysis'!JK18 | DN18: 5486 | DO18: =IF(DN18>0,(DN18-DO$5)/DO$5,0) | DP18: ='Investment Analysis'!HU18 | DQ18: 27747 | DR18: =IF(DQ18>0,(DQ18-DR$5)/DR$5,0) | DS18: ='Investment Analysis'!JR18 | DT18: 3846 | DU18: =IF(DT18>0,(DT18-DU$5)/DU$5,0) | DV18: ='Investment Analysis'!JY18 | DW18: 22930.75 | DX18: =IF(DW18>0,(DW18-DX$5)/DX$5,0) | DY18: ='Investment Analysis'!KF18 | DZ18: 2346 | EA18: =IF(DZ18>0,(DZ18-EA$5)/EA$5,0) | EB18: ='Investment Analysis'!KM18 | EC18: 2332.8 | ED18: =IF(EC18>0,(EC18-ED$5)/ED$5,0) | EE18: ='Investment Analysis'!KT18 | EF18: 38017.5 | EG18: =IF(EF18>0,(EF18-EG$5)/EG$5,0) | EH18: ='Investment Analysis'!LH18 | EI18: 7806.42 | EJ18: =IF(EI18>0,(EI18-EJ$5)/EJ$5,0) | EK18: ='Investment Analysis'!LO18 | EM18: =IF(EL18>0,(EL18-EM$5)/EM$5,0) | EN18: ='Investment Analysis'!LV18 | EP18: =IF(EO18>0,(EO18-EP$5)/EP$5,0) | EQ18: ='Investment Analysis'!MC18 | ER18: 23719.67 | ES18: =IF(ER18>0,(ER18-ES$5)/ES$5,0) | ET18: ='Investment Analysis'!LA18 | EU18: 31934 | EV18: ='Investment Analysis'!ML18 | EW18: ='Investment Analysis'!MJ18 | EX18: 40988.5 | EY18: =IF(EX18>0,(EX18-EY$5)/EY$5,0) | EZ18: ='Investment Analysis'!MQ18 | FB18: =IF(FA18>0,(FA18-FB$5)/FB$5,0) | FC18: ='Investment Analysis'!MX18 | FD18: 4421.5 | FE18: =IF(FD18>0,(FD18-FE$5)/FE$5,0) | FF18: ='Investment Analysis'!NE18 | FH18: =IF(FG18>0,(FG18-FH$5)/FH$5,0) | FI18: ='Investment Analysis'!NL18 | FJ18: 9556.5 | FK18: =IF(FJ18>0,(FJ18-FK$5)/FK$5,0) | FL18: ='Investment Analysis'!NS18 | FM18: 30345.6 | FN18: =IF(FM18>0,(FM18-FN$5)/FN$5,0) | FO18: ='Investment Analysis'!NZ18 | FQ18: =IF(FP18>0,(FP18-FQ$5)/FQ$5,0) | FR18: ='Investment Analysis'!OG18 | FS18: 33183.5 | FT18: =IF(FS18>0,(FS18-FT$5)/FT$5,0) | FU18: ='Investment Analysis'!ON18 | FW18: =IF(FV18>0,(FV18-FW$5)/FW$5,0) | FX18: ='Investment Analysis'!OU18 | FZ18: =IF(FY18>0,(FY18-FZ$5)/FZ$5,0) | GA18: ='Investment Analysis'!PB18 | GC18: ='Investment Analysis'!PK18 | GD18: ='Investment Analysis'!PI18 | GE18: 6774 | GF18: ='Investment Analysis'!PY18 | GG18: ='Investment Analysis'!PW18 | GH18: 32263.75 | GI18: ='Investment Analysis'!QF18 | GJ18: ='Investment Analysis'!QD18 | GK18: 23694 | GL18: ='Investment Analysis'!QM18 | GM18: ='Investment Analysis'!QK18 | GN18: 10626.48 | GO18: ='Investment Analysis'!QT18 | GP18: ='Investment Analysis'!QR18 | GQ18: 16788.45 | GR18: ='Investment Analysis'!RA18 | GS18: ='Investment Analysis'!QY18 | GT18: 17051 | GU18: ='Investment Analysis'!RH18 | GV18: ='Investment Analysis'!RF18 | GX18: ='Investment Analysis'!RO18 | GY18: ='Investment Analysis'!RM18 | HA18: ='Investment Analysis'!RV18 | HB18: ='Investment Analysis'!RT18 | HD18: ='Investment Analysis'!SC18 | HE18: ='Investment Analysis'!SA18 | HG18: ='Investment Analysis'!SJ18 | HH18: ='Investment Analysis'!SH18 | HJ18: ='Investment Analysis'!SM18 | HK18: ='Investment Analysis'!SK18 | HM18: ='Investment Analysis'!SP18 | HN18: ='Investment Analysis'!SN18 | HP18: ='Investment Analysis'!TE18 | HQ18: ='Investment Analysis'!TC18 | HS18: ='Investment Analysis'!TL18 | HT18: ='Investment Analysis'!TJ18 | HV18: ='Investment Analysis'!TS18 | HW18: ='Investment Analysis'!TQ18 | HY18: ='Investment Analysis'!TZ18 | HZ18: ='Investment Analysis'!TX18 | IB18: ='Investment Analysis'!UG18 | IC18: ='Investment Analysis'!UE18 | IE18: ='Investment Analysis'!UN18 | IF18: ='Investment Analysis'!UL18 | IH18: ='Investment Analysis'!UU18 | II18: ='Investment Analysis'!US18 | IK18: ='Investment Analysis'!VB18 | IL18: ='Investment Analysis'!UZ18 | IN18: ='Investment Analysis'!VI18 | IO18: ='Investment Analysis'!VG18 | IS18: =IF(IT18>0,IT18-IT17,0) | IT18: =FY18+FV18+FS18+FP18+FM18+FJ18+FG18+FD18+FA18+EX18+EU18+ER18+EO18+EL18+EI18+EF18+EC18+DZ18+DW18+DT18+DQ18+DN18+DK18+DH18+DE18+DB18+CY18+CV18+CS18+CP18+CJ18+CG18+CD18+CA18+BX18+P18+CM18+GT18+GQ18+GN18+GK18+GH18+GE18+GB18+BU18+BR18+BO18+BL18+BI18+BF18+BC18+AZ18+AW18+AT18+AQ18+AN18+AK18+AH18+AE18+AB18+Y18+V18+S18+GW18+GZ18+HC18+HF18+HI18+HL18+HO18+HR18+HU18 | IU18: =IF(IT18>0,IV18,0) | IW18: =IF(IT18>0,(IT18+IV$11-I$2)/I$2,0) | IX18: =IF(IT18>0,IT18+IV$11-I$2,0) | IY18: =IF(IT18>0,(IT18+IV$11-IT$8)/IT$8,0) | IZ18: =IF(IT18>0,IT18+IV$11-IT$8,0)
A19: ='Investment Analysis'!A19 | B19: ='Investment Analysis'!B19 | C19: ='Investment Analysis'!C19 | D19: ='Investment Analysis'!D19 | E19: ='Investment Analysis'!E19 | F19: ='Investment Analysis'!G19 | G19: ='Investment Analysis'!H19 | H19: ='Investment Analysis'!I19 | I19: ='Investment Analysis'!K19 | J19: ='Investment Analysis'!L19 | K19: ='Investment Analysis'!M19 | L19: ='Investment Analysis'!T19 | M19: ='Investment Analysis'!V19 | N19: ='Investment Analysis'!W19 | P19: ='Investment Analysis'!Y19 | S19: 22598.99 | T19: =IF(S19>0,(S19-T$5)/T$5,0) | U19: ='Investment Analysis'!AF19 | V19: 17999.13 | W19: =IF(V19>0,(V19-W$5)/W$5,0) | X19: ='Investment Analysis'!AT19 | Y19: 9711.88 | Z19: =IF(Y19>0,(Y19-Z$5)/Z$5,0) | AA19: ='Investment Analysis'!GK19 | AB19: 2678.2 | AC19: =IF(AB19>0,(AB19-AC$5)/AC$5,0) | AD19: ='Investment Analysis'!AT19 | AE19: 22541.29 | AF19: =IF(AE19>0,(AE19-AF$5)/AF$5,0) | AG19: ='Investment Analysis'!BA19 | AI19: =IF(AH19>0,(AH19-AI$5)/AI$5,0) | AJ19: ='Investment Analysis'!BH19 | AK19: 19409.64 | AL19: =IF(AK19>0,(AK19-AL$5)/AL$5,0) | AM19: ='Investment Analysis'!BO19 | AN19: 15121.27 | AO19: =IF(AN19>0,(AN19-AO$5)/AO$5,0) | AP19: ='Investment Analysis'!BV19 | AR19: =IF(AQ19>0,(AQ19-AR$5)/AR$5,0) | AS19: ='Investment Analysis'!CC19 | AT19: 27834.57 | AU19: =IF(AT19>0,(AT19-AU$5)/AU$5,0) | AV19: ='Investment Analysis'!CJ19 | AW19: 19490.9 | AX19: =IF(AW19>0,(AW19-AX$5)/AX$5,0) | AY19: ='Investment Analysis'!CQ19 | AZ19: 17152.76 | BA19: =IF(AZ19>0,(AZ19-BA$5)/BA$5,0) | BB19: ='Investment Analysis'!CX19 | BC19: 10288.7 | BD19: =IF(BC19>0,(BC19-BD$5)/BD$5,0) | BE19: ='Investment Analysis'!DE19 | BF19: 4203.5 | BG19: =IF(BF19>0,(BF19-BG$5)/BG$5,0) | BH19: ='Investment Analysis'!DL19 | BI19: 2604.66 | BJ19: =IF(BI19>0,(BI19-BJ$5)/BJ$5,0) | BK19: ='Investment Analysis'!DZ19 | BL19: 4396.94 | BM19: =IF(BL19>0,(BL19-BM$5)/BM$5,0) | BN19: ='Investment Analysis'!EG19 | BP19: =IF(BO19>0,(BO19-BP$5)/BP$5,0) | BQ19: ='Investment Analysis'!DS19 | BR19: 5751.86 | BS19: =IF(BR19>0,(BR19-BS$5)/BS$5,0) | BT19: ='Investment Analysis'!EN19 | BU19: 14667.02 | BV19: =IF(BU19>0,(BU19-BV$5)/BV$5,0) | BW19: ='Investment Analysis'!EU19 | BY19: =IF(BX19>0,(BX19-BY$5)/BY$5,0) | BZ19: ='Investment Analysis'!FB19 | CA19: 3417.29 | CB19: =IF(CA19>0,(CA19-CB$5)/CB$5,0) | CC19: ='Investment Analysis'!FI19 | CD19: 19168.19 | CE19: =IF(CD19>0,(CD19-CE$5)/CE$5,0) | CF19: ='Investment Analysis'!FP19 | CG19: 5073.46 | CH19: =IF(CG19>0,(CG19-CH$5)/CH$5,0) | CI19: ='Investment Analysis'!FW19 | CK19: =IF(CJ19>0,(CJ19-CK$5)/CK$5,0) | CL19: ='Investment Analysis'!GD19 | CM19: 5036.64 | CN19: =IF(CM19>0,(CM19-CN$5)/CN$5,0) | CO19: ='Investment Analysis'!GT19 | CP19: 64233 | CQ19: =IF(CP19>0,(CP19-CQ$5)/CQ$5,0) | CR19: ='Investment Analysis'!HG19 | CS19: 7020 | CT19: =IF(CS19>0,(CS19-CT$5)/CT$5,0) | CU19: ='Investment Analysis'!HN19 | CV19: 20436 | CW19: =IF(CV19>0,(CV19-CW$5)/CW$5,0) | CX19: ='Investment Analysis'!IB19 | CY19: 22800 | CZ19: =IF(CY19>0,(CY19-CZ$5)/CZ$5,0) | DA19: ='Investment Analysis'!II19 | DC19: =IF(DB19>0,(DB19-DC$5)/DC$5,0) | DD19: ='Investment Analysis'!IP19 | DF19: =IF(DE19>0,(DE19-DF$5)/DF$5,0) | DG19: ='Investment Analysis'!IW19 | DH19: 12342.4 | DI19: =IF(DH19>0,(DH19-DI$5)/DI$5,0) | DJ19: ='Investment Analysis'!JD19 | DK19: 2131.55 | DL19: =IF(DK19>0,(DK19-DL$5)/DL$5,0) | DM19: ='Investment Analysis'!JK19 | DN19: 5575.5 | DO19: =IF(DN19>0,(DN19-DO$5)/DO$5,0) | DP19: ='Investment Analysis'!HU19 | DQ19: 27918 | DR19: =IF(DQ19>0,(DQ19-DR$5)/DR$5,0) | DS19: ='Investment Analysis'!JR19 | DT19: 4164 | DU19: =IF(DT19>0,(DT19-DU$5)/DU$5,0) | DV19: ='Investment Analysis'!JY19 | DW19: 23087.5 | DX19: =IF(DW19>0,(DW19-DX$5)/DX$5,0) | DY19: ='Investment Analysis'!KF19 | DZ19: 2328 | EA19: =IF(DZ19>0,(DZ19-EA$5)/EA$5,0) | EB19: ='Investment Analysis'!KM19 | EC19: 2378.7 | ED19: =IF(EC19>0,(EC19-ED$5)/ED$5,0) | EE19: ='Investment Analysis'!KT19 | EF19: 39330 | EG19: =IF(EF19>0,(EF19-EG$5)/EG$5,0) | EH19: ='Investment Analysis'!LH19 | EI19: 7843.62 | EJ19: =IF(EI19>0,(EI19-EJ$5)/EJ$5,0) | EK19: ='Investment Analysis'!LO19 | EM19: =IF(EL19>0,(EL19-EM$5)/EM$5,0) | EN19: ='Investment Analysis'!LV19 | EP19: =IF(EO19>0,(EO19-EP$5)/EP$5,0) | EQ19: ='Investment Analysis'!MC19 | ER19: 24244.99 | ES19: =IF(ER19>0,(ER19-ES$5)/ES$5,0) | ET19: ='Investment Analysis'!LA19 | EU19: 33838 | EV19: ='Investment Analysis'!ML19 | EW19: ='Investment Analysis'!MJ19 | EX19: 41478.5 | EY19: =IF(EX19>0,(EX19-EY$5)/EY$5,0) | EZ19: ='Investment Analysis'!MQ19 | FB19: =IF(FA19>0,(FA19-FB$5)/FB$5,0) | FC19: ='Investment Analysis'!MX19 | FD19: 4507.25 | FE19: =IF(FD19>0,(FD19-FE$5)/FE$5,0) | FF19: ='Investment Analysis'!NE19 | FH19: =IF(FG19>0,(FG19-FH$5)/FH$5,0) | FI19: ='Investment Analysis'!NL19 | FJ19: 9675.75 | FK19: =IF(FJ19>0,(FJ19-FK$5)/FK$5,0) | FL19: ='Investment Analysis'!NS19 | FM19: 31288 | FN19: =IF(FM19>0,(FM19-FN$5)/FN$5,0) | FO19: ='Investment Analysis'!NZ19 | FQ19: =IF(FP19>0,(FP19-FQ$5)/FQ$5,0) | FR19: ='Investment Analysis'!OG19 | FS19: 34969.5 | FT19: =IF(FS19>0,(FS19-FT$5)/FT$5,0) | FU19: ='Investment Analysis'!ON19 | FW19: =IF(FV19>0,(FV19-FW$5)/FW$5,0) | FX19: ='Investment Analysis'!OU19 | FZ19: =IF(FY19>0,(FY19-FZ$5)/FZ$5,0) | GA19: ='Investment Analysis'!PB19 | GC19: ='Investment Analysis'!PK19 | GD19: ='Investment Analysis'!PI19 | GE19: 6839.5 | GF19: ='Investment Analysis'!PY19 | GG19: ='Investment Analysis'!PW19 | GH19: 32787.5 | GI19: ='Investment Analysis'!QF19 | GJ19: ='Investment Analysis'!QD19 | GK19: 23702 | GL19: ='Investment Analysis'!QM19 | GM19: ='Investment Analysis'!QK19 | GN19: 10999.92 | GO19: ='Investment Analysis'!QT19 | GP19: ='Investment Analysis'!QR19 | GQ19: 17151.3 | GR19: ='Investment Analysis'!RA19 | GS19: ='Investment Analysis'!QY19 | GT19: 16917 | GU19: ='Investment Analysis'!RH19 | GV19: ='Investment Analysis'!RF19 | GX19: ='Investment Analysis'!RO19 | GY19: ='Investment Analysis'!RM19 | HA19: ='Investment Analysis'!RV19 | HB19: ='Investment Analysis'!RT19 | HD19: ='Investment Analysis'!SC19 | HE19: ='Investment Analysis'!SA19 | HG19: ='Investment Analysis'!SJ19 | HH19: ='Investment Analysis'!SH19 | HJ19: ='Investment Analysis'!SM19 | HK19: ='Investment Analysis'!SK19 | HM19: ='Investment Analysis'!SP19 | HN19: ='Investment Analysis'!SN19 | HP19: ='Investment Analysis'!TE19 | HQ19: ='Investment Analysis'!TC19 | HS19: ='Investment Analysis'!TL19 | HT19: ='Investment Analysis'!TJ19 | HV19: ='Investment Analysis'!TS19 | HW19: ='Investment Analysis'!TQ19 | HY19: ='Investment Analysis'!TZ19 | HZ19: ='Investment Analysis'!TX19 | IB19: ='Investment Analysis'!UG19 | IC19: ='Investment Analysis'!UE19 | IE19: ='Investment Analysis'!UN19 | IF19: ='Investment Analysis'!UL19 | IH19: ='Investment Analysis'!UU19 | II19: ='Investment Analysis'!US19 | IK19: ='Investment Analysis'!VB19 | IL19: ='Investment Analysis'!UZ19 | IN19: ='Investment Analysis'!VI19 | IO19: ='Investment Analysis'!VG19 | IS19: =IF(IT19>0,IT19-IT18,0) | IT19: =FY19+FV19+FS19+FP19+FM19+FJ19+FG19+FD19+FA19+EX19+EU19+ER19+EO19+EL19+EI19+EF19+EC19+DZ19+DW19+DT19+DQ19+DN19+DK19+DH19+DE19+DB19+CY19+CV19+CS19+CP19+CJ19+CG19+CD19+CA19+BX19+P19+CM19+GT19+GQ19+GN19+GK19+GH19+GE19+GB19+BU19+BR19+BO19+BL19+BI19+BF19+BC19+AZ19+AW19+AT19+AQ19+AN19+AK19+AH19+AE19+AB19+Y19+V19+S19+GW19+GZ19+HC19+HF19+HI19+HL19+HO19+HR19+HU19 | IU19: =IF(IT19>0,IV19,0) | IW19: =IF(IT19>0,(IT19+IV$11-I$2)/I$2,0) | IX19: =IF(IT19>0,IT19+IV$11-I$2,0) | IY19: =IF(IT19>0,(IT19+IV$11-IT$8)/IT$8,0) | IZ19: =IF(IT19>0,IT19+IV$11-IT$8,0)
A20: ='Investment Analysis'!A20 | B20: ='Investment Analysis'!B20 | C20: ='Investment Analysis'!C20 | D20: ='Investment Analysis'!D20 | E20: ='Investment Analysis'!E20 | F20: ='Investment Analysis'!G20 | G20: ='Investment Analysis'!H20 | H20: ='Investment Analysis'!I20 | I20: ='Investment Analysis'!K20 | J20: ='Investment Analysis'!L20 | K20: ='Investment Analysis'!M20 | L20: ='Investment Analysis'!T20 | M20: ='Investment Analysis'!V20 | N20: ='Investment Analysis'!W20 | P20: ='Investment Analysis'!Y20 | S20: 22417.32 | T20: =IF(S20>0,(S20-T$5)/T$5,0) | U20: ='Investment Analysis'!AF20 | V20: 17923.85 | W20: =IF(V20>0,(V20-W$5)/W$5,0) | X20: ='Investment Analysis'!AT20 | Y20: 9654.23 | Z20: =IF(Y20>0,(Y20-Z$5)/Z$5,0) | AA20: ='Investment Analysis'!GK20 | AB20: 2658.5 | AC20: =IF(AB20>0,(AB20-AC$5)/AC$5,0) | AD20: ='Investment Analysis'!AT20 | AE20: 22493.29 | AF20: =IF(AE20>0,(AE20-AF$5)/AF$5,0) | AG20: ='Investment Analysis'!BA20 | AI20: =IF(AH20>0,(AH20-AI$5)/AI$5,0) | AJ20: ='Investment Analysis'!BH20 | AK20: 19615.47 | AL20: =IF(AK20>0,(AK20-AL$5)/AL$5,0) | AM20: ='Investment Analysis'!BO20 | AN20: 15242.88 | AO20: =IF(AN20>0,(AN20-AO$5)/AO$5,0) | AP20: ='Investment Analysis'!BV20 | AR20: =IF(AQ20>0,(AQ20-AR$5)/AR$5,0) | AS20: ='Investment Analysis'!CC20 | AT20: 27984.05 | AU20: =IF(AT20>0,(AT20-AU$5)/AU$5,0) | AV20: ='Investment Analysis'!CJ20 | AW20: 19593.66 | AX20: =IF(AW20>0,(AW20-AX$5)/AX$5,0) | AY20: ='Investment Analysis'!CQ20 | AZ20: 17215.51 | BA20: =IF(AZ20>0,(AZ20-BA$5)/BA$5,0) | BB20: ='Investment Analysis'!CX20 | BC20: 10318.08 | BD20: =IF(BC20>0,(BC20-BD$5)/BD$5,0) | BE20: ='Investment Analysis'!DE20 | BF20: 4242.04 | BG20: =IF(BF20>0,(BF20-BG$5)/BG$5,0) | BH20: ='Investment Analysis'!DL20 | BI20: 2601.63 | BJ20: =IF(BI20>0,(BI20-BJ$5)/BJ$5,0) | BK20: ='Investment Analysis'!DZ20 | BL20: 4338.88 | BM20: =IF(BL20>0,(BL20-BM$5)/BM$5,0) | BN20: ='Investment Analysis'!EG20 | BP20: =IF(BO20>0,(BO20-BP$5)/BP$5,0) | BQ20: ='Investment Analysis'!DS20 | BR20: 5705.92 | BS20: =IF(BR20>0,(BR20-BS$5)/BS$5,0) | BT20: ='Investment Analysis'!EN20 | BU20: 14856.71 | BV20: =IF(BU20>0,(BU20-BV$5)/BV$5,0) | BW20: ='Investment Analysis'!EU20 | BY20: =IF(BX20>0,(BX20-BY$5)/BY$5,0) | BZ20: ='Investment Analysis'!FB20 | CA20: 3429.04 | CB20: =IF(CA20>0,(CA20-CB$5)/CB$5,0) | CC20: ='Investment Analysis'!FI20 | CD20: 19416.82 | CE20: =IF(CD20>0,(CD20-CE$5)/CE$5,0) | CF20: ='Investment Analysis'!FP20 | CG20: 5152.85 | CH20: =IF(CG20>0,(CG20-CH$5)/CH$5,0) | CI20: ='Investment Analysis'!FW20 | CK20: =IF(CJ20>0,(CJ20-CK$5)/CK$5,0) | CL20: ='Investment Analysis'!GD20 | CM20: 5115.45 | CN20: =IF(CM20>0,(CM20-CN$5)/CN$5,0) | CO20: ='Investment Analysis'!GT20 | CP20: 62073 | CQ20: =IF(CP20>0,(CP20-CQ$5)/CQ$5,0) | CR20: ='Investment Analysis'!HG20 | CS20: 6810 | CT20: =IF(CS20>0,(CS20-CT$5)/CT$5,0) | CU20: ='Investment Analysis'!HN20 | CV20: 26714 | CW20: =IF(CV20>0,(CV20-CW$5)/CW$5,0) | CX20: ='Investment Analysis'!IB20 | CY20: 22941 | CZ20: =IF(CY20>0,(CY20-CZ$5)/CZ$5,0) | DA20: ='Investment Analysis'!II20 | DC20: =IF(DB20>0,(DB20-DC$5)/DC$5,0) | DD20: ='Investment Analysis'!IP20 | DF20: =IF(DE20>0,(DE20-DF$5)/DF$5,0) | DG20: ='Investment Analysis'!IW20 | DH20: 12226 | DI20: =IF(DH20>0,(DH20-DI$5)/DI$5,0) | DJ20: ='Investment Analysis'!JD20 | DK20: 2122.9 | DL20: =IF(DK20>0,(DK20-DL$5)/DL$5,0) | DM20: ='Investment Analysis'!JK20 | DN20: 5566 | DO20: =IF(DN20>0,(DN20-DO$5)/DO$5,0) | DP20: ='Investment Analysis'!HU20 | DQ20: 28215 | DR20: =IF(DQ20>0,(DQ20-DR$5)/DR$5,0) | DS20: ='Investment Analysis'!JR20 | DT20: 4056 | DU20: =IF(DT20>0,(DT20-DU$5)/DU$5,0) | DV20: ='Investment Analysis'!JY20 | DW20: 22993.75 | DX20: =IF(DW20>0,(DW20-DX$5)/DX$5,0) | DY20: ='Investment Analysis'!KF20 | DZ20: 2335.2 | EA20: =IF(DZ20>0,(DZ20-EA$5)/EA$5,0) | EB20: ='Investment Analysis'!KM20 | EC20: 2282.6 | ED20: =IF(EC20>0,(EC20-ED$5)/ED$5,0) | EE20: ='Investment Analysis'!KT20 | EF20: 40335 | EG20: =IF(EF20>0,(EF20-EG$5)/EG$5,0) | EH20: ='Investment Analysis'!LH20 | EI20: 7828.74 | EJ20: =IF(EI20>0,(EI20-EJ$5)/EJ$5,0) | EK20: ='Investment Analysis'!LO20 | EM20: =IF(EL20>0,(EL20-EM$5)/EM$5,0) | EN20: ='Investment Analysis'!LV20 | EP20: =IF(EO20>0,(EO20-EP$5)/EP$5,0) | EQ20: ='Investment Analysis'!MC20 | ER20: 24314.68 | ES20: =IF(ER20>0,(ER20-ES$5)/ES$5,0) | ET20: ='Investment Analysis'!LA20 | EU20: 33922 | EV20: ='Investment Analysis'!ML20 | EW20: ='Investment Analysis'!MJ20 | EX20: 42395.5 | EY20: =IF(EX20>0,(EX20-EY$5)/EY$5,0) | EZ20: ='Investment Analysis'!MQ20 | FB20: =IF(FA20>0,(FA20-FB$5)/FB$5,0) | FC20: ='Investment Analysis'!MX20 | FD20: 4493.5 | FE20: =IF(FD20>0,(FD20-FE$5)/FE$5,0) | FF20: ='Investment Analysis'!NE20 | FH20: =IF(FG20>0,(FG20-FH$5)/FH$5,0) | FI20: ='Investment Analysis'!NL20 | FJ20: 9775 | FK20: =IF(FJ20>0,(FJ20-FK$5)/FK$5,0) | FL20: ='Investment Analysis'!NS20 | FM20: 30865.6 | FN20: =IF(FM20>0,(FM20-FN$5)/FN$5,0) | FO20: ='Investment Analysis'!NZ20 | FQ20: =IF(FP20>0,(FP20-FQ$5)/FQ$5,0) | FR20: ='Investment Analysis'!OG20 | FS20: 35178.5 | FT20: =IF(FS20>0,(FS20-FT$5)/FT$5,0) | FU20: ='Investment Analysis'!ON20 | FW20: =IF(FV20>0,(FV20-FW$5)/FW$5,0) | FX20: ='Investment Analysis'!OU20 | FZ20: =IF(FY20>0,(FY20-FZ$5)/FZ$5,0) | GA20: ='Investment Analysis'!PB20 | GC20: ='Investment Analysis'!PK20 | GD20: ='Investment Analysis'!PI20 | GE20: 6915 | GF20: ='Investment Analysis'!PY20 | GG20: ='Investment Analysis'!PW20 | GH20: 32982.5 | GI20: ='Investment Analysis'!QF20 | GJ20: ='Investment Analysis'!QD20 | GK20: 23960 | GL20: ='Investment Analysis'!QM20 | GM20: ='Investment Analysis'!QK20 | GN20: 32038.77 | GO20: ='Investment Analysis'!QT20 | GP20: ='Investment Analysis'!QR20 | GQ20: 16956.6 | GR20: ='Investment Analysis'!RA20 | GS20: ='Investment Analysis'!QY20 | GT20: 17400 | GU20: ='Investment Analysis'!RH20 | GV20: ='Investment Analysis'!RF20 | GX20: ='Investment Analysis'!RO20 | GY20: ='Investment Analysis'!RM20 | HA20: ='Investment Analysis'!RV20 | HB20: ='Investment Analysis'!RT20 | HD20: ='Investment Analysis'!SC20 | HE20: ='Investment Analysis'!SA20 | HG20: ='Investment Analysis'!SJ20 | HH20: ='Investment Analysis'!SH20 | HJ20: ='Investment Analysis'!SM20 | HK20: ='Investment Analysis'!SK20 | HM20: ='Investment Analysis'!SP20 | HN20: ='Investment Analysis'!SN20 | HP20: ='Investment Analysis'!TE20 | HQ20: ='Investment Analysis'!TC20 | HS20: ='Investment Analysis'!TL20 | HT20: ='Investment Analysis'!TJ20 | HV20: ='Investment Analysis'!TS20 | HW20: ='Investment Analysis'!TQ20 | HY20: ='Investment Analysis'!TZ20 | HZ20: ='Investment Analysis'!TX20 | IB20: ='Investment Analysis'!UG20 | IC20: ='Investment Analysis'!UE20 | IE20: ='Investment Analysis'!UN20 | IF20: ='Investment Analysis'!UL20 | IH20: ='Investment Analysis'!UU20 | II20: ='Investment Analysis'!US20 | IK20: ='Investment Analysis'!VB20 | IL20: ='Investment Analysis'!UZ20 | IN20: ='Investment Analysis'!VI20 | IO20: ='Investment Analysis'!VG20 | IS20: =IF(IT20>0,IT20-IT19,0) | IT20: =FY20+FV20+FS20+FP20+FM20+FJ20+FG20+FD20+FA20+EX20+EU20+ER20+EO20+EL20+EI20+EF20+EC20+DZ20+DW20+DT20+DQ20+DN20+DK20+DH20+DE20+DB20+CY20+CV20+CS20+CP20+CJ20+CG20+CD20+CA20+BX20+P20+CM20+GT20+GQ20+GN20+GK20+GH20+GE20+GB20+BU20+BR20+BO20+BL20+BI20+BF20+BC20+AZ20+AW20+AT20+AQ20+AN20+AK20+AH20+AE20+AB20+Y20+V20+S20+GW20+GZ20+HC20+HF20+HI20+HL20+HO20+HR20+HU20 | IU20: =IF(IT20>0,IV20,0) | IW20: =IF(IT20>0,(IT20+IV$11-I$2)/I$2,0) | IX20: =IF(IT20>0,IT20+IV$11-I$2,0) | IY20: =IF(IT20>0,(IT20+IV$11-IT$8)/IT$8,0) | IZ20: =IF(IT20>0,IT20+IV$11-IT$8,0)
A21: ='Investment Analysis'!A21 | B21: ='Investment Analysis'!B21 | C21: ='Investment Analysis'!C21 | D21: ='Investment Analysis'!D21 | E21: ='Investment Analysis'!E21 | F21: ='Investment Analysis'!G21 | G21: ='Investment Analysis'!H21 | H21: ='Investment Analysis'!I21 | I21: ='Investment Analysis'!K21 | J21: ='Investment Analysis'!L21 | K21: ='Investment Analysis'!M21 | L21: ='Investment Analysis'!T21 | M21: ='Investment Analysis'!V21 | N21: ='Investment Analysis'!W21 | P21: ='Investment Analysis'!Y21 | S21: 22741.38 | T21: =IF(S21>0,(S21-T$5)/T$5,0) | U21: ='Investment Analysis'!AF21 | V21: 18091.13 | W21: =IF(V21>0,(V21-W$5)/W$5,0) | X21: ='Investment Analysis'!AT21 | Y21: 9628.02 | Z21: =IF(Y21>0,(Y21-Z$5)/Z$5,0) | AA21: ='Investment Analysis'!GK21 | AB21: 2694.21 | AC21: =IF(AB21>0,(AB21-AC$5)/AC$5,0) | AD21: ='Investment Analysis'!AT21 | AE21: 22719.07 | AF21: =IF(AE21>0,(AE21-AF$5)/AF$5,0) | AG21: ='Investment Analysis'!BA21 | AI21: =IF(AH21>0,(AH21-AI$5)/AI$5,0) | AJ21: ='Investment Analysis'!BH21 | AK21: 19784.64 | AL21: =IF(AK21>0,(AK21-AL$5)/AL$5,0) | AM21: ='Investment Analysis'!BO21 | AN21: 15368.29 | AO21: =IF(AN21>0,(AN21-AO$5)/AO$5,0) | AP21: ='Investment Analysis'!BV21 | AR21: =IF(AQ21>0,(AQ21-AR$5)/AR$5,0) | AS21: ='Investment Analysis'!CC21 | AT21: 28172.87 | AU21: =IF(AT21>0,(AT21-AU$5)/AU$5,0) | AV21: ='Investment Analysis'!CJ21 | AW21: 19713.55 | AX21: =IF(AW21>0,(AW21-AX$5)/AX$5,0) | AY21: ='Investment Analysis'!CQ21 | AZ21: 17282.74 | BA21: =IF(AZ21>0,(AZ21-BA$5)/BA$5,0) | BB21: ='Investment Analysis'!CX21 | BC21: 10371.95 | BD21: =IF(BC21>0,(BC21-BD$5)/BD$5,0) | BE21: ='Investment Analysis'!DE21 | BF21: 4260.81 | BG21: =IF(BF21>0,(BF21-BG$5)/BG$5,0) | BH21: ='Investment Analysis'!DL21 | BI21: 2672.09 | BJ21: =IF(BI21>0,(BI21-BJ$5)/BJ$5,0) | BK21: ='Investment Analysis'!DZ21 | BL21: 4418.26 | BM21: =IF(BL21>0,(BL21-BM$5)/BM$5,0) | BN21: ='Investment Analysis'!EG21 | BP21: =IF(BO21>0,(BO21-BP$5)/BP$5,0) | BQ21: ='Investment Analysis'!DS21 | BR21: 5760.45 | BS21: =IF(BR21>0,(BR21-BS$5)/BS$5,0) | BT21: ='Investment Analysis'!EN21 | BU21: 14951.56 | BV21: =IF(BU21>0,(BU21-BV$5)/BV$5,0) | BW21: ='Investment Analysis'!EU21 | BY21: =IF(BX21>0,(BX21-BY$5)/BY$5,0) | BZ21: ='Investment Analysis'!FB21 | CA21: 3451.98 | CB21: =IF(CA21>0,(CA21-CB$5)/CB$5,0) | CC21: ='Investment Analysis'!FI21 | CD21: 19638.4 | CE21: =IF(CD21>0,(CD21-CE$5)/CE$5,0) | CF21: ='Investment Analysis'!FP21 | CG21: 5128.81 | CH21: =IF(CG21>0,(CG21-CH$5)/CH$5,0) | CI21: ='Investment Analysis'!FW21 | CK21: =IF(CJ21>0,(CJ21-CK$5)/CK$5,0) | CL21: ='Investment Analysis'!GD21 | CM21: 5140.52 | CN21: =IF(CM21>0,(CM21-CN$5)/CN$5,0) | CO21: ='Investment Analysis'!GT21 | CP21: 63975 | CQ21: =IF(CP21>0,(CP21-CQ$5)/CQ$5,0) | CR21: ='Investment Analysis'!HG21 | CS21: 6840 | CT21: =IF(CS21>0,(CS21-CT$5)/CT$5,0) | CU21: ='Investment Analysis'!HN21 | CV21: 27542 | CW21: =IF(CV21>0,(CV21-CW$5)/CW$5,0) | CX21: ='Investment Analysis'!IB21 | CY21: 23744 | CZ21: =IF(CY21>0,(CY21-CZ$5)/CZ$5,0) | DA21: ='Investment Analysis'!II21 | DC21: =IF(DB21>0,(DB21-DC$5)/DC$5,0) | DD21: ='Investment Analysis'!IP21 | DF21: =IF(DE21>0,(DE21-DF$5)/DF$5,0) | DG21: ='Investment Analysis'!IW21 | DH21: 12255.4 | DI21: =IF(DH21>0,(DH21-DI$5)/DI$5,0) | DJ21: ='Investment Analysis'!JD21 | DK21: 2145.15 | DL21: =IF(DK21>0,(DK21-DL$5)/DL$5,0) | DM21: ='Investment Analysis'!JK21 | DN21: 5616 | DO21: =IF(DN21>0,(DN21-DO$5)/DO$5,0) | DP21: ='Investment Analysis'!HU21 | DQ21: 28269 | DR21: =IF(DQ21>0,(DQ21-DR$5)/DR$5,0) | DS21: ='Investment Analysis'!JR21 | DT21: 4394 | DU21: =IF(DT21>0,(DT21-DU$5)/DU$5,0) | DV21: ='Investment Analysis'!JY21 | DW21: 23579.75 | DX21: =IF(DW21>0,(DW21-DX$5)/DX$5,0) | DY21: ='Investment Analysis'!KF21 | DZ21: 2344.8 | EA21: =IF(DZ21>0,(DZ21-EA$5)/EA$5,0) | EB21: ='Investment Analysis'!KM21 | EC21: 2299.8 | ED21: =IF(EC21>0,(EC21-ED$5)/ED$5,0) | EE21: ='Investment Analysis'!KT21 | EF21: 39720 | EG21: =IF(EF21>0,(EF21-EG$5)/EG$5,0) | EH21: ='Investment Analysis'!LH21 | EI21: 7907.79 | EJ21: =IF(EI21>0,(EI21-EJ$5)/EJ$5,0) | EK21: ='Investment Analysis'!LO21 | EM21: =IF(EL21>0,(EL21-EM$5)/EM$5,0) | EN21: ='Investment Analysis'!LV21 | EP21: =IF(EO21>0,(EO21-EP$5)/EP$5,0) | EQ21: ='Investment Analysis'!MC21 | ER21: 24644.04 | ES21: =IF(ER21>0,(ER21-ES$5)/ES$5,0) | ET21: ='Investment Analysis'!LA21 | EU21: 36470 | EV21: ='Investment Analysis'!ML21 | EW21: ='Investment Analysis'!MJ21 | EX21: 42850.5 | EY21: =IF(EX21>0,(EX21-EY$5)/EY$5,0) | EZ21: ='Investment Analysis'!MQ21 | FB21: =IF(FA21>0,(FA21-FB$5)/FB$5,0) | FC21: ='Investment Analysis'!MX21 | FD21: 4571.25 | FE21: =IF(FD21>0,(FD21-FE$5)/FE$5,0) | FF21: ='Investment Analysis'!NE21 | FH21: =IF(FG21>0,(FG21-FH$5)/FH$5,0) | FI21: ='Investment Analysis'!NL21 | FJ21: 10035.25 | FK21: =IF(FJ21>0,(FJ21-FK$5)/FK$5,0) | FL21: ='Investment Analysis'!NS21 | FM21: 31360 | FN21: =IF(FM21>0,(FM21-FN$5)/FN$5,0) | FO21: ='Investment Analysis'!NZ21 | FQ21: =IF(FP21>0,(FP21-FQ$5)/FQ$5,0) | FR21: ='Investment Analysis'!OG21 | FS21: 36969.25 | FT21: =IF(FS21>0,(FS21-FT$5)/FT$5,0) | FU21: ='Investment Analysis'!ON21 | FW21: =IF(FV21>0,(FV21-FW$5)/FW$5,0) | FX21: ='Investment Analysis'!OU21 | FZ21: =IF(FY21>0,(FY21-FZ$5)/FZ$5,0) | GA21: ='Investment Analysis'!PB21 | GC21: ='Investment Analysis'!PK21 | GD21: ='Investment Analysis'!PI21 | GE21: 6927 | GF21: ='Investment Analysis'!PY21 | GG21: ='Investment Analysis'!PW21 | GH21: 32993.75 | GI21: ='Investment Analysis'!QF21 | GJ21: ='Investment Analysis'!QD21 | GK21: 24318 | GL21: ='Investment Analysis'!QM21 | GM21: ='Investment Analysis'!QK21 | GN21: 32494.4 | GO21: ='Investment Analysis'!QT21 | GP21: ='Investment Analysis'!QR21 | GQ21: 17042.15 | GR21: ='Investment Analysis'!RA21 | GS21: ='Investment Analysis'!QY21 | GT21: 17086 | GU21: ='Investment Analysis'!RH21 | GV21: ='Investment Analysis'!RF21 | GX21: ='Investment Analysis'!RO21 | GY21: ='Investment Analysis'!RM21 | HA21: ='Investment Analysis'!RV21 | HB21: ='Investment Analysis'!RT21 | HD21: ='Investment Analysis'!SC21 | HE21: ='Investment Analysis'!SA21 | HG21: ='Investment Analysis'!SJ21 | HH21: ='Investment Analysis'!SH21 | HJ21: ='Investment Analysis'!SM21 | HK21: ='Investment Analysis'!SK21 | HM21: ='Investment Analysis'!SP21 | HN21: ='Investment Analysis'!SN21 | HP21: ='Investment Analysis'!TE21 | HQ21: ='Investment Analysis'!TC21 | HS21: ='Investment Analysis'!TL21 | HT21: ='Investment Analysis'!TJ21 | HV21: ='Investment Analysis'!TS21 | HW21: ='Investment Analysis'!TQ21 | HY21: ='Investment Analysis'!TZ21 | HZ21: ='Investment Analysis'!TX21 | IB21: ='Investment Analysis'!UG21 | IC21: ='Investment Analysis'!UE21 | IE21: ='Investment Analysis'!UN21 | IF21: ='Investment Analysis'!UL21 | IH21: ='Investment Analysis'!UU21 | II21: ='Investment Analysis'!US21 | IK21: ='Investment Analysis'!VB21 | IL21: ='Investment Analysis'!UZ21 | IN21: ='Investment Analysis'!VI21 | IO21: ='Investment Analysis'!VG21 | IS21: =IF(IT21>0,IT21-IT20,0) | IT21: =FY21+FV21+FS21+FP21+FM21+FJ21+FG21+FD21+FA21+EX21+EU21+ER21+EO21+EL21+EI21+EF21+EC21+DZ21+DW21+DT21+DQ21+DN21+DK21+DH21+DE21+DB21+CY21+CV21+CS21+CP21+CJ21+CG21+CD21+CA21+BX21+P21+CM21+GT21+GQ21+GN21+GK21+GH21+GE21+GB21+BU21+BR21+BO21+BL21+BI21+BF21+BC21+AZ21+AW21+AT21+AQ21+AN21+AK21+AH21+AE21+AB21+Y21+V21+S21+GW21+GZ21+HC21+HF21+HI21+HL21+HO21+HR21+HU21 | IU21: =IF(IT21>0,IV21,0) | IW21: =IF(IT21>0,(IT21+IV$11-I$2)/I$2,0) | IX21: =IF(IT21>0,IT21+IV$11-I$2,0) | IY21: =IF(IT21>0,(IT21+IV$11-IT$8)/IT$8,0) | IZ21: =IF(IT21>0,IT21+IV$11-IT$8,0)
A22: ='Investment Analysis'!A22 | B22: ='Investment Analysis'!B22 | C22: ='Investment Analysis'!C22 | D22: ='Investment Analysis'!D22 | E22: ='Investment Analysis'!E22 | F22: ='Investment Analysis'!G22 | G22: ='Investment Analysis'!H22 | H22: ='Investment Analysis'!I22 | I22: ='Investment Analysis'!K22 | J22: ='Investment Analysis'!L22 | K22: ='Investment Analysis'!M22 | L22: ='Investment Analysis'!T22 | M22: ='Investment Analysis'!V22 | N22: ='Investment Analysis'!W22 | P22: ='Investment Analysis'!Y22 | S22: 22893.59 | T22: =IF(S22>0,(S22-T$5)/T$5,0) | U22: ='Investment Analysis'!AF22 | V22: 18283.5 | W22: =IF(V22>0,(V22-W$5)/W$5,0) | X22: ='Investment Analysis'!AT22 | Y22: 9874.36 | Z22: =IF(Y22>0,(Y22-Z$5)/Z$5,0) | AA22: ='Investment Analysis'!GK22 | AB22: 2717.61 | AC22: =IF(AB22>0,(AB22-AC$5)/AC$5,0) | AD22: ='Investment Analysis'!AT22 | AE22: 22918.66 | AF22: =IF(AE22>0,(AE22-AF$5)/AF$5,0) | AG22: ='Investment Analysis'!BA22 | AI22: =IF(AH22>0,(AH22-AI$5)/AI$5,0) | AJ22: ='Investment Analysis'!BH22 | AK22: 20145.54 | AL22: =IF(AK22>0,(AK22-AL$5)/AL$5,0) | AM22: ='Investment Analysis'!BO22 | AN22: 15695.11 | AO22: =IF(AN22>0,(AN22-AO$5)/AO$5,0) | AP22: ='Investment Analysis'!BV22 | AR22: =IF(AQ22>0,(AQ22-AR$5)/AR$5,0) | AS22: ='Investment Analysis'!CC22 | AT22: 28629.17 | AU22: =IF(AT22>0,(AT22-AU$5)/AU$5,0) | AV22: ='Investment Analysis'!CJ22 | AW22: 20067.52 | AX22: =IF(AW22>0,(AW22-AX$5)/AX$5,0) | AY22: ='Investment Analysis'!CQ22 | AZ22: 17605.45 | BA22: =IF(AZ22>0,(AZ22-BA$5)/BA$5,0) | BB22: ='Investment Analysis'!CX22 | BC22: 10548.24 | BD22: =IF(BC22>0,(BC22-BD$5)/BD$5,0) | BE22: ='Investment Analysis'!DE22 | BF22: 4339.86 | BG22: =IF(BF22>0,(BF22-BG$5)/BG$5,0) | BH22: ='Investment Analysis'!DL22 | BI22: 2709.97 | BJ22: =IF(BI22>0,(BI22-BJ$5)/BJ$5,0) | BK22: ='Investment Analysis'!DZ22 | BL22: 4443.15 | BM22: =IF(BL22>0,(BL22-BM$5)/BM$5,0) | BN22: ='Investment Analysis'!EG22 | BP22: =IF(BO22>0,(BO22-BP$5)/BP$5,0) | BQ22: ='Investment Analysis'!DS22 | BR22: 5820.53 | BS22: =IF(BR22>0,(BR22-BS$5)/BS$5,0) | BT22: ='Investment Analysis'!EN22 | BU22: 15126.07 | BV22: =IF(BU22>0,(BU22-BV$5)/BV$5,0) | BW22: ='Investment Analysis'!EU22 | BY22: =IF(BX22>0,(BX22-BY$5)/BY$5,0) | BZ22: ='Investment Analysis'!FB22 | CA22: 23421.59 | CB22: =IF(CA22>0,(CA22-CB$5)/CB$5,0) | CC22: ='Investment Analysis'!FI22 | CD22: 19949.44 | CE22: =IF(CD22>0,(CD22-CE$5)/CE$5,0) | CF22: ='Investment Analysis'!FP22 | CG22: 5147.26 | CH22: =IF(CG22>0,(CG22-CH$5)/CH$5,0) | CI22: ='Investment Analysis'!FW22 | CK22: =IF(CJ22>0,(CJ22-CK$5)/CK$5,0) | CL22: ='Investment Analysis'!GD22 | CM22: 25508.43 | CN22: =IF(CM22>0,(CM22-CN$5)/CN$5,0) | CO22: ='Investment Analysis'!GT22 | CP22: 63610.5 | CQ22: =IF(CP22>0,(CP22-CQ$5)/CQ$5,0) | CR22: ='Investment Analysis'!HG22 | CS22: 6960 | CT22: =IF(CS22>0,(CS22-CT$5)/CT$5,0) | CU22: ='Investment Analysis'!HN22 | CV22: 28166 | CW22: =IF(CV22>0,(CV22-CW$5)/CW$5,0) | CX22: ='Investment Analysis'!IB22 | CY22: 24031 | CZ22: =IF(CY22>0,(CY22-CZ$5)/CZ$5,0) | DA22: ='Investment Analysis'!II22 | DC22: =IF(DB22>0,(DB22-DC$5)/DC$5,0) | DD22: ='Investment Analysis'!IP22 | DF22: =IF(DE22>0,(DE22-DF$5)/DF$5,0) | DG22: ='Investment Analysis'!IW22 | DH22: 12329.2 | DI22: =IF(DH22>0,(DH22-DI$5)/DI$5,0) | DJ22: ='Investment Analysis'!JD22 | DK22: 2142.5 | DL22: =IF(DK22>0,(DK22-DL$5)/DL$5,0) | DM22: ='Investment Analysis'!JK22 | DN22: 5573.5 | DO22: =IF(DN22>0,(DN22-DO$5)/DO$5,0) | DP22: ='Investment Analysis'!HU22 | DQ22: 29160 | DR22: =IF(DQ22>0,(DQ22-DR$5)/DR$5,0) | DS22: ='Investment Analysis'!JR22 | DT22: 5122 | DU22: =IF(DT22>0,(DT22-DU$5)/DU$5,0) | DV22: ='Investment Analysis'!JY22 | DW22: 23693.25 | DX22: =IF(DW22>0,(DW22-DX$5)/DX$5,0) | DY22: ='Investment Analysis'!KF22 | DZ22: 2389.2 | EA22: =IF(DZ22>0,(DZ22-EA$5)/EA$5,0) | EB22: ='Investment Analysis'!KM22 | EC22: 2226.4 | ED22: =IF(EC22>0,(EC22-ED$5)/ED$5,0) | EE22: ='Investment Analysis'!KT22 | EF22: 40072.5 | EG22: =IF(EF22>0,(EF22-EG$5)/EG$5,0) | EH22: ='Investment Analysis'!LH22 | EI22: 8239.8 | EJ22: =IF(EI22>0,(EI22-EJ$5)/EJ$5,0) | EK22: ='Investment Analysis'!LO22 | EM22: =IF(EL22>0,(EL22-EM$5)/EM$5,0) | EN22: ='Investment Analysis'!LV22 | EP22: =IF(EO22>0,(EO22-EP$5)/EP$5,0) | EQ22: ='Investment Analysis'!MC22 | ER22: 25227.55 | ES22: =IF(ER22>0,(ER22-ES$5)/ES$5,0) | ET22: ='Investment Analysis'!LA22 | EU22: 43750 | EV22: ='Investment Analysis'!ML22 | EW22: ='Investment Analysis'!MJ22 | EX22: 44338 | EY22: =IF(EX22>0,(EX22-EY$5)/EY$5,0) | EZ22: ='Investment Analysis'!MQ22 | FB22: =IF(FA22>0,(FA22-FB$5)/FB$5,0) | FC22: ='Investment Analysis'!MX22 | FD22: 4687.5 | FE22: =IF(FD22>0,(FD22-FE$5)/FE$5,0) | FF22: ='Investment Analysis'!NE22 | FH22: =IF(FG22>0,(FG22-FH$5)/FH$5,0) | FI22: ='Investment Analysis'!NL22 | FJ22: 10400 | FK22: =IF(FJ22>0,(FJ22-FK$5)/FK$5,0) | FL22: ='Investment Analysis'!NS22 | FM22: 31688 | FN22: =IF(FM22>0,(FM22-FN$5)/FN$5,0) | FO22: ='Investment Analysis'!NZ22 | FQ22: =IF(FP22>0,(FP22-FQ$5)/FQ$5,0) | FR22: ='Investment Analysis'!OG22 | FS22: 42051.75 | FT22: =IF(FS22>0,(FS22-FT$5)/FT$5,0) | FU22: ='Investment Analysis'!ON22 | FW22: =IF(FV22>0,(FV22-FW$5)/FW$5,0) | FX22: ='Investment Analysis'!OU22 | FZ22: =IF(FY22>0,(FY22-FZ$5)/FZ$5,0) | GA22: ='Investment Analysis'!PB22 | GC22: ='Investment Analysis'!PK22 | GD22: ='Investment Analysis'!PI22 | GE22: 7036.5 | GF22: ='Investment Analysis'!PY22 | GG22: ='Investment Analysis'!PW22 | GH22: 33467.5 | GI22: ='Investment Analysis'!QF22 | GJ22: ='Investment Analysis'!QD22 | GK22: 24762 | GL22: ='Investment Analysis'!QM22 | GM22: ='Investment Analysis'!QK22 | GN22: 32606.18 | GO22: ='Investment Analysis'!QT22 | GP22: ='Investment Analysis'!QR22 | GQ22: 17540.7 | GR22: ='Investment Analysis'!RA22 | GS22: ='Investment Analysis'!QY22 | GT22: 18535 | GU22: ='Investment Analysis'!RH22 | GV22: ='Investment Analysis'!RF22 | GX22: ='Investment Analysis'!RO22 | GY22: ='Investment Analysis'!RM22 | HA22: ='Investment Analysis'!RV22 | HB22: ='Investment Analysis'!RT22 | HD22: ='Investment Analysis'!SC22 | HE22: ='Investment Analysis'!SA22 | HG22: ='Investment Analysis'!SJ22 | HH22: ='Investment Analysis'!SH22 | HJ22: ='Investment Analysis'!SM22 | HK22: ='Investment Analysis'!SK22 | HM22: ='Investment Analysis'!SP22 | HN22: ='Investment Analysis'!SN22 | HP22: ='Investment Analysis'!TE22 | HQ22: ='Investment Analysis'!TC22 | HS22: ='Investment Analysis'!TL22 | HT22: ='Investment Analysis'!TJ22 | HV22: ='Investment Analysis'!TS22 | HW22: ='Investment Analysis'!TQ22 | HY22: ='Investment Analysis'!TZ22 | HZ22: ='Investment Analysis'!TX22 | IB22: ='Investment Analysis'!UG22 | IC22: ='Investment Analysis'!UE22 | IE22: ='Investment Analysis'!UN22 | IF22: ='Investment Analysis'!UL22 | IH22: ='Investment Analysis'!UU22 | II22: ='Investment Analysis'!US22 | IK22: ='Investment Analysis'!VB22 | IL22: ='Investment Analysis'!UZ22 | IN22: ='Investment Analysis'!VI22 | IO22: ='Investment Analysis'!VG22 | IS22: =IF(IT22>0,IT22-IT21,0) | IT22: =FY22+FV22+FS22+FP22+FM22+FJ22+FG22+FD22+FA22+EX22+EU22+ER22+EO22+EL22+EI22+EF22+EC22+DZ22+DW22+DT22+DQ22+DN22+DK22+DH22+DE22+DB22+CY22+CV22+CS22+CP22+CJ22+CG22+CD22+CA22+BX22+P22+CM22+GT22+GQ22+GN22+GK22+GH22+GE22+GB22+BU22+BR22+BO22+BL22+BI22+BF22+BC22+AZ22+AW22+AT22+AQ22+AN22+AK22+AH22+AE22+AB22+Y22+V22+S22+GW22+GZ22+HC22+HF22+HI22+HL22+HO22+HR22+HU22 | IU22: =IF(IT22>0,IV22,0) | IW22: =IF(IT22>0,(IT22+IV$11-I$2)/I$2,0) | IX22: =IF(IT22>0,IT22+IV$11-I$2,0) | IY22: =IF(IT22>0,(IT22+IV$11-IT$8)/IT$8,0) | IZ22: =IF(IT22>0,IT22+IV$11-IT$8,0)
A23: ='Investment Analysis'!A23 | B23: ='Investment Analysis'!B23 | C23: ='Investment Analysis'!C23 | D23: ='Investment Analysis'!D23 | E23: ='Investment Analysis'!E23 | F23: ='Investment Analysis'!G23 | G23: ='Investment Analysis'!H23 | H23: ='Investment Analysis'!I23 | I23: ='Investment Analysis'!K23 | J23: ='Investment Analysis'!L23 | K23: ='Investment Analysis'!M23 | L23: ='Investment Analysis'!T23 | M23: ='Investment Analysis'!V23 | N23: ='Investment Analysis'!W23 | P23: ='Investment Analysis'!Y23 | S23: 23259.88 | T23: =IF(S23>0,(S23-T$5)/T$5,0) | U23: ='Investment Analysis'!AF23 | V23: 18526.06 | W23: =IF(V23>0,(V23-W$5)/W$5,0) | X23: ='Investment Analysis'!AT23 | Y23: 9895.32 | Z23: =IF(Y23>0,(Y23-Z$5)/Z$5,0) | AA23: ='Investment Analysis'!GK23 | AB23: 2760.7 | AC23: =IF(AB23>0,(AB23-AC$5)/AC$5,0) | AD23: ='Investment Analysis'!AT23 | AE23: 23059.36 | AF23: =IF(AE23>0,(AE23-AF$5)/AF$5,0) | AG23: ='Investment Analysis'!BA23 | AI23: =IF(AH23>0,(AH23-AI$5)/AI$5,0) | AJ23: ='Investment Analysis'!BH23 | AK23: 20320.35 | AL23: =IF(AK23>0,(AK23-AL$5)/AL$5,0) | AM23: ='Investment Analysis'!BO23 | AN23: 15881.32 | AO23: =IF(AN23>0,(AN23-AO$5)/AO$5,0) | AP23: ='Investment Analysis'!BV23 | AR23: =IF(AQ23>0,(AQ23-AR$5)/AR$5,0) | AS23: ='Investment Analysis'!CC23 | AT23: 28613.44 | AU23: =IF(AT23>0,(AT23-AU$5)/AU$5,0) | AV23: ='Investment Analysis'!CJ23 | AW23: 20044.68 | AX23: =IF(AW23>0,(AW23-AX$5)/AX$5,0) | AY23: ='Investment Analysis'!CQ23 | AZ23: 17578.56 | BA23: =IF(AZ23>0,(AZ23-BA$5)/BA$5,0) | BB23: ='Investment Analysis'!CX23 | BC23: 10484.58 | BD23: =IF(BC23>0,(BC23-BD$5)/BD$5,0) | BE23: ='Investment Analysis'!DE23 | BF23: 4358.64 | BG23: =IF(BF23>0,(BF23-BG$5)/BG$5,0) | BH23: ='Investment Analysis'!DL23 | BI23: 2760.73 | BJ23: =IF(BI23>0,(BI23-BJ$5)/BJ$5,0) | BK23: ='Investment Analysis'!DZ23 | BL23: 4534.38 | BM23: =IF(BL23>0,(BL23-BM$5)/BM$5,0) | BN23: ='Investment Analysis'!EG23 | BP23: =IF(BO23>0,(BO23-BP$5)/BP$5,0) | BQ23: ='Investment Analysis'!DS23 | BR23: 5875.05 | BS23: =IF(BR23>0,(BR23-BS$5)/BS$5,0) | BT23: ='Investment Analysis'!EN23 | BU23: 14936.38 | BV23: =IF(BU23>0,(BU23-BV$5)/BV$5,0) | BW23: ='Investment Analysis'!EU23 | BY23: =IF(BX23>0,(BX23-BY$5)/BY$5,0) | BZ23: ='Investment Analysis'!FB23 | CA23: 23052.84 | CB23: =IF(CA23>0,(CA23-CB$5)/CB$5,0) | CC23: ='Investment Analysis'!FI23 | CD23: 20083.64 | CE23: =IF(CD23>0,(CD23-CE$5)/CE$5,0) | CF23: ='Investment Analysis'!FP23 | CG23: 5127.69 | CH23: =IF(CG23>0,(CG23-CH$5)/CH$5,0) | CI23: ='Investment Analysis'!FW23 | CK23: =IF(CJ23>0,(CJ23-CK$5)/CK$5,0) | CL23: ='Investment Analysis'!GD23 | CM23: 25193.08 | CN23: =IF(CM23>0,(CM23-CN$5)/CN$5,0) | CO23: ='Investment Analysis'!GT23 | CP23: 62266.5 | CQ23: =IF(CP23>0,(CP23-CQ$5)/CQ$5,0) | CR23: ='Investment Analysis'!HG23 | CS23: 6990 | CT23: =IF(CS23>0,(CS23-CT$5)/CT$5,0) | CU23: ='Investment Analysis'!HN23 | CV23: 29414 | CW23: =IF(CV23>0,(CV23-CW$5)/CW$5,0) | CX23: ='Investment Analysis'!IB23 | CY23: 24091 | CZ23: =IF(CY23>0,(CY23-CZ$5)/CZ$5,0) | DA23: ='Investment Analysis'!II23 | DC23: =IF(DB23>0,(DB23-DC$5)/DC$5,0) | DD23: ='Investment Analysis'!IP23 | DF23: =IF(DE23>0,(DE23-DF$5)/DF$5,0) | DG23: ='Investment Analysis'!IW23 | DH23: 12470 | DI23: =IF(DH23>0,(DH23-DI$5)/DI$5,0) | DJ23: ='Investment Analysis'!JD23 | DK23: 2231 | DL23: =IF(DK23>0,(DK23-DL$5)/DL$5,0) | DM23: ='Investment Analysis'!JK23 | DN23: 5476.5 | DO23: =IF(DN23>0,(DN23-DO$5)/DO$5,0) | DP23: ='Investment Analysis'!HU23 | DQ23: 29472 | DR23: =IF(DQ23>0,(DQ23-DR$5)/DR$5,0) | DS23: ='Investment Analysis'!JR23 | DT23: 5114 | DU23: =IF(DT23>0,(DT23-DU$5)/DU$5,0) | DV23: ='Investment Analysis'!JY23 | DW23: 23617.5 | DX23: =IF(DW23>0,(DW23-DX$5)/DX$5,0) | DY23: ='Investment Analysis'!KF23 | DZ23: 2421.6 | EA23: =IF(DZ23>0,(DZ23-EA$5)/EA$5,0) | EB23: ='Investment Analysis'!KM23 | EC23: 2238.3 | ED23: =IF(EC23>0,(EC23-ED$5)/ED$5,0) | EE23: ='Investment Analysis'!KT23 | EF23: 40050 | EG23: =IF(EF23>0,(EF23-EG$5)/EG$5,0) | EH23: ='Investment Analysis'!LH23 | EI23: 8298.39 | EJ23: =IF(EI23>0,(EI23-EJ$5)/EJ$5,0) | EK23: ='Investment Analysis'!LO23 | EM23: =IF(EL23>0,(EL23-EM$5)/EM$5,0) | EN23: ='Investment Analysis'!LV23 | EP23: =IF(EO23>0,(EO23-EP$5)/EP$5,0) | EQ23: ='Investment Analysis'!MC23 | ER23: 25878.91 | ES23: =IF(ER23>0,(ER23-ES$5)/ES$5,0) | ET23: ='Investment Analysis'!LA23 | EU23: 47838 | EV23: ='Investment Analysis'!ML23 | EW23: ='Investment Analysis'!MJ23 | EX23: 44915.5 | EY23: =IF(EX23>0,(EX23-EY$5)/EY$5,0) | EZ23: ='Investment Analysis'!MQ23 | FB23: =IF(FA23>0,(FA23-FB$5)/FB$5,0) | FC23: ='Investment Analysis'!MX23 | FD23: 4709 | FE23: =IF(FD23>0,(FD23-FE$5)/FE$5,0) | FF23: ='Investment Analysis'!NE23 | FH23: =IF(FG23>0,(FG23-FH$5)/FH$5,0) | FI23: ='Investment Analysis'!NL23 | FJ23: 10677.5 | FK23: =IF(FJ23>0,(FJ23-FK$5)/FK$5,0) | FL23: ='Investment Analysis'!NS23 | FM23: 31739.2 | FN23: =IF(FM23>0,(FM23-FN$5)/FN$5,0) | FO23: ='Investment Analysis'!NZ23 | FQ23: =IF(FP23>0,(FP23-FQ$5)/FQ$5,0) | FR23: ='Investment Analysis'!OG23 | FS23: 43134.75 | FT23: =IF(FS23>0,(FS23-FT$5)/FT$5,0) | FU23: ='Investment Analysis'!ON23 | FW23: =IF(FV23>0,(FV23-FW$5)/FW$5,0) | FX23: ='Investment Analysis'!OU23 | FZ23: =IF(FY23>0,(FY23-FZ$5)/FZ$5,0) | GA23: ='Investment Analysis'!PB23 | GC23: ='Investment Analysis'!PK23 | GD23: ='Investment Analysis'!PI23 | GE23: 6934 | GF23: ='Investment Analysis'!PY23 | GG23: ='Investment Analysis'!PW23 | GH23: 34010 | GI23: ='Investment Analysis'!QF23 | GJ23: ='Investment Analysis'!QD23 | GK23: 24578 | GL23: ='Investment Analysis'!QM23 | GM23: ='Investment Analysis'!QK23 | GN23: 32560.64 | GO23: ='Investment Analysis'!QT23 | GP23: ='Investment Analysis'!QR23 | GQ23: 17396.15 | GR23: ='Investment Analysis'!RA23 | GS23: ='Investment Analysis'!QY23 | GT23: 18686 | GU23: ='Investment Analysis'!RH23 | GV23: ='Investment Analysis'!RF23 | GX23: ='Investment Analysis'!RO23 | GY23: ='Investment Analysis'!RM23 | HA23: ='Investment Analysis'!RV23 | HB23: ='Investment Analysis'!RT23 | HD23: ='Investment Analysis'!SC23 | HE23: ='Investment Analysis'!SA23 | HG23: ='Investment Analysis'!SJ23 | HH23: ='Investment Analysis'!SH23 | HJ23: ='Investment Analysis'!SM23 | HK23: ='Investment Analysis'!SK23 | HM23: ='Investment Analysis'!SP23 | HN23: ='Investment Analysis'!SN23 | HP23: ='Investment Analysis'!TE23 | HQ23: ='Investment Analysis'!TC23 | HS23: ='Investment Analysis'!TL23 | HT23: ='Investment Analysis'!TJ23 | HV23: ='Investment Analysis'!TS23 | HW23: ='Investment Analysis'!TQ23 | HY23: ='Investment Analysis'!TZ23 | HZ23: ='Investment Analysis'!TX23 | IB23: ='Investment Analysis'!UG23 | IC23: ='Investment Analysis'!UE23 | IE23: ='Investment Analysis'!UN23 | IF23: ='Investment Analysis'!UL23 | IH23: ='Investment Analysis'!UU23 | II23: ='Investment Analysis'!US23 | IK23: ='Investment Analysis'!VB23 | IL23: ='Investment Analysis'!UZ23 | IN23: ='Investment Analysis'!VI23 | IO23: ='Investment Analysis'!VG23 | IS23: =IF(IT23>0,IT23-IT22,0) | IT23: =FY23+FV23+FS23+FP23+FM23+FJ23+FG23+FD23+FA23+EX23+EU23+ER23+EO23+EL23+EI23+EF23+EC23+DZ23+DW23+DT23+DQ23+DN23+DK23+DH23+DE23+DB23+CY23+CV23+CS23+CP23+CJ23+CG23+CD23+CA23+BX23+P23+CM23+GT23+GQ23+GN23+GK23+GH23+GE23+GB23+BU23+BR23+BO23+BL23+BI23+BF23+BC23+AZ23+AW23+AT23+AQ23+AN23+AK23+AH23+AE23+AB23+Y23+V23+S23+GW23+GZ23+HC23+HF23+HI23+HL23+HO23+HR23+HU23 | IU23: =IF(IT23>0,IV23,0) | IW23: =IF(IT23>0,(IT23+IV$11-I$2)/I$2,0) | IX23: =IF(IT23>0,IT23+IV$11-I$2,0) | IY23: =IF(IT23>0,(IT23+IV$11-IT$8)/IT$8,0) | IZ23: =IF(IT23>0,IT23+IV$11-IT$8,0)
A24: ='Investment Analysis'!A24 | B24: ='Investment Analysis'!B24 | C24: ='Investment Analysis'!C24 | D24: ='Investment Analysis'!D24 | E24: ='Investment Analysis'!E24 | F24: ='Investment Analysis'!G24 | G24: ='Investment Analysis'!H24 | H24: ='Investment Analysis'!I24 | I24: ='Investment Analysis'!K24 | J24: ='Investment Analysis'!L24 | K24: ='Investment Analysis'!M24 | L24: ='Investment Analysis'!T24 | M24: ='Investment Analysis'!V24 | N24: ='Investment Analysis'!W24 | P24: ='Investment Analysis'!Y24 | S24: 23382.64 | T24: =IF(S24>0,(S24-T$5)/T$5,0) | U24: ='Investment Analysis'!AF24 | V24: 18668.24 | W24: =IF(V24>0,(V24-W$5)/W$5,0) | X24: ='Investment Analysis'!AT24 | Y24: 10031.59 | Z24: =IF(Y24>0,(Y24-Z$5)/Z$5,0) | AA24: ='Investment Analysis'!GK24 | AB24: 2768.09 | AC24: =IF(AB24>0,(AB24-AC$5)/AC$5,0) | AD24: ='Investment Analysis'!AT24 | AE24: 23182.61 | AF24: =IF(AE24>0,(AE24-AF$5)/AF$5,0) | AG24: ='Investment Analysis'!BA24 | AI24: =IF(AH24>0,(AH24-AI$5)/AI$5,0) | AJ24: ='Investment Analysis'!BH24 | AK24: 20419.03 | AL24: =IF(AK24>0,(AK24-AL$5)/AL$5,0) | AM24: ='Investment Analysis'!BO24 | AN24: 15980.13 | AO24: =IF(AN24>0,(AN24-AO$5)/AO$5,0) | AP24: ='Investment Analysis'!BV24 | AR24: =IF(AQ24>0,(AQ24-AR$5)/AR$5,0) | AS24: ='Investment Analysis'!CC24 | AT24: 28637.04 | AU24: =IF(AT24>0,(AT24-AU$5)/AU$5,0) | AV24: ='Investment Analysis'!CJ24 | AW24: 20187.41 | AX24: =IF(AW24>0,(AW24-AX$5)/AX$5,0) | AY24: ='Investment Analysis'!CQ24 | AZ24: 17632.34 | BA24: =IF(AZ24>0,(AZ24-BA$5)/BA$5,0) | BB24: ='Investment Analysis'!CX24 | BC24: 10504.17 | BD24: =IF(BC24>0,(BC24-BD$5)/BD$5,0) | BE24: ='Investment Analysis'!DE24 | BF24: 4387.29 | BG24: =IF(BF24>0,(BF24-BG$5)/BG$5,0) | BH24: ='Investment Analysis'!DL24 | BI24: 2752.39 | BJ24: =IF(BI24>0,(BI24-BJ$5)/BJ$5,0) | BK24: ='Investment Analysis'!DZ24 | BL24: 4537.93 | BM24: =IF(BL24>0,(BL24-BM$5)/BM$5,0) | BN24: ='Investment Analysis'!EG24 | BP24: =IF(BO24>0,(BO24-BP$5)/BP$5,0) | BQ24: ='Investment Analysis'!DS24 | BR24: 5941.19 | BS24: =IF(BR24>0,(BR24-BS$5)/BS$5,0) | BT24: ='Investment Analysis'!EN24 | BU24: 15072.96 | BV24: =IF(BU24>0,(BU24-BV$5)/BV$5,0) | BW24: ='Investment Analysis'!EU24 | BY24: =IF(BX24>0,(BX24-BY$5)/BY$5,0) | BZ24: ='Investment Analysis'!FB24 | CA24: 23216.31 | CB24: =IF(CA24>0,(CA24-CB$5)/CB$5,0) | CC24: ='Investment Analysis'!FI24 | CD24: 20272.97 | CE24: =IF(CD24>0,(CD24-CE$5)/CE$5,0) | CF24: ='Investment Analysis'!FP24 | CG24: 5099.74 | CH24: =IF(CG24>0,(CG24-CH$5)/CH$5,0) | CI24: ='Investment Analysis'!FW24 | CK24: =IF(CJ24>0,(CJ24-CK$5)/CK$5,0) | CL24: ='Investment Analysis'!GD24 | CM24: 25368.27 | CN24: =IF(CM24>0,(CM24-CN$5)/CN$5,0) | CO24: ='Investment Analysis'!GT24 | CP24: 61857 | CQ24: =IF(CP24>0,(CP24-CQ$5)/CQ$5,0) | CR24: ='Investment Analysis'!HG24 | CS24: 6960 | CT24: =IF(CS24>0,(CS24-CT$5)/CT$5,0) | CU24: ='Investment Analysis'!HN24 | CV24: 29444 | CW24: =IF(CV24>0,(CV24-CW$5)/CW$5,0) | CX24: ='Investment Analysis'!IB24 | CY24: 24028 | CZ24: =IF(CY24>0,(CY24-CZ$5)/CZ$5,0) | DA24: ='Investment Analysis'!II24 | DC24: =IF(DB24>0,(DB24-DC$5)/DC$5,0) | DD24: ='Investment Analysis'!IP24 | DF24: =IF(DE24>0,(DE24-DF$5)/DF$5,0) | DG24: ='Investment Analysis'!IW24 | DH24: 12729 | DI24: =IF(DH24>0,(DH24-DI$5)/DI$5,0) | DJ24: ='Investment Analysis'!JD24 | DK24: 2233.55 | DL24: =IF(DK24>0,(DK24-DL$5)/DL$5,0) | DM24: ='Investment Analysis'!JK24 | DN24: 5507.5 | DO24: =IF(DN24>0,(DN24-DO$5)/DO$5,0) | DP24: ='Investment Analysis'!HU24 | DQ24: 29235 | DR24: =IF(DQ24>0,(DQ24-DR$5)/DR$5,0) | DS24: ='Investment Analysis'!JR24 | DT24: 5816 | DU24: =IF(DT24>0,(DT24-DU$5)/DU$5,0) | DV24: ='Investment Analysis'!JY24 | DW24: 23554 | DX24: =IF(DW24>0,(DW24-DX$5)/DX$5,0) | DY24: ='Investment Analysis'!KF24 | DZ24: 2414.4 | EA24: =IF(DZ24>0,(DZ24-EA$5)/EA$5,0) | EB24: ='Investment Analysis'!KM24 | EC24: 2236.6 | ED24: =IF(EC24>0,(EC24-ED$5)/ED$5,0) | EE24: ='Investment Analysis'!KT24 | EF24: 40185 | EG24: =IF(EF24>0,(EF24-EG$5)/EG$5,0) | EH24: ='Investment Analysis'!LH24 | EI24: 8249.1 | EJ24: =IF(EI24>0,(EI24-EJ$5)/EJ$5,0) | EK24: ='Investment Analysis'!LO24 | EM24: =IF(EL24>0,(EL24-EM$5)/EM$5,0) | EN24: ='Investment Analysis'!LV24 | EP24: =IF(EO24>0,(EO24-EP$5)/EP$5,0) | EQ24: ='Investment Analysis'!MC24 | ER24: 26086.6 | ES24: =IF(ER24>0,(ER24-ES$5)/ES$5,0) | ET24: ='Investment Analysis'!LA24 | EU24: 54292 | EV24: ='Investment Analysis'!ML24 | EW24: ='Investment Analysis'!MJ24 | EX24: 44961 | EY24: =IF(EX24>0,(EX24-EY$5)/EY$5,0) | EZ24: ='Investment Analysis'!MQ24 | FB24: =IF(FA24>0,(FA24-FB$5)/FB$5,0) | FC24: ='Investment Analysis'!MX24 | FD24: 5020 | FE24: =IF(FD24>0,(FD24-FE$5)/FE$5,0) | FF24: ='Investment Analysis'!NE24 | FH24: =IF(FG24>0,(FG24-FH$5)/FH$5,0) | FI24: ='Investment Analysis'!NL24 | FJ24: 10942.75 | FK24: =IF(FJ24>0,(FJ24-FK$5)/FK$5,0) | FL24: ='Investment Analysis'!NS24 | FM24: 31676.8 | FN24: =IF(FM24>0,(FM24-FN$5)/FN$5,0) | FO24: ='Investment Analysis'!NZ24 | FQ24: =IF(FP24>0,(FP24-FQ$5)/FQ$5,0) | FR24: ='Investment Analysis'!OG24 | FS24: 44745 | FT24: =IF(FS24>0,(FS24-FT$5)/FT$5,0) | FU24: ='Investment Analysis'!ON24 | FW24: =IF(FV24>0,(FV24-FW$5)/FW$5,0) | FX24: ='Investment Analysis'!OU24 | FZ24: =IF(FY24>0,(FY24-FZ$5)/FZ$5,0) | GA24: ='Investment Analysis'!PB24 | GC24: ='Investment Analysis'!PK24 | GD24: ='Investment Analysis'!PI24 | GE24: 6940.5 | GF24: ='Investment Analysis'!PY24 | GG24: ='Investment Analysis'!PW24 | GH24: 34113.75 | GI24: ='Investment Analysis'!QF24 | GJ24: ='Investment Analysis'!QD24 | GK24: 25086 | GL24: ='Investment Analysis'!QM24 | GM24: ='Investment Analysis'!QK24 | GN24: 32321.9 | GO24: ='Investment Analysis'!QT24 | GP24: ='Investment Analysis'!QR24 | GQ24: 17390.25 | GR24: ='Investment Analysis'!RA24 | GS24: ='Investment Analysis'!QY24 | GT24: 19189 | GU24: ='Investment Analysis'!RH24 | GV24: ='Investment Analysis'!RF24 | GX24: ='Investment Analysis'!RO24 | GY24: ='Investment Analysis'!RM24 | HA24: ='Investment Analysis'!RV24 | HB24: ='Investment Analysis'!RT24 | HD24: ='Investment Analysis'!SC24 | HE24: ='Investment Analysis'!SA24 | HG24: ='Investment Analysis'!SJ24 | HH24: ='Investment Analysis'!SH24 | HJ24: ='Investment Analysis'!SM24 | HK24: ='Investment Analysis'!SK24 | HM24: ='Investment Analysis'!SP24 | HN24: ='Investment Analysis'!SN24 | HP24: ='Investment Analysis'!TE24 | HQ24: ='Investment Analysis'!TC24 | HS24: ='Investment Analysis'!TL24 | HT24: ='Investment Analysis'!TJ24 | HV24: ='Investment Analysis'!TS24 | HW24: ='Investment Analysis'!TQ24 | HY24: ='Investment Analysis'!TZ24 | HZ24: ='Investment Analysis'!TX24 | IB24: ='Investment Analysis'!UG24 | IC24: ='Investment Analysis'!UE24 | IE24: ='Investment Analysis'!UN24 | IF24: ='Investment Analysis'!UL24 | IH24: ='Investment Analysis'!UU24 | II24: ='Investment Analysis'!US24 | IK24: ='Investment Analysis'!VB24 | IL24: ='Investment Analysis'!UZ24 | IN24: ='Investment Analysis'!VI24 | IO24: ='Investment Analysis'!VG24 | IS24: =IF(IT24>0,IT24-IT23,0) | IT24: =FY24+FV24+FS24+FP24+FM24+FJ24+FG24+FD24+FA24+EX24+EU24+ER24+EO24+EL24+EI24+EF24+EC24+DZ24+DW24+DT24+DQ24+DN24+DK24+DH24+DE24+DB24+CY24+CV24+CS24+CP24+CJ24+CG24+CD24+CA24+BX24+P24+CM24+GT24+GQ24+GN24+GK24+GH24+GE24+GB24+BU24+BR24+BO24+BL24+BI24+BF24+BC24+AZ24+AW24+AT24+AQ24+AN24+AK24+AH24+AE24+AB24+Y24+V24+S24+GW24+GZ24+HC24+HF24+HI24+HL24+HO24+HR24+HU24 | IU24: =IF(IT24>0,IV24,0) | IW24: =IF(IT24>0,(IT24+IV$11-I$2)/I$2,0) | IX24: =IF(IT24>0,IT24+IV$11-I$2,0) | IY24: =IF(IT24>0,(IT24+IV$11-IT$8)/IT$8,0) | IZ24: =IF(IT24>0,IT24+IV$11-IT$8,0)
A25: ='Investment Analysis'!A25 | B25: ='Investment Analysis'!B25 | C25: ='Investment Analysis'!C25 | D25: ='Investment Analysis'!D25 | E25: ='Investment Analysis'!E25 | F25: ='Investment Analysis'!G25 | G25: ='Investment Analysis'!H25 | H25: ='Investment Analysis'!I25 | I25: ='Investment Analysis'!K25 | J25: ='Investment Analysis'!L25 | K25: ='Investment Analysis'!M25 | L25: ='Investment Analysis'!T25 | M25: ='Investment Analysis'!V25 | N25: ='Investment Analysis'!W25 | P25: ='Investment Analysis'!Y25 | S25: 23261.85 | T25: =IF(S25>0,(S25+10000-T$5)/T$5,0) | U25: ='Investment Analysis'!AF25 | V25: 18659.88 | W25: =IF(V25>0,(V25+5000-W$5)/W$5,0) | X25: ='Investment Analysis'!AT25 | Y25: 9989.67 | Z25: =IF(Y25>0,(Y25-Z$5)/Z$5,0) | AA25: ='Investment Analysis'!GK25 | AB25: 2755.78 | AC25: =IF(AB25>0,(AB25+8000-AC$5)/AC$5,0) | AD25: ='Investment Analysis'!AT25 | AE25: 23118.26 | AF25: =IF(AE25>0,(AE25-AF$5)/AF$5,0) | AG25: ='Investment Analysis'!BA25 | AI25: =IF(AH25>0,(AH25-AI$5)/AI$5,0) | AJ25: ='Investment Analysis'!BH25 | AK25: 20348.54 | AL25: =IF(AK25>0,(AK25+7000-AL$5)/AL$5,0) | AM25: ='Investment Analysis'!BO25 | AN25: 15919.33 | AO25: =IF(AN25>0,(AN25-AO$5)/AO$5,0) | AP25: ='Investment Analysis'!BV25 | AR25: =IF(AQ25>0,(AQ25+10000-AR$5)/AR$5,0) | AS25: ='Investment Analysis'!CC25 | AT25: 28581.97 | AU25: =IF(AT25>0,(AT25+10000-AU$5)/AU$5,0) | AV25: ='Investment Analysis'!CJ25 | AW25: 20084.64 | AX25: =IF(AW25>0,(AW25+2000-AX$5)/AX$5,0) | AY25: ='Investment Analysis'!CQ25 | AZ25: 17560.63 | BA25: =IF(AZ25>0,(AZ25+15000-BA$5)/BA$5,0) | BB25: ='Investment Analysis'!CX25 | BC25: 10528.65 | BD25: =IF(BC25>0,(BC25-BD$5)/BD$5,0) | BE25: ='Investment Analysis'!DE25 | BF25: 4410.02 | BG25: =IF(BF25>0,(BF25-BG$5)/BG$5,0) | BH25: ='Investment Analysis'!DL25 | BI25: 2703.91 | BJ25: =IF(BI25>0,(BI25-BJ$5)/BJ$5,0) | BK25: ='Investment Analysis'!DZ25 | BL25: 4479.88 | BM25: =IF(BL25>0,(BL25-BM$5)/BM$5,0) | BN25: ='Investment Analysis'!EG25 | BP25: =IF(BO25>0,(BO25+5000-BP$5)/BP$5,0) | BQ25: ='Investment Analysis'!DS25 | BR25: 5994.7 | BS25: =IF(BR25>0,(BR25-BS$5)/BS$5,0) | BT25: ='Investment Analysis'!EN25 | BU25: 15145.04 | BV25: =IF(BU25>0,(BU25+8000-BV$5)/BV$5,0) | BW25: ='Investment Analysis'!EU25 | BY25: =IF(BX25>0,(BX25-BY$5)/BY$5,0) | BZ25: ='Investment Analysis'!FB25 | CA25: 22992.01 | CB25: =IF(CA25>0,(CA25-CB$5)/CB$5,0) | CC25: ='Investment Analysis'!FI25 | CD25: 20387.4 | CE25: =IF(CD25>0,(CD25+20000-CE$5)/CE$5,0) | CF25: ='Investment Analysis'!FP25 | CG25: 5119.87 | CH25: =IF(CG25>0,(CG25+10000-CH$5)/CH$5,0) | CI25: ='Investment Analysis'!FW25 | CK25: =IF(CJ25>0,(CJ25-CK$5)/CK$5,0) | CL25: ='Investment Analysis'!GD25 | CM25: 25420.83 | CN25: =IF(CM25>0,(CM25-CN$5)/CN$5,0) | CO25: ='Investment Analysis'!GT25 | CP25: 60987 | CQ25: =IF(CP25>0,(CP25-CQ$5)/CQ$5,0) | CR25: ='Investment Analysis'!HG25 | CS25: 6990 | CT25: =IF(CS25>0,(CS25-CT$5)/CT$5,0) | CU25: ='Investment Analysis'!HN25 | CV25: 28524 | CW25: =IF(CV25>0,(CV25-CW$5)/CW$5,0) | CX25: ='Investment Analysis'!IB25 | CY25: 24470 | CZ25: =IF(CY25>0,(CY25-CZ$5)/CZ$5,0) | DA25: ='Investment Analysis'!II25 | DC25: =IF(DB25>0,(DB25-DC$5)/DC$5,0) | DD25: ='Investment Analysis'!IP25 | DF25: =IF(DE25>0,(DE25-DF$5)/DF$5,0) | DG25: ='Investment Analysis'!IW25 | DH25: 12949.8 | DI25: =IF(DH25>0,(DH25-DI$5)/DI$5,0) | DJ25: ='Investment Analysis'!JD25 | DK25: 2220.3 | DL25: =IF(DK25>0,(DK25-DL$5)/DL$5,0) | DM25: ='Investment Analysis'!JK25 | DN25: 5433 | DO25: =IF(DN25>0,(DN25-DO$5)/DO$5,0) | DP25: ='Investment Analysis'!HU25 | DQ25: 29070 | DR25: =IF(DQ25>0,(DQ25-DR$5)/DR$5,0) | DS25: ='Investment Analysis'!JR25 | DT25: 5594 | DU25: =IF(DT25>0,(DT25-DU$5)/DU$5,0) | DV25: ='Investment Analysis'!JY25 | DW25: 23492 | DX25: =IF(DW25>0,(DW25-DX$5)/DX$5,0) | DY25: ='Investment Analysis'!KF25 | DZ25: 2472 | EA25: =IF(DZ25>0,(DZ25-EA$5)/EA$5,0) | EB25: ='Investment Analysis'!KM25 | EC25: 2227.8 | ED25: =IF(EC25>0,(EC25-ED$5)/ED$5,0) | EE25: ='Investment Analysis'!KT25 | EF25: 40260 | EG25: =IF(EF25>0,(EF25-EG$5)/EG$5,0) | EH25: ='Investment Analysis'!LH25 | EI25: 8364.42 | EJ25: =IF(EI25>0,(EI25-EJ$5)/EJ$5,0) | EK25: ='Investment Analysis'!LO25 | EM25: =IF(EL25>0,(EL25-EM$5)/EM$5,0) | EN25: ='Investment Analysis'!LV25 | EP25: =IF(EO25>0,(EO25-EP$5)/EP$5,0) | EQ25: ='Investment Analysis'!MC25 | ER25: 25874.54 | ES25: =IF(ER25>0,(ER25-ES$5)/ES$5,0) | ET25: ='Investment Analysis'!LA25 | EU25: 58548 | EV25: ='Investment Analysis'!ML25 | EW25: ='Investment Analysis'!MJ25 | EX25: 44677.5 | EY25: =IF(EX25>0,(EX25-EY$5)/EY$5,0) | EZ25: ='Investment Analysis'!MQ25 | FB25: =IF(FA25>0,(FA25-FB$5)/FB$5,0) | FC25: ='Investment Analysis'!MX25 | FD25: 4918.75 | FE25: =IF(FD25>0,(FD25-FE$5)/FE$5,0) | FF25: ='Investment Analysis'!NE25 | FH25: =IF(FG25>0,(FG25-FH$5)/FH$5,0) | FI25: ='Investment Analysis'!NL25 | FJ25: 10512.25 | FK25: =IF(FJ25>0,(FJ25-FK$5)/FK$5,0) | FL25: ='Investment Analysis'!NS25 | FM25: 32033.6 | FN25: =IF(FM25>0,(FM25-FN$5)/FN$5,0) | FO25: ='Investment Analysis'!NZ25 | FQ25: =IF(FP25>0,(FP25-FQ$5)/FQ$5,0) | FR25: ='Investment Analysis'!OG25 | FS25: 43700 | FT25: =IF(FS25>0,(FS25-FT$5)/FT$5,0) | FU25: ='Investment Analysis'!ON25 | FW25: =IF(FV25>0,(FV25-FW$5)/FW$5,0) | FX25: ='Investment Analysis'!OU25 | FZ25: =IF(FY25>0,(FY25-FZ$5)/FZ$5,0) | GA25: ='Investment Analysis'!PB25 | GC25: ='Investment Analysis'!PK25 | GD25: ='Investment Analysis'!PI25 | GE25: 6972 | GF25: ='Investment Analysis'!PY25 | GG25: ='Investment Analysis'!PW25 | GH25: 34123.75 | GI25: ='Investment Analysis'!QF25 | GJ25: ='Investment Analysis'!QD25 | GK25: 0 | GL25: ='Investment Analysis'!QM25 | GM25: ='Investment Analysis'!QK25 | GN25: 31281.38 | GO25: ='Investment Analysis'!QT25 | GP25: ='Investment Analysis'!QR25 | GQ25: 17700 | GR25: ='Investment Analysis'!RA25 | GS25: ='Investment Analysis'!QY25 | GT25: 19111 | GU25: ='Investment Analysis'!RH25 | GV25: ='Investment Analysis'!RF25 | GX25: ='Investment Analysis'!RO25 | GY25: ='Investment Analysis'!RM25 | HA25: ='Investment Analysis'!RV25 | HB25: ='Investment Analysis'!RT25 | HD25: ='Investment Analysis'!SC25 | HE25: ='Investment Analysis'!SA25 | HG25: ='Investment Analysis'!SJ25 | HH25: ='Investment Analysis'!SH25 | HJ25: ='Investment Analysis'!SM25 | HK25: ='Investment Analysis'!SK25 | HM25: ='Investment Analysis'!SP25 | HN25: ='Investment Analysis'!SN25 | HP25: ='Investment Analysis'!TE25 | HQ25: ='Investment Analysis'!TC25 | HS25: ='Investment Analysis'!TL25 | HT25: ='Investment Analysis'!TJ25 | HV25: ='Investment Analysis'!TS25 | HW25: ='Investment Analysis'!TQ25 | HY25: ='Investment Analysis'!TZ25 | HZ25: ='Investment Analysis'!TX25 | IB25: ='Investment Analysis'!UG25 | IC25: ='Investment Analysis'!UE25 | IE25: ='Investment Analysis'!UN25 | IF25: ='Investment Analysis'!UL25 | IH25: ='Investment Analysis'!UU25 | II25: ='Investment Analysis'!US25 | IK25: ='Investment Analysis'!VB25 | IL25: ='Investment Analysis'!UZ25 | IN25: ='Investment Analysis'!VI25 | IO25: ='Investment Analysis'!VG25 | IS25: =IF(IT25>0,IT25-IT24,0) | IT25: =FY25+FV25+FS25+FP25+FM25+FJ25+FG25+FD25+FA25+EX25+EU25+ER25+EO25+EL25+EI25+EF25+EC25+DZ25+DW25+DT25+DQ25+DN25+DK25+DH25+DE25+DB25+CY25+CV25+CS25+CP25+CJ25+CG25+CD25+CA25+BX25+P25+CM25+GT25+GQ25+GN25+GK25+GH25+GE25+GB25+BU25+BR25+BO25+BL25+BI25+BF25+BC25+AZ25+AW25+AT25+AQ25+AN25+AK25+AH25+AE25+AB25+Y25+V25+S25+GW25+GZ25+HC25+HF25+HI25+HL25+HO25+HR25+HU25 | IU25: =IF(IT25>0,IV25,0) | IW25: =IF(IT25>0,(IT25+IV$11-I$2)/I$2,0) | IX25: =IF(IT25>0,IT25+IV$11-I$2,0) | IY25: =IF(IT25>0,(IT25+IV$11-IT$8)/IT$8,0) | IZ25: =IF(IT25>0,IT25+IV$11-IT$8,0)
A26: ='Investment Analysis'!A26 | B26: ='Investment Analysis'!B26 | C26: ='Investment Analysis'!C26 | D26: ='Investment Analysis'!D26 | E26: ='Investment Analysis'!E26 | F26: ='Investment Analysis'!G26 | G26: ='Investment Analysis'!H26 | H26: ='Investment Analysis'!I26 | I26: ='Investment Analysis'!K26 | J26: ='Investment Analysis'!L26 | K26: ='Investment Analysis'!M26 | L26: ='Investment Analysis'!T26 | M26: ='Investment Analysis'!V26 | N26: ='Investment Analysis'!W26 | P26: ='Investment Analysis'!Y26 | S26: 22335.81 | T26: =IF(S26>0,(S26+10000-T$5)/T$5,0) | U26: ='Investment Analysis'!AF26 | V26: 18241.68 | W26: =IF(V26>0,(V26+5000-W$5)/W$5,0) | X26: ='Investment Analysis'!AT26 | Y26: 10063.04 | Z26: =IF(Y26>0,(Y26-Z$5)/Z$5,0) | AA26: ='Investment Analysis'!GK26 | AB26: 2635.11 | AC26: =IF(AB26>0,(AB26+8000-AC$5)/AC$5,0) | AD26: ='Investment Analysis'!AT26 | AE26: 22781.24 | AF26: =IF(AE26>0,(AE26+30000-AF$5)/AF$5,0) | AG26: ='Investment Analysis'!BA26 | AI26: =IF(AH26>0,(AH26-AI$5)/AI$5,0) | AJ26: ='Investment Analysis'!BH26 | AK26: 19522.42 | AL26: =IF(AK26>0,(AK26+7000-AL$5)/AL$5,0) | AM26: ='Investment Analysis'!BO26 | AN26: 14798.25 | AO26: =IF(AN26>0,(AN26-AO$5)/AO$5,0) | AP26: ='Investment Analysis'!BV26 | AR26: =IF(AQ26>0,(AQ26+10000-AR$5)/AR$5,0) | AS26: ='Investment Analysis'!CC26 | AT26: 28330.21 | AU26: =IF(AT26>0,(AT26+10000-AU$5)/AU$5,0) | AV26: ='Investment Analysis'!CJ26 | AW26: 19616.5 | AX26: =IF(AW26>0,(AW26+2000-AX$5)/AX$5,0) | AY26: ='Investment Analysis'!CQ26 | AZ26: 17202.06 | BA26: =IF(AZ26>0,(AZ26+15000-BA$5)/BA$5,0) | BB26: ='Investment Analysis'!CX26 | BC26: 10445.4 | BD26: =IF(BC26>0,(BC26-BD$5)/BD$5,0) | BE26: ='Investment Analysis'!DE26 | BF26: 4358.64 | BG26: =IF(BF26>0,(BF26-BG$5)/BG$5,0) | BH26: ='Investment Analysis'!DL26 | BI26: 2386.47 | BJ26: =IF(BI26>0,(BI26-BJ$5)/BJ$5,0) | BK26: ='Investment Analysis'!DZ26 | BL26: 4231.06 | BM26: =IF(BL26>0,(BL26-BM$5)/BM$5,0) | BN26: ='Investment Analysis'!EG26 | BP26: =IF(BO26>0,(BO26+5000-BP$5)/BP$5,0) | BQ26: ='Investment Analysis'!DS26 | BR26: 5941.69 | BS26: =IF(BR26>0,(BR26-BS$5)/BS$5,0) | BT26: ='Investment Analysis'!EN26 | BU26: 15137.46 | BV26: =IF(BU26>0,(BU26+8000-BV$5)/BV$5,0) | BW26: ='Investment Analysis'!EU26 | BY26: =IF(BX26>0,(BX26-BY$5)/BY$5,0) | BZ26: ='Investment Analysis'!FB26 | CA26: 22581.44 | CB26: =IF(CA26>0,(CA26-CB$5)/CB$5,0) | CC26: ='Investment Analysis'!FI26 | CD26: 20083.64 | CE26: =IF(CD26>0,(CD26+20000-CE$5)/CE$5,0) | CF26: ='Investment Analysis'!FP26 | CG26: 5238.95 | CH26: =IF(CG26>0,(CG26+10000-CH$5)/CH$5,0) | CI26: ='Investment Analysis'!FW26 | CK26: =IF(CJ26>0,(CJ26-CK$5)/CK$5,0) | CL26: ='Investment Analysis'!GD26 | CM26: 24439.74 | CN26: =IF(CM26>0,(CM26-CN$5)/CN$5,0) | CO26: ='Investment Analysis'!GT26 | CP26: 59572.5 | CQ26: =IF(CP26>0,(CP26-CQ$5)/CQ$5,0) | CR26: ='Investment Analysis'!HG26 | CS26: 6870 | CT26: =IF(CS26>0,(CS26-CT$5)/CT$5,0) | CU26: ='Investment Analysis'!HN26 | CV26: 23684 | CW26: =IF(CV26>0,(CV26-CW$5)/CW$5,0) | CX26: ='Investment Analysis'!IB26 | CY26: 20213 | CZ26: =IF(CY26>0,(CY26-CZ$5)/CZ$5,0) | DA26: ='Investment Analysis'!II26 | DC26: =IF(DB26>0,(DB26-DC$5)/DC$5,0) | DD26: ='Investment Analysis'!IP26 | DF26: =IF(DE26>0,(DE26-DF$5)/DF$5,0) | DG26: ='Investment Analysis'!IW26 | DH26: 13197.6 | DI26: =IF(DH26>0,(DH26-DI$5)/DI$5,0) | DJ26: ='Investment Analysis'!JD26 | DK26: 2172.8 | DL26: =IF(DK26>0,(DK26-DL$5)/DL$5,0) | DM26: ='Investment Analysis'!JK26 | DN26: 5508.5 | DO26: =IF(DN26>0,(DN26-DO$5)/DO$5,0) | DP26: ='Investment Analysis'!HU26 | DQ26: 29031 | DR26: =IF(DQ26>0,(DQ26-DR$5)/DR$5,0) | DS26: ='Investment Analysis'!JR26 | DT26: 4054 | DU26: =IF(DT26>0,(DT26-DU$5)/DU$5,0) | DV26: ='Investment Analysis'!JY26 | DW26: 24131.25 | DX26: =IF(DW26>0,(DW26-DX$5)/DX$5,0) | DY26: ='Investment Analysis'!KF26 | DZ26: 2416.8 | EA26: =IF(DZ26>0,(DZ26-EA$5)/EA$5,0) | EB26: ='Investment Analysis'!KM26 | EC26: 2298.6 | ED26: =IF(EC26>0,(EC26-ED$5)/ED$5,0) | EE26: ='Investment Analysis'!KT26 | EF26: 36345 | EG26: =IF(EF26>0,(EF26-EG$5)/EG$5,0) | EH26: ='Investment Analysis'!LH26 | EI26: 8320.71 | EJ26: =IF(EI26>0,(EI26-EJ$5)/EJ$5,0) | EK26: ='Investment Analysis'!LO26 | EM26: =IF(EL26>0,(EL26-EM$5)/EM$5,0) | EN26: ='Investment Analysis'!LV26 | EP26: =IF(EO26>0,(EO26-EP$5)/EP$5,0) | EQ26: ='Investment Analysis'!MC26 | ER26: 26234.26 | ES26: =IF(ER26>0,(ER26-ES$5)/ES$5,0) | ET26: ='Investment Analysis'!LA26 | EU26: 43554 | EV26: ='Investment Analysis'!ML26 | EW26: ='Investment Analysis'!MJ26 | EX26: 39011 | EY26: =IF(EX26>0,(EX26-EY$5)/EY$5,0) | EZ26: ='Investment Analysis'!MQ26 | FB26: =IF(FA26>0,(FA26-FB$5)/FB$5,0) | FC26: ='Investment Analysis'!MX26 | FD26: 4861.5 | FE26: =IF(FD26>0,(FD26-FE$5)/FE$5,0) | FF26: ='Investment Analysis'!NE26 | FH26: =IF(FG26>0,(FG26-FH$5)/FH$5,0) | FI26: ='Investment Analysis'!NL26 | FJ26: 8250 | FK26: =IF(FJ26>0,(FJ26-FK$5)/FK$5,0) | FL26: ='Investment Analysis'!NS26 | FM26: 30689.6 | FN26: =IF(FM26>0,(FM26-FN$5)/FN$5,0) | FO26: ='Investment Analysis'!NZ26 | FQ26: =IF(FP26>0,(FP26-FQ$5)/FQ$5,0) | FR26: ='Investment Analysis'!OG26 | FS26: 37140.25 | FT26: =IF(FS26>0,(FS26-FT$5)/FT$5,0) | FU26: ='Investment Analysis'!ON26 | FW26: =IF(FV26>0,(FV26-FW$5)/FW$5,0) | FX26: ='Investment Analysis'!OU26 | FZ26: =IF(FY26>0,(FY26-FZ$5)/FZ$5,0) | GA26: ='Investment Analysis'!PB26 | GC26: ='Investment Analysis'!PK26 | GD26: ='Investment Analysis'!PI26 | GE26: 6920.5 | GF26: ='Investment Analysis'!PY26 | GG26: ='Investment Analysis'!PW26 | GH26: 32876.25 | GI26: ='Investment Analysis'!QF26 | GJ26: ='Investment Analysis'!QD26 | GL26: ='Investment Analysis'!QM26 | GM26: ='Investment Analysis'!QK26 | GN26: 28881.56 | GO26: ='Investment Analysis'!QT26 | GP26: ='Investment Analysis'!QR26 | GQ26: 17466.95 | GR26: ='Investment Analysis'!RA26 | GS26: ='Investment Analysis'!QY26 | GT26: 13708 | GU26: ='Investment Analysis'!RH26 | GV26: ='Investment Analysis'!RF26 | GX26: ='Investment Analysis'!RO26 | GY26: ='Investment Analysis'!RM26 | HA26: ='Investment Analysis'!RV26 | HB26: ='Investment Analysis'!RT26 | HD26: ='Investment Analysis'!SC26 | HE26: ='Investment Analysis'!SA26 | HG26: ='Investment Analysis'!SJ26 | HH26: ='Investment Analysis'!SH26 | HJ26: ='Investment Analysis'!SM26 | HK26: ='Investment Analysis'!SK26 | HM26: ='Investment Analysis'!SP26 | HN26: ='Investment Analysis'!SN26 | HP26: ='Investment Analysis'!TE26 | HQ26: ='Investment Analysis'!TC26 | HS26: ='Investment Analysis'!TL26 | HT26: ='Investment Analysis'!TJ26 | HV26: ='Investment Analysis'!TS26 | HW26: ='Investment Analysis'!TQ26 | HY26: ='Investment Analysis'!TZ26 | HZ26: ='Investment Analysis'!TX26 | IB26: ='Investment Analysis'!UG26 | IC26: ='Investment Analysis'!UE26 | IE26: ='Investment Analysis'!UN26 | IF26: ='Investment Analysis'!UL26 | IH26: ='Investment Analysis'!UU26 | II26: ='Investment Analysis'!US26 | IK26: ='Investment Analysis'!VB26 | IL26: ='Investment Analysis'!UZ26 | IN26: ='Investment Analysis'!VI26 | IO26: ='Investment Analysis'!VG26 | IS26: =IF(IT26>0,IT26-IT25,0) | IT26: =FY26+FV26+FS26+FP26+FM26+FJ26+FG26+FD26+FA26+EX26+EU26+ER26+EO26+EL26+EI26+EF26+EC26+DZ26+DW26+DT26+DQ26+DN26+DK26+DH26+DE26+DB26+CY26+CV26+CS26+CP26+CJ26+CG26+CD26+CA26+BX26+P26+CM26+GT26+GQ26+GN26+GK26+GH26+GE26+GB26+BU26+BR26+BO26+BL26+BI26+BF26+BC26+AZ26+AW26+AT26+AQ26+AN26+AK26+AH26+AE26+AB26+Y26+V26+S26+GW26+GZ26+HC26+HF26+HI26+HL26+HO26+HR26+HU26 | IU26: =IF(IT26>0,IV26,0) | IW26: =IF(IT26>0,(IT26+IV$11-I$2)/I$2,0) | IX26: =IF(IT26>0,IT26+IV$11-I$2,0) | IY26: =IF(IT26>0,(IT26+IV$11-IT$8)/IT$8,0) | IZ26: =IF(IT26>0,IT26+IV$11-IT$8,0)
A27: ='Investment Analysis'!A27 | B27: ='Investment Analysis'!B27 | C27: ='Investment Analysis'!C27 | D27: ='Investment Analysis'!D27 | E27: ='Investment Analysis'!E27 | F27: ='Investment Analysis'!G27 | G27: ='Investment Analysis'!H27 | H27: ='Investment Analysis'!I27 | I27: ='Investment Analysis'!K27 | J27: ='Investment Analysis'!L27 | K27: ='Investment Analysis'!M27 | L27: ='Investment Analysis'!T27 | M27: ='Investment Analysis'!V27 | N27: ='Investment Analysis'!W27 | P27: ='Investment Analysis'!Y27 | S27: 22931.89 | T27: =IF(S27>0,(S27+10000-T$5)/T$5,0) | U27: ='Investment Analysis'!AF27 | V27: 18542.78 | W27: =IF(V27>0,(V27+5000-W$5)/W$5,0) | X27: ='Investment Analysis'!AT27 | Y27: 10047.32 | Z27: =IF(Y27>0,(Y27-Z$5)/Z$5,0) | AA27: ='Investment Analysis'!GK27 | AB27: 2702.83 | AC27: =IF(AB27>0,(AB27+8000-AC$5)/AC$5,0) | AD27: ='Investment Analysis'!AT27 | AE27: 22991.74 | AF27: =IF(AE27>0,(AE27+30000-AF$5)/AF$5,0) | AG27: ='Investment Analysis'!BA27 | AI27: =IF(AH27>0,(AH27-AI$5)/AI$5,0) | AJ27: ='Investment Analysis'!BH27 | AK27: 19857.94 | AL27: =IF(AK27>0,(AK27+7000-AL$5)/AL$5,0) | AM27: ='Investment Analysis'!BO27 | AN27: 15033.86 | AO27: =IF(AN27>0,(AN27-AO$5)/AO$5,0) | AP27: ='Investment Analysis'!BV27 | AR27: =IF(AQ27>0,(AQ27+10000-AR$5)/AR$5,0) | AS27: ='Investment Analysis'!CC27 | AT27: 28660.64 | AU27: =IF(AT27>0,(AT27+10000-AU$5)/AU$5,0) | AV27: ='Investment Analysis'!CJ27 | AW27: 19850.57 | AX27: =IF(AW27>0,(AW27+2000-AX$5)/AX$5,0) | AY27: ='Investment Analysis'!CQ27 | AZ27: 17251.37 | BA27: =IF(AZ27>0,(AZ27+15000-BA$5)/BA$5,0) | BB27: ='Investment Analysis'!CX27 | BC27: 10416.02 | BD27: =IF(BC27>0,(BC27-BD$5)/BD$5,0) | BE27: ='Investment Analysis'!DE27 | BF27: 4349.74 | BG27: =IF(BF27>0,(BF27-BG$5)/BG$5,0) | BH27: ='Investment Analysis'!DL27 | BI27: 2455.41 | BJ27: =IF(BI27>0,(BI27-BJ$5)/BJ$5,0) | BK27: ='Investment Analysis'!DZ27 | BL27: 4391.01 | BM27: =IF(BL27>0,(BL27-BM$5)/BM$5,0) | BN27: ='Investment Analysis'!EG27 | BP27: =IF(BO27>0,(BO27+5000-BP$5)/BP$5,0) | BQ27: ='Investment Analysis'!DS27 | BR27: 6040.14 | BS27: =IF(BR27>0,(BR27-BS$5)/BS$5,0) | BT27: ='Investment Analysis'!EN27 | BU27: 15091.93 | BV27: =IF(BU27>0,(BU27+8000-BV$5)/BV$5,0) | BW27: ='Investment Analysis'!EU27 | BY27: =IF(BX27>0,(BX27-BY$5)/BY$5,0) | BZ27: ='Investment Analysis'!FB27 | CA27: 22448.38 | CB27: =IF(CA27>0,(CA27-CB$5)/CB$5,0) | CC27: ='Investment Analysis'!FI27 | CD27: 20275.05 | CE27: =IF(CD27>0,(CD27+20000-CE$5)/CE$5,0) | CF27: ='Investment Analysis'!FP27 | CG27: 5189.19 | CH27: =IF(CG27>0,(CG27+10000-CH$5)/CH$5,0) | CI27: ='Investment Analysis'!FW27 | CK27: =IF(CJ27>0,(CJ27-CK$5)/CK$5,0) | CL27: ='Investment Analysis'!GD27 | CM27: 24439.74 | CN27: =IF(CM27>0,(CM27-CN$5)/CN$5,0) | CO27: ='Investment Analysis'!GT27 | CP27: 59713.5 | CQ27: =IF(CP27>0,(CP27-CQ$5)/CQ$5,0) | CR27: ='Investment Analysis'!HG27 | CS27: 6780 | CT27: =IF(CS27>0,(CS27-CT$5)/CT$5,0) | CU27: ='Investment Analysis'!HN27 | CV27: 25798 | CW27: =IF(CV27>0,(CV27-CW$5)/CW$5,0) | CX27: ='Investment Analysis'!IB27 | CY27: 20736 | CZ27: =IF(CY27>0,(CY27-CZ$5)/CZ$5,0) | DA27: ='Investment Analysis'!II27 | DC27: =IF(DB27>0,(DB27-DC$5)/DC$5,0) | DD27: ='Investment Analysis'!IP27 | DF27: =IF(DE27>0,(DE27-DF$5)/DF$5,0) | DG27: ='Investment Analysis'!IW27 | DH27: 13486.6 | DI27: =IF(DH27>0,(DH27-DI$5)/DI$5,0) | DJ27: ='Investment Analysis'!JD27 | DK27: 2236 | DL27: =IF(DK27>0,(DK27-DL$5)/DL$5,0) | DM27: ='Investment Analysis'!JK27 | DN27: 5402 | DO27: =IF(DN27>0,(DN27-DO$5)/DO$5,0) | DP27: ='Investment Analysis'!HU27 | DQ27: 29949 | DR27: =IF(DQ27>0,(DQ27-DR$5)/DR$5,0) | DS27: ='Investment Analysis'!JR27 | DT27: 4190 | DU27: =IF(DT27>0,(DT27-DU$5)/DU$5,0) | DV27: ='Investment Analysis'!JY27 | DW27: 23966.75 | DX27: =IF(DW27>0,(DW27-DX$5)/DX$5,0) | DY27: ='Investment Analysis'!KF27 | DZ27: 2457.6 | EA27: =IF(DZ27>0,(DZ27-EA$5)/EA$5,0) | EB27: ='Investment Analysis'!KM27 | EC27: 2382.6 | ED27: =IF(EC27>0,(EC27-ED$5)/ED$5,0) | EE27: ='Investment Analysis'!KT27 | EF27: 37425 | EG27: =IF(EF27>0,(EF27-EG$5)/EG$5,0) | EH27: ='Investment Analysis'!LH27 | EI27: 8367.21 | EJ27: =IF(EI27>0,(EI27-EJ$5)/EJ$5,0) | EK27: ='Investment Analysis'!LO27 | EM27: =IF(EL27>0,(EL27-EM$5)/EM$5,0) | EN27: ='Investment Analysis'!LV27 | EP27: =IF(EO27>0,(EO27-500-EP$5)/EP$5,0) | EQ27: ='Investment Analysis'!MC27 | ER27: 26918.97 | ES27: =IF(ER27>0,(ER27-ES$5)/ES$5,0) | ET27: ='Investment Analysis'!LA27 | EU27: 47768 | EV27: ='Investment Analysis'!ML27 | EW27: ='Investment Analysis'!MJ27 | EX27: 39221 | EY27: =IF(EX27>0,(EX27-EY$5)/EY$5,0) | EZ27: ='Investment Analysis'!MQ27 | FB27: =IF(FA27>0,(FA27-FB$5)/FB$5,0) | FC27: ='Investment Analysis'!MX27 | FD27: 4860.75 | FE27: =IF(FD27>0,(FD27-FE$5)/FE$5,0) | FF27: ='Investment Analysis'!NE27 | FH27: =IF(FG27>0,(FG27-FH$5)/FH$5,0) | FI27: ='Investment Analysis'!NL27 | FJ27: 8878 | FK27: =IF(FJ27>0,(FJ27-FK$5)/FK$5,0) | FL27: ='Investment Analysis'!NS27 | FM27: 31248 | FN27: =IF(FM27>0,(FM27-FN$5)/FN$5,0) | FO27: ='Investment Analysis'!NZ27 | FQ27: =IF(FP27>0,(FP27-FQ$5)/FQ$5,0) | FR27: ='Investment Analysis'!OG27 | FS27: 37487 | FT27: =IF(FS27>0,(FS27-FT$5)/FT$5,0) | FU27: ='Investment Analysis'!ON27 | FW27: =IF(FV27>0,(FV27-FW$5)/FW$5,0) | FX27: ='Investment Analysis'!OU27 | FZ27: =IF(FY27>0,(FY27-FZ$5)/FZ$5,0) | GA27: ='Investment Analysis'!PB27 | GC27: ='Investment Analysis'!PK27 | GD27: ='Investment Analysis'!PI27 | GE27: 6951.5 | GF27: ='Investment Analysis'!PY27 | GG27: ='Investment Analysis'!PW27 | GH27: 33715 | GI27: ='Investment Analysis'!QF27 | GJ27: ='Investment Analysis'!QD27 | GL27: ='Investment Analysis'!QM27 | GM27: ='Investment Analysis'!QK27 | GN27: 29330.29 | GO27: ='Investment Analysis'!QT27 | GP27: ='Investment Analysis'!QR27 | GQ27: 17809.15 | GR27: ='Investment Analysis'!RA27 | GS27: ='Investment Analysis'!QY27 | GT27: 14964 | GU27: ='Investment Analysis'!RH27 | GV27: ='Investment Analysis'!RF27 | GX27: ='Investment Analysis'!RO27 | GY27: ='Investment Analysis'!RM27 | HA27: ='Investment Analysis'!RV27 | HB27: ='Investment Analysis'!RT27 | HD27: ='Investment Analysis'!SC27 | HE27: ='Investment Analysis'!SA27 | HG27: ='Investment Analysis'!SJ27 | HH27: ='Investment Analysis'!SH27 | HJ27: ='Investment Analysis'!SM27 | HK27: ='Investment Analysis'!SK27 | HM27: ='Investment Analysis'!SP27 | HN27: ='Investment Analysis'!SN27 | HP27: ='Investment Analysis'!TE27 | HQ27: ='Investment Analysis'!TC27 | HS27: ='Investment Analysis'!TL27 | HT27: ='Investment Analysis'!TJ27 | HV27: ='Investment Analysis'!TS27 | HW27: ='Investment Analysis'!TQ27 | HY27: ='Investment Analysis'!TZ27 | HZ27: ='Investment Analysis'!TX27 | IB27: ='Investment Analysis'!UG27 | IC27: ='Investment Analysis'!UE27 | IE27: ='Investment Analysis'!UN27 | IF27: ='Investment Analysis'!UL27 | IH27: ='Investment Analysis'!UU27 | II27: ='Investment Analysis'!US27 | IK27: ='Investment Analysis'!VB27 | IL27: ='Investment Analysis'!UZ27 | IN27: ='Investment Analysis'!VI27 | IO27: ='Investment Analysis'!VG27 | IS27: =IF(IT27>0,IT27-IT26,0) | IT27: =FY27+FV27+FS27+FP27+FM27+FJ27+FG27+FD27+FA27+EX27+EU27+ER27+EO27+EL27+EI27+EF27+EC27+DZ27+DW27+DT27+DQ27+DN27+DK27+DH27+DE27+DB27+CY27+CV27+CS27+CP27+CJ27+CG27+CD27+CA27+BX27+P27+CM27+GT27+GQ27+GN27+GK27+GH27+GE27+GB27+BU27+BR27+BO27+BL27+BI27+BF27+BC27+AZ27+AW27+AT27+AQ27+AN27+AK27+AH27+AE27+AB27+Y27+V27+S27+GW27+GZ27+HC27+HF27+HI27+HL27+HO27+HR27+HU27 | IU27: =IF(IT27>0,IV27,0) | IW27: =IF(IT27>0,(IT27+IV$11-I$2)/I$2,0) | IX27: =IF(IT27>0,IT27+IV$11-I$2,0) | IY27: =IF(IT27>0,(IT27+IV$11-IT$8)/IT$8,0) | IZ27: =IF(IT27>0,IT27+IV$11-IT$8,0)
A28: ='Investment Analysis'!A28 | B28: ='Investment Analysis'!B28 | C28: ='Investment Analysis'!C28 | D28: ='Investment Analysis'!D28 | E28: ='Investment Analysis'!E28 | F28: ='Investment Analysis'!G28 | G28: ='Investment Analysis'!H28 | H28: ='Investment Analysis'!I28 | I28: ='Investment Analysis'!K28 | J28: ='Investment Analysis'!L28 | K28: ='Investment Analysis'!M28 | L28: ='Investment Analysis'!T28 | M28: ='Investment Analysis'!V28 | N28: ='Investment Analysis'!W28 | P28: ='Investment Analysis'!Y28 | S28: 22846.46 | T28: =IF(S28>0,(S28+10000-T$5)/T$5,0) | U28: ='Investment Analysis'!AF28 | V28: 18500.96 | W28: =IF(V28>0,(V28+5000-W$5)/W$5,0) | X28: ='Investment Analysis'!AT28 | Y28: 10026.35 | Z28: =IF(Y28>0,(Y28-Z$5)/Z$5,0) | AA28: ='Investment Analysis'!GK28 | AB28: 2694.21 | AC28: =IF(AB28>0,(AB28+8000-AC$5)/AC$5,0) | AD28: ='Investment Analysis'!AT28 | AE28: 22883.76 | AF28: =IF(AE28>0,(AE28+30000-AF$5)/AF$5,0) | AG28: ='Investment Analysis'!BA28 | AI28: =IF(AH28>0,(AH28-5000-AI$5)/AI$5,0) | AJ28: ='Investment Analysis'!BH28 | AK28: 19812.83 | AL28: =IF(AK28>0,(AK28+7000-AL$5)/AL$5,0) | AM28: ='Investment Analysis'!BO28 | AN28: 15079.47 | AO28: =IF(AN28>0,(AN28-AO$5)/AO$5,0) | AP28: ='Investment Analysis'!BV28 | AR28: =IF(AQ28>0,(AQ28+10000-AR$5)/AR$5,0) | AS28: ='Investment Analysis'!CC28 | AT28: 28479.69 | AU28: =IF(AT28>0,(AT28+10000-AU$5)/AU$5,0) | AV28: ='Investment Analysis'!CJ28 | AW28: 19861.99 | AX28: =IF(AW28>0,(AW28+2000-AX$5)/AX$5,0) | AY28: ='Investment Analysis'!CQ28 | AZ28: 17215.51 | BA28: =IF(AZ28>0,(AZ28+15000-BA$5)/BA$5,0) | BB28: ='Investment Analysis'!CX28 | BC28: 10401.33 | BD28: =IF(BC28>0,(BC28-10000-BD$5)/BD$5,0) | BE28: ='Investment Analysis'!DE28 | BF28: 4355.67 | BG28: =IF(BF28>0,(BF28-BG$5)/BG$5,0) | BH28: ='Investment Analysis'!DL28 | BI28: 2443.29 | BJ28: =IF(BI28>0,(BI28-BJ$5)/BJ$5,0) | BK28: ='Investment Analysis'!DZ28 | BL28: 4336.51 | BM28: =IF(BL28>0,(BL28-BM$5)/BM$5,0) | BN28: ='Investment Analysis'!EG28 | BP28: =IF(BO28>0,(BO28+5000-BP$5)/BP$5,0) | BQ28: ='Investment Analysis'!DS28 | BR28: 6060.84 | BS28: =IF(BR28>0,(BR28-BS$5)/BS$5,0) | BT28: ='Investment Analysis'!EN28 | BU28: 14981.91 | BV28: =IF(BU28>0,(BU28+8000-BV$5)/BV$5,0) | BW28: ='Investment Analysis'!EU28 | BY28: =IF(BX28>0,(BX28-10000-BY$5)/BY$5,0) | BZ28: ='Investment Analysis'!FB28 | CA28: 22577.64 | CB28: =IF(CA28>0,(CA28-5000-CB$5)/CB$5,0) | CC28: ='Investment Analysis'!FI28 | CD28: 20262.57 | CE28: =IF(CD28>0,(CD28+20000-CE$5)/CE$5,0) | CF28: ='Investment Analysis'!FP28 | CG28: 5192.54 | CH28: =IF(CG28>0,(CG28+10000-CH$5)/CH$5,0) | CI28: ='Investment Analysis'!FW28 | CK28: =IF(CJ28>0,(CJ28+5000-CK$5)/CK$5,0) | CL28: ='Investment Analysis'!GD28 | CM28: 24474.78 | CN28: =IF(CM28>0,(CM28-CN$5)/CN$5,0) | CO28: ='Investment Analysis'!GT28 | CP28: 58365 | CQ28: =IF(CP28>0,(CP28-CQ$5)/CQ$5,0) | CR28: ='Investment Analysis'!HG28 | CS28: 6750 | CT28: =IF(CS28>0,(CS28-CT$5)/CT$5,0) | CU28: ='Investment Analysis'!HN28 | CV28: 24740 | CW28: =IF(CV28>0,(CV28-CW$5)/CW$5,0) | CX28: ='Investment Analysis'!IB28 | CY28: 20635 | CZ28: =IF(CY28>0,(CY28-CZ$5)/CZ$5,0) | DA28: ='Investment Analysis'!II28 | DC28: =IF(DB28>0,(DB28-DC$5)/DC$5,0) | DD28: ='Investment Analysis'!IP28 | DF28: =IF(DE28>0,(DE28-DF$5)/DF$5,0) | DG28: ='Investment Analysis'!IW28 | DH28: 13529.8 | DI28: =IF(DH28>0,(DH28-DI$5)/DI$5,0) | DJ28: ='Investment Analysis'!JD28 | DK28: 2211.65 | DL28: =IF(DK28>0,(DK28-DL$5)/DL$5,0) | DM28: ='Investment Analysis'!JK28 | DN28: 5433.5 | DO28: =IF(DN28>0,(DN28-DO$5)/DO$5,0) | DP28: ='Investment Analysis'!HU28 | DQ28: 29799 | DR28: =IF(DQ28>0,(DQ28-DR$5)/DR$5,0) | DS28: ='Investment Analysis'!JR28 | DT28: 4400 | DU28: =IF(DT28>0,(DT28-DU$5)/DU$5,0) | DV28: ='Investment Analysis'!JY28 | DW28: 24100.5 | DX28: =IF(DW28>0,(DW28-DX$5)/DX$5,0) | DY28: ='Investment Analysis'!KF28 | DZ28: 2463.6 | EA28: =IF(DZ28>0,(DZ28-EA$5)/EA$5,0) | EB28: ='Investment Analysis'!KM28 | EC28: 2393.6 | ED28: =IF(EC28>0,(EC28-ED$5)/ED$5,0) | EE28: ='Investment Analysis'!KT28 | EF28: 37965 | EG28: =IF(EF28>0,(EF28-EG$5)/EG$5,0) | EH28: ='Investment Analysis'!LH28 | EI28: 8380.23 | EJ28: =IF(EI28>0,(EI28-EJ$5)/EJ$5,0) | EK28: ='Investment Analysis'!LO28 | EM28: =IF(EL28>0,(EL28-EM$5)/EM$5,0) | EN28: ='Investment Analysis'!LV28 | EP28: =IF(EO28>0,(EO28-500-EP$5)/EP$5,0) | EQ28: ='Investment Analysis'!MC28 | ER28: 26303.49 | ES28: =IF(ER28>0,(ER28-ES$5)/ES$5,0) | ET28: ='Investment Analysis'!LA28 | EU28: 49420 | EV28: ='Investment Analysis'!ML28 | EW28: ='Investment Analysis'!MJ28 | EX28: 39249 | EY28: =IF(EX28>0,(EX28-EY$5)/EY$5,0) | EZ28: ='Investment Analysis'!MQ28 | FB28: =IF(FA28>0,(FA28-FB$5)/FB$5,0) | FC28: ='Investment Analysis'!MX28 | FD28: 4977.5 | FE28: =IF(FD28>0,(FD28-FE$5)/FE$5,0) | FF28: ='Investment Analysis'!NE28 | FH28: =IF(FG28>0,(FG28-FH$5)/FH$5,0) | FI28: ='Investment Analysis'!NL28 | FJ28: 8831.25 | FK28: =IF(FJ28>0,(FJ28-FK$5)/FK$5,0) | FL28: ='Investment Analysis'!NS28 | FM28: 31265.6 | FN28: =IF(FM28>0,(FM28-FN$5)/FN$5,0) | FO28: ='Investment Analysis'!NZ28 | FQ28: =IF(FP28>0,(FP28-FQ$5)/FQ$5,0) | FR28: ='Investment Analysis'!OG28 | FS28: 38655.5 | FT28: =IF(FS28>0,(FS28-FT$5)/FT$5,0) | FU28: ='Investment Analysis'!ON28 | FW28: =IF(FV28>0,(FV28-FW$5)/FW$5,0) | FX28: ='Investment Analysis'!OU28 | FZ28: =IF(FY28>0,(FY28-FZ$5)/FZ$5,0) | GA28: ='Investment Analysis'!PB28 | GC28: ='Investment Analysis'!PK28 | GD28: ='Investment Analysis'!PI28 | GE28: 6873 | GF28: ='Investment Analysis'!PY28 | GG28: ='Investment Analysis'!PW28 | GH28: 37557.5 | GI28: ='Investment Analysis'!QF28 | GJ28: ='Investment Analysis'!QD28 | GL28: ='Investment Analysis'!QM28 | GM28: ='Investment Analysis'!QK28 | GN28: 29255.77 | GO28: ='Investment Analysis'!QT28 | GP28: ='Investment Analysis'!QR28 | GQ28: 17829.8 | GR28: ='Investment Analysis'!RA28 | GS28: ='Investment Analysis'!QY28 | GT28: 15521 | GU28: ='Investment Analysis'!RH28 | GV28: ='Investment Analysis'!RF28 | GX28: ='Investment Analysis'!RO28 | GY28: ='Investment Analysis'!RM28 | HA28: ='Investment Analysis'!RV28 | HB28: ='Investment Analysis'!RT28 | HD28: ='Investment Analysis'!SC28 | HE28: ='Investment Analysis'!SA28 | HG28: ='Investment Analysis'!SJ28 | HH28: ='Investment Analysis'!SH28 | HJ28: ='Investment Analysis'!SM28 | HK28: ='Investment Analysis'!SK28 | HM28: ='Investment Analysis'!SP28 | HN28: ='Investment Analysis'!SN28 | HP28: ='Investment Analysis'!TE28 | HQ28: ='Investment Analysis'!TC28 | HS28: ='Investment Analysis'!TL28 | HT28: ='Investment Analysis'!TJ28 | HV28: ='Investment Analysis'!TS28 | HW28: ='Investment Analysis'!TQ28 | HY28: ='Investment Analysis'!TZ28 | HZ28: ='Investment Analysis'!TX28 | IB28: ='Investment Analysis'!UG28 | IC28: ='Investment Analysis'!UE28 | IE28: ='Investment Analysis'!UN28 | IF28: ='Investment Analysis'!UL28 | IH28: ='Investment Analysis'!UU28 | II28: ='Investment Analysis'!US28 | IK28: ='Investment Analysis'!VB28 | IL28: ='Investment Analysis'!UZ28 | IN28: ='Investment Analysis'!VI28 | IO28: ='Investment Analysis'!VG28 | IS28: =IF(IT28>0,IT28-IT27,0) | IT28: =FY28+FV28+FS28+FP28+FM28+FJ28+FG28+FD28+FA28+EX28+EU28+ER28+EO28+EL28+EI28+EF28+EC28+DZ28+DW28+DT28+DQ28+DN28+DK28+DH28+DE28+DB28+CY28+CV28+CS28+CP28+CJ28+CG28+CD28+CA28+BX28+P28+CM28+GT28+GQ28+GN28+GK28+GH28+GE28+GB28+BU28+BR28+BO28+BL28+BI28+BF28+BC28+AZ28+AW28+AT28+AQ28+AN28+AK28+AH28+AE28+AB28+Y28+V28+S28+GW28+GZ28+HC28+HF28+HI28+HL28+HO28+HR28+HU28 | IU28: =IF(IT28>0,IV28,0) | IW28: =IF(IT28>0,(IT28+IV$11-I$2)/I$2,0) | IX28: =IF(IT28>0,IT28+IV$11-I$2,0) | IY28: =IF(IT28>0,(IT28+IV$11-IT$8)/IT$8,0) | IZ28: =IF(IT28>0,IT28+IV$11-IT$8,0)
A29: ='Investment Analysis'!A29 | B29: ='Investment Analysis'!B29 | C29: ='Investment Analysis'!C29 | D29: ='Investment Analysis'!D29 | E29: ='Investment Analysis'!E29 | F29: ='Investment Analysis'!G29 | G29: ='Investment Analysis'!H29 | H29: ='Investment Analysis'!I29 | I29: ='Investment Analysis'!K29 | J29: ='Investment Analysis'!L29 | K29: ='Investment Analysis'!M29 | L29: ='Investment Analysis'!T29 | M29: ='Investment Analysis'!V29 | N29: ='Investment Analysis'!W29 | P29: ='Investment Analysis'!Y29 | S29: 22944.66 | T29: =IF(S29>0,(S29+10000-T$5)/T$5,0) | U29: ='Investment Analysis'!AF29 | V29: 18634.79 | W29: =IF(V29>0,(V29+5000-W$5)/W$5,0) | X29: ='Investment Analysis'!AT29 | Y29: 10120.69 | Z29: =IF(Y29>0,(Y29-Z$5)/Z$5,0) | AA29: ='Investment Analysis'!GK29 | AB29: 2707.76 | AC29: =IF(AB29>0,(AB29+8000-AC$5)/AC$5,0) | AD29: ='Investment Analysis'!AT29 | AE29: 23004.83 | AF29: =IF(AE29>0,(AE29+30000-AF$5)/AF$5,0) | AG29: ='Investment Analysis'!BA29 | AI29: =IF(AH29>0,(AH29-5000-AI$5)/AI$5,0) | AJ29: ='Investment Analysis'!BH29 | AK29: 20035.58 | AL29: =IF(AK29>0,(AK29+7000-AL$5)/AL$5,0) | AM29: ='Investment Analysis'!BO29 | AN29: 15394.89 | AO29: =IF(AN29>0,(AN29-AO$5)/AO$5,0) | AP29: ='Investment Analysis'!BV29 | AR29: =IF(AQ29>0,(AQ29+10000-AR$5)/AR$5,0) | AS29: ='Investment Analysis'!CC29 | AT29: 28778.65 | AU29: =IF(AT29>0,(AT29+10000-AU$5)/AU$5,0) | AV29: ='Investment Analysis'!CJ29 | AW29: 20073.23 | AX29: =IF(AW29>0,(AW29+2000-AX$5)/AX$5,0) | AY29: ='Investment Analysis'!CQ29 | AZ29: 17390.31 | BA29: =IF(AZ29>0,(AZ29+15000-BA$5)/BA$5,0) | BB29: ='Investment Analysis'!CX29 | BC29: 10513.96 | BD29: =IF(BC29>0,(BC29-10000-BD$5)/BD$5,0) | BE29: ='Investment Analysis'!DE29 | BF29: 4408.04 | BG29: =IF(BF29>0,(BF29-BG$5)/BG$5,0) | BH29: ='Investment Analysis'!DL29 | BI29: 2496.32 | BJ29: =IF(BI29>0,(BI29-BJ$5)/BJ$5,0) | BK29: ='Investment Analysis'!DZ29 | BL29: 4304.52 | BM29: =IF(BL29>0,(BL29-BM$5)/BM$5,0) | BN29: ='Investment Analysis'!EG29 | BP29: =IF(BO29>0,(BO29+5000-BP$5)/BP$5,0) | BQ29: ='Investment Analysis'!DS29 | BR29: 6117.38 | BS29: =IF(BR29>0,(BR29-BS$5)/BS$5,0) | BT29: ='Investment Analysis'!EN29 | BU29: 15228.51 | BV29: =IF(BU29>0,(BU29+8000-BV$5)/BV$5,0) | BW29: ='Investment Analysis'!EU29 | BY29: =IF(BX29>0,(BX29-10000-BY$5)/BY$5,0) | BZ29: ='Investment Analysis'!FB29 | CA29: 22790.53 | CB29: =IF(CA29>0,(CA29-CB$5)/CB$5,0) | CC29: ='Investment Analysis'!FI29 | CD29: 20408.21 | CE29: =IF(CD29>0,(CD29+20000-CE$5)/CE$5,0) | CF29: ='Investment Analysis'!FP29 | CG29: 5209.88 | CH29: =IF(CG29>0,(CG29+10000-CH$5)/CH$5,0) | CI29: ='Investment Analysis'!FW29 | CK29: =IF(CJ29>0,(CJ29+5000-CK$5)/CK$5,0) | CL29: ='Investment Analysis'!GD29 | CM29: 24895.25 | CN29: =IF(CM29>0,(CM29-CN$5)/CN$5,0) | CO29: ='Investment Analysis'!GT29 | CP29: 60042 | CQ29: =IF(CP29>0,(CP29-CQ$5)/CQ$5,0) | CR29: ='Investment Analysis'!HG29 | CS29: 6750 | CT29: =IF(CS29>0,(CS29-CT$5)/CT$5,0) | CU29: ='Investment Analysis'!HN29 | CV29: 24930 | CW29: =IF(CV29>0,(CV29-CW$5)/CW$5,0) | CX29: ='Investment Analysis'!IB29 | CY29: 21566 | CZ29: =IF(CY29>0,(CY29-CZ$5)/CZ$5,0) | DA29: ='Investment Analysis'!II29 | DC29: =IF(DB29>0,(DB29-DC$5)/DC$5,0) | DD29: ='Investment Analysis'!IP29 | DF29: =IF(DE29>0,(DE29-DF$5)/DF$5,0) | DG29: ='Investment Analysis'!IW29 | DH29: 13740 | DI29: =IF(DH29>0,(DH29-DI$5)/DI$5,0) | DJ29: ='Investment Analysis'!JD29 | DK29: 2074.95 | DL29: =IF(DK29>0,(DK29-DL$5)/DL$5,0) | DM29: ='Investment Analysis'!JK29 | DN29: 5478.5 | DO29: =IF(DN29>0,(DN29-DO$5)/DO$5,0) | DP29: ='Investment Analysis'!HU29 | DQ29: 30279 | DR29: =IF(DQ29>0,(DQ29-DR$5)/DR$5,0) | DS29: ='Investment Analysis'!JR29 | DT29: 4716 | DU29: =IF(DT29>0,(DT29-DU$5)/DU$5,0) | DV29: ='Investment Analysis'!JY29 | DW29: 24475.25 | DX29: =IF(DW29>0,(DW29-DX$5)/DX$5,0) | DY29: ='Investment Analysis'!KF29 | DZ29: 2545.2 | EA29: =IF(DZ29>0,(DZ29-EA$5)/EA$5,0) | EB29: ='Investment Analysis'!KM29 | EC29: 2375.9 | ED29: =IF(EC29>0,(EC29-ED$5)/ED$5,0) | EE29: ='Investment Analysis'!KT29 | EF29: 38737.5 | EG29: =IF(EF29>0,(EF29-EG$5)/EG$5,0) | EH29: ='Investment Analysis'!LH29 | EI29: 8784.78 | EJ29: =IF(EI29>0,(EI29-EJ$5)/EJ$5,0) | EK29: ='Investment Analysis'!LO29 | EM29: =IF(EL29>0,(EL29-EM$5)/EM$5,0) | EN29: ='Investment Analysis'!LV29 | EP29: =IF(EO29>0,(EO29-500-EP$5)/EP$5,0) | EQ29: ='Investment Analysis'!MC29 | ER29: 23293.25 | ES29: =IF(ER29>0,(ER29-ES$5)/ES$5,0) | ET29: ='Investment Analysis'!LA29 | EU29: 58674 | EV29: ='Investment Analysis'!ML29 | EW29: ='Investment Analysis'!MJ29 | EX29: 40334 | EY29: =IF(EX29>0,(EX29-EY$5)/EY$5,0) | EZ29: ='Investment Analysis'!MQ29 | FB29: =IF(FA29>0,(FA29-FB$5)/FB$5,0) | FC29: ='Investment Analysis'!MX29 | FD29: 5139.25 | FE29: =IF(FD29>0,(FD29-FE$5)/FE$5,0) | FF29: ='Investment Analysis'!NE29 | FH29: =IF(FG29>0,(FG29-FH$5)/FH$5,0) | FI29: ='Investment Analysis'!NL29 | FJ29: 9573.5 | FK29: =IF(FJ29>0,(FJ29-FK$5)/FK$5,0) | FL29: ='Investment Analysis'!NS29 | FM29: 32139.2 | FN29: =IF(FM29>0,(FM29-FN$5)/FN$5,0) | FO29: ='Investment Analysis'!NZ29 | FQ29: =IF(FP29>0,(FP29-FQ$5)/FQ$5,0) | FR29: ='Investment Analysis'!OG29 | FS29: 40555.5 | FT29: =IF(FS29>0,(FS29-FT$5)/FT$5,0) | FU29: ='Investment Analysis'!ON29 | FW29: =IF(FV29>0,(FV29-FW$5)/FW$5,0) | FX29: ='Investment Analysis'!OU29 | FZ29: =IF(FY29>0,(FY29-FZ$5)/FZ$5,0) | GA29: ='Investment Analysis'!PB29 | GC29: ='Investment Analysis'!PK29 | GD29: ='Investment Analysis'!PI29 | GE29: 7066.5 | GF29: ='Investment Analysis'!PY29 | GG29: ='Investment Analysis'!PW29 | GH29: 37685 | GI29: ='Investment Analysis'!QF29 | GJ29: ='Investment Analysis'!QD29 | GL29: ='Investment Analysis'!QM29 | GM29: ='Investment Analysis'!QK29 | GN29: 29770.97 | GO29: ='Investment Analysis'!QT29 | GP29: ='Investment Analysis'!QR29 | GQ29: 18620.4 | GR29: ='Investment Analysis'!RA29 | GS29: ='Investment Analysis'!QY29 | GT29: 17630 | GU29: ='Investment Analysis'!RH29 | GV29: ='Investment Analysis'!RF29 | GX29: ='Investment Analysis'!RO29 | GY29: ='Investment Analysis'!RM29 | HA29: ='Investment Analysis'!RV29 | HB29: ='Investment Analysis'!RT29 | HD29: ='Investment Analysis'!SC29 | HE29: ='Investment Analysis'!SA29 | HG29: ='Investment Analysis'!SJ29 | HH29: ='Investment Analysis'!SH29 | HJ29: ='Investment Analysis'!SM29 | HK29: ='Investment Analysis'!SK29 | HM29: ='Investment Analysis'!SP29 | HN29: ='Investment Analysis'!SN29 | HP29: ='Investment Analysis'!TE29 | HQ29: ='Investment Analysis'!TC29 | HS29: ='Investment Analysis'!TL29 | HT29: ='Investment Analysis'!TJ29 | HV29: ='Investment Analysis'!TS29 | HW29: ='Investment Analysis'!TQ29 | HY29: ='Investment Analysis'!TZ29 | HZ29: ='Investment Analysis'!TX29 | IB29: ='Investment Analysis'!UG29 | IC29: ='Investment Analysis'!UE29 | IE29: ='Investment Analysis'!UN29 | IF29: ='Investment Analysis'!UL29 | IH29: ='Investment Analysis'!UU29 | II29: ='Investment Analysis'!US29 | IK29: ='Investment Analysis'!VB29 | IL29: ='Investment Analysis'!UZ29 | IN29: ='Investment Analysis'!VI29 | IO29: ='Investment Analysis'!VG29 | IS29: =IF(IT29>0,IT29-IT28,0) | IT29: =FY29+FV29+FS29+FP29+FM29+FJ29+FG29+FD29+FA29+EX29+EU29+ER29+EO29+EL29+EI29+EF29+EC29+DZ29+DW29+DT29+DQ29+DN29+DK29+DH29+DE29+DB29+CY29+CV29+CS29+CP29+CJ29+CG29+CD29+CA29+BX29+P29+CM29+GT29+GQ29+GN29+GK29+GH29+GE29+GB29+BU29+BR29+BO29+BL29+BI29+BF29+BC29+AZ29+AW29+AT29+AQ29+AN29+AK29+AH29+AE29+AB29+Y29+V29+S29+GW29+GZ29+HC29+HF29+HI29+HL29+HO29+HR29+HU29 | IU29: =IF(IT29>0,IV29,0) | IW29: =IF(IT29>0,(IT29+IV$11-I$2)/I$2,0) | IX29: =IF(IT29>0,IT29+IV$11-I$2,0) | IY29: =IF(IT29>0,(IT29+IV$11-IT$8)/IT$8,0) | IZ29: =IF(IT29>0,IT29+IV$11-IT$8,0)
A30: ='Investment Analysis'!A30 | B30: ='Investment Analysis'!B30 | C30: ='Investment Analysis'!C30 | D30: ='Investment Analysis'!D30 | E30: ='Investment Analysis'!E30 | F30: ='Investment Analysis'!G30 | G30: ='Investment Analysis'!H30 | H30: ='Investment Analysis'!I30 | I30: ='Investment Analysis'!K30 | J30: ='Investment Analysis'!L30 | K30: ='Investment Analysis'!M30 | L30: ='Investment Analysis'!T30 | M30: ='Investment Analysis'!V30 | N30: ='Investment Analysis'!W30 | P30: ='Investment Analysis'!Y30 | S30: 22809.14 | T30: =IF(S30>0,(S30+10000-T$5)/T$5,0) | U30: ='Investment Analysis'!AF30 | V30: 18542.78 | W30: =IF(V30>0,(V30+5000-W$5)/W$5,0) | X30: ='Investment Analysis'!AT30 | Y30: 10215.04 | Z30: =IF(Y30>0,(Y30-Z$5)/Z$5,0) | AA30: ='Investment Analysis'!GK30 | AB30: 2701.6 | AC30: =IF(AB30>0,(AB30+8000-AC$5)/AC$5,0) | AD30: ='Investment Analysis'!AT30 | AE30: 22890.31 | AF30: =IF(AE30>0,(AE30+30000-AF$5)/AF$5,0) | AG30: ='Investment Analysis'!BA30 | AI30: =IF(AH30>0,(AH30-5000-AI$5)/AI$5,0) | AJ30: ='Investment Analysis'!BH30 | AK30: 19877.68 | AL30: =IF(AK30>0,(AK30+7000-AL$5)/AL$5,0) | AM30: ='Investment Analysis'!BO30 | AN30: 15265.68 | AO30: =IF(AN30>0,(AN30-AO$5)/AO$5,0) | AP30: ='Investment Analysis'!BV30 | AR30: =IF(AQ30>0,(AQ30+10000-AR$5)/AR$5,0) | AS30: ='Investment Analysis'!CC30 | AT30: 28637.04 | AU30: =IF(AT30>0,(AT30+10000-AU$5)/AU$5,0) | AV30: ='Investment Analysis'!CJ30 | AW30: 19901.95 | AX30: =IF(AW30>0,(AW30+2000-AX$5)/AX$5,0) | AY30: ='Investment Analysis'!CQ30 | AZ30: 17219.99 | BA30: =IF(AZ30>0,(AZ30+15000-BA$5)/BA$5,0) | BB30: ='Investment Analysis'!CX30 | BC30: 10396.43 | BD30: =IF(BC30>0,(BC30-10000-BD$5)/BD$5,0) | BE30: ='Investment Analysis'!DE30 | BF30: 4378.4 | BG30: =IF(BF30>0,(BF30-BG$5)/BG$5,0) | BH30: ='Investment Analysis'!DL30 | BI30: 2483.44 | BJ30: =IF(BI30>0,(BI30-BJ$5)/BJ$5,0) | BK30: ='Investment Analysis'!DZ30 | BL30: 4267.79 | BM30: =IF(BL30>0,(BL30-BM$5)/BM$5,0) | BN30: ='Investment Analysis'!EG30 | BP30: =IF(BO30>0,(BO30+5000-BP$5)/BP$5,0) | BQ30: ='Investment Analysis'!DS30 | BR30: 6131.52 | BS30: =IF(BR30>0,(BR30-BS$5)/BS$5,0) | BT30: ='Investment Analysis'!EN30 | BU30: 15084.34 | BV30: =IF(BU30>0,(BU30+8000-BV$5)/BV$5,0) | BW30: ='Investment Analysis'!EU30 | BY30: =IF(BX30>0,(BX30-10000-BY$5)/BY$5,0) | BZ30: ='Investment Analysis'!FB30 | CA30: 22182.27 | CB30: =IF(CA30>0,(CA30-CB$5)/CB$5,0) | CC30: ='Investment Analysis'!FI30 | CD30: 20358.27 | CE30: =IF(CD30>0,(CD30+20000-CE$5)/CE$5,0) | CF30: ='Investment Analysis'!FP30 | CG30: 5165.71 | CH30: =IF(CG30>0,(CG30+10000-CH$5)/CH$5,0) | CI30: ='Investment Analysis'!FW30 | CK30: =IF(CJ30>0,(CJ30+5000-CK$5)/CK$5,0) | CL30: ='Investment Analysis'!GD30 | CM30: 24632.45 | CN30: =IF(CM30>0,(CM30-CN$5)/CN$5,0) | CO30: ='Investment Analysis'!GT30 | CP30: 60690 | CQ30: =IF(CP30>0,(CP30-CQ$5)/CQ$5,0) | CR30: ='Investment Analysis'!HG30 | CS30: 6660 | CT30: =IF(CS30>0,(CS30-CT$5)/CT$5,0) | CU30: ='Investment Analysis'!HN30 | CV30: 24014 | CW30: =IF(CV30>0,(CV30-CW$5)/CW$5,0) | CX30: ='Investment Analysis'!IB30 | CY30: 22127 | CZ30: =IF(CY30>0,(CY30-CZ$5)/CZ$5,0) | DA30: ='Investment Analysis'!II30 | DC30: =IF(DB30>0,(DB30-DC$5)/DC$5,0) | DD30: ='Investment Analysis'!IP30 | DF30: =IF(DE30>0,(DE30-DF$5)/DF$5,0) | DG30: ='Investment Analysis'!IW30 | DH30: 13783.6 | DI30: =IF(DH30>0,(DH30-DI$5)/DI$5,0) | DJ30: ='Investment Analysis'!JD30 | DK30: 2075.3 | DL30: =IF(DK30>0,(DK30-DL$5)/DL$5,0) | DM30: ='Investment Analysis'!JK30 | DN30: 5341.5 | DO30: =IF(DN30>0,(DN30-DO$5)/DO$5,0) | DP30: ='Investment Analysis'!HU30 | DQ30: 30264 | DR30: =IF(DQ30>0,(DQ30-DR$5)/DR$5,0) | DS30: ='Investment Analysis'!JR30 | DT30: 4768 | DU30: =IF(DT30>0,(DT30-DU$5)/DU$5,0) | DV30: ='Investment Analysis'!JY30 | DW30: 24497 | DX30: =IF(DW30>0,(DW30-DX$5)/DX$5,0) | DY30: ='Investment Analysis'!KF30 | DZ30: 2511.6 | EA30: =IF(DZ30>0,(DZ30-EA$5)/EA$5,0) | EB30: ='Investment Analysis'!KM30 | EC30: 2360 | ED30: =IF(EC30>0,(EC30-ED$5)/ED$5,0) | EE30: ='Investment Analysis'!KT30 | EF30: 38340 | EG30: =IF(EF30>0,(EF30-EG$5)/EG$5,0) | EH30: ='Investment Analysis'!LH30 | EI30: 8643.42 | EJ30: =IF(EI30>0,(EI30-EJ$5)/EJ$5,0) | EK30: ='Investment Analysis'!LO30 | EM30: =IF(EL30>0,(EL30-EM$5)/EM$5,0) | EN30: ='Investment Analysis'!LV30 | EP30: =IF(EO30>0,(EO30-500-EP$5)/EP$5,0) | EQ30: ='Investment Analysis'!MC30 | ER30: 23422.74 | ES30: =IF(ER30>0,(ER30-ES$5)/ES$5,0) | ET30: ='Investment Analysis'!LA30 | EU30: 58254 | EV30: ='Investment Analysis'!ML30 | EW30: ='Investment Analysis'!MJ30 | EX30: 39525.5 | EY30: =IF(EX30>0,(EX30-EY$5)/EY$5,0) | EZ30: ='Investment Analysis'!MQ30 | FB30: =IF(FA30>0,(FA30-FB$5)/FB$5,0) | FC30: ='Investment Analysis'!MX30 | FD30: 5089.25 | FE30: =IF(FD30>0,(FD30-FE$5)/FE$5,0) | FF30: ='Investment Analysis'!NE30 | FH30: =IF(FG30>0,(FG30-FH$5)/FH$5,0) | FI30: ='Investment Analysis'!NL30 | FJ30: 9322 | FK30: =IF(FJ30>0,(FJ30-FK$5)/FK$5,0) | FL30: ='Investment Analysis'!NS30 | FM30: 32643.2 | FN30: =IF(FM30>0,(FM30-FN$5)/FN$5,0) | FO30: ='Investment Analysis'!NZ30 | FQ30: =IF(FP30>0,(FP30-FQ$5)/FQ$5,0) | FR30: ='Investment Analysis'!OG30 | FS30: 39092.5 | FT30: =IF(FS30>0,(FS30-FT$5)/FT$5,0) | FU30: ='Investment Analysis'!ON30 | FW30: =IF(FV30>0,(FV30-FW$5)/FW$5,0) | FX30: ='Investment Analysis'!OU30 | FZ30: =IF(FY30>0,(FY30-FZ$5)/FZ$5,0) | GA30: ='Investment Analysis'!PB30 | GC30: ='Investment Analysis'!PK30 | GD30: ='Investment Analysis'!PI30 | GE30: 6991 | GF30: ='Investment Analysis'!PY30 | GG30: ='Investment Analysis'!PW30 | GH30: 37157.5 | GI30: ='Investment Analysis'!QF30 | GJ30: ='Investment Analysis'!QD30 | GL30: ='Investment Analysis'!QM30 | GM30: ='Investment Analysis'!QK30 | GN30: 29834.91 | GO30: ='Investment Analysis'!QT30 | GP30: ='Investment Analysis'!QR30 | GQ30: 18428.65 | GR30: ='Investment Analysis'!RA30 | GS30: ='Investment Analysis'!QY30 | GT30: 16803 | GU30: ='Investment Analysis'!RH30 | GV30: ='Investment Analysis'!RF30 | GX30: ='Investment Analysis'!RO30 | GY30: ='Investment Analysis'!RM30 | HA30: ='Investment Analysis'!RV30 | HB30: ='Investment Analysis'!RT30 | HD30: ='Investment Analysis'!SC30 | HE30: ='Investment Analysis'!SA30 | HG30: ='Investment Analysis'!SJ30 | HH30: ='Investment Analysis'!SH30 | HJ30: ='Investment Analysis'!SM30 | HK30: ='Investment Analysis'!SK30 | HM30: ='Investment Analysis'!SP30 | HN30: ='Investment Analysis'!SN30 | HP30: ='Investment Analysis'!TE30 | HQ30: ='Investment Analysis'!TC30 | HS30: ='Investment Analysis'!TL30 | HT30: ='Investment Analysis'!TJ30 | HV30: ='Investment Analysis'!TS30 | HW30: ='Investment Analysis'!TQ30 | HY30: ='Investment Analysis'!TZ30 | HZ30: ='Investment Analysis'!TX30 | IB30: ='Investment Analysis'!UG30 | IC30: ='Investment Analysis'!UE30 | IE30: ='Investment Analysis'!UN30 | IF30: ='Investment Analysis'!UL30 | IH30: ='Investment Analysis'!UU30 | II30: ='Investment Analysis'!US30 | IK30: ='Investment Analysis'!VB30 | IL30: ='Investment Analysis'!UZ30 | IN30: ='Investment Analysis'!VI30 | IO30: ='Investment Analysis'!VG30 | IS30: =IF(IT30>0,IT30-IT29,0) | IT30: =FY30+FV30+FS30+FP30+FM30+FJ30+FG30+FD30+FA30+EX30+EU30+ER30+EO30+EL30+EI30+EF30+EC30+DZ30+DW30+DT30+DQ30+DN30+DK30+DH30+DE30+DB30+CY30+CV30+CS30+CP30+CJ30+CG30+CD30+CA30+BX30+P30+CM30+GT30+GQ30+GN30+GK30+GH30+GE30+GB30+BU30+BR30+BO30+BL30+BI30+BF30+BC30+AZ30+AW30+AT30+AQ30+AN30+AK30+AH30+AE30+AB30+Y30+V30+S30+GW30+GZ30+HC30+HF30+HI30+HL30+HO30+HR30+HU30 | IU30: =IF(IT30>0,IV30,0) | IW30: =IF(IT30>0,(IT30+IV$11-I$2)/I$2,0) | IX30: =IF(IT30>0,IT30+IV$11-I$2,0) | IY30: =IF(IT30>0,(IT30+IV$11-IT$8)/IT$8,0) | IZ30: =IF(IT30>0,IT30+IV$11-IT$8,0)
A31: ='Investment Analysis'!A31 | B31: ='Investment Analysis'!B31 | C31: ='Investment Analysis'!C31 | D31: ='Investment Analysis'!D31 | E31: ='Investment Analysis'!E31 | F31: ='Investment Analysis'!G31 | G31: ='Investment Analysis'!H31 | H31: ='Investment Analysis'!I31 | I31: ='Investment Analysis'!K31 | J31: ='Investment Analysis'!L31 | K31: ='Investment Analysis'!M31 | L31: ='Investment Analysis'!T31 | M31: ='Investment Analysis'!V31 | N31: ='Investment Analysis'!W31 | P31: ='Investment Analysis'!Y31 | S31: 22332.54 | T31: =IF(S31>0,(S31+10000-T$5)/T$5,0) | U31: ='Investment Analysis'!AF31 | V31: 18307.91 | W31: =IF(V31>0,(V31+5000-W$5)/W$5,0) | X31: ='Investment Analysis'!AT31 | Y31: 10091.64 | Z31: =IF(Y31>0,(Y31-Z$5)/Z$5,0) | AA31: ='Investment Analysis'!GK31 | AB31: 2649.02 | AC31: =IF(AB31>0,(AB31+8000-AC$5)/AC$5,0) | AD31: ='Investment Analysis'!AT31 | AE31: 22521.56 | AF31: =IF(AE31>0,(AE31+30000-AF$5)/AF$5,0) | AG31: ='Investment Analysis'!BA31 | AI31: =IF(AH31>0,(AH31-5000-AI$5)/AI$5,0) | AJ31: ='Investment Analysis'!BH31 | AK31: 19596.37 | AL31: =IF(AK31>0,(AK31+7000-AL$5)/AL$5,0) | AM31: ='Investment Analysis'!BO31 | AN31: 14967.56 | AO31: =IF(AN31>0,(AN31-AO$5)/AO$5,0) | AP31: ='Investment Analysis'!BV31 | AR31: =IF(AQ31>0,(AQ31+10000-AR$5)/AR$5,0) | AS31: ='Investment Analysis'!CC31 | AT31: 28124.34 | AU31: =IF(AT31>0,(AT31+10000-AU$5)/AU$5,0) | AV31: ='Investment Analysis'!CJ31 | AW31: 19542.56 | AX31: =IF(AW31>0,(AW31+2000-AX$5)/AX$5,0) | AY31: ='Investment Analysis'!CQ31 | AZ31: 16817.2 | BA31: =IF(AZ31>0,(AZ31+15000-BA$5)/BA$5,0) | BB31: ='Investment Analysis'!CX31 | BC31: 10111.84 | BD31: =IF(BC31>0,(BC31-10000-BD$5)/BD$5,0) | BE31: ='Investment Analysis'!DE31 | BF31: 4293.49 | BG31: =IF(BF31>0,(BF31-BG$5)/BG$5,0) | BH31: ='Investment Analysis'!DL31 | BI31: 2412.4 | BJ31: =IF(BI31>0,(BI31-BJ$5)/BJ$5,0) | BK31: ='Investment Analysis'!DZ31 | BL31: 4160.29 | BM31: =IF(BL31>0,(BL31-BM$5)/BM$5,0) | BN31: ='Investment Analysis'!EG31 | BP31: =IF(BO31>0,(BO31+5000-BP$5)/BP$5,0) | BQ31: ='Investment Analysis'!DS31 | BR31: 6081.43 | BS31: =IF(BR31>0,(BR31-BS$5)/BS$5,0) | BT31: ='Investment Analysis'!EN31 | BU31: 14851.83 | BV31: =IF(BU31>0,(BU31+8000-BV$5)/BV$5,0) | BW31: ='Investment Analysis'!EU31 | BY31: =IF(BX31>0,(BX31-10000-BY$5)/BY$5,0) | BZ31: ='Investment Analysis'!FB31 | CA31: 22027.72 | CB31: =IF(CA31>0,(CA31-CB$5)/CB$5,0) | CC31: ='Investment Analysis'!FI31 | CD31: 19934.19 | CE31: =IF(CD31>0,(CD31+20000-CE$5)/CE$5,0) | CF31: ='Investment Analysis'!FP31 | CG31: 5133.09 | CH31: =IF(CG31>0,(CG31+10000-CH$5)/CH$5,0) | CI31: ='Investment Analysis'!FW31 | CK31: =IF(CJ31>0,(CJ31+5000-CK$5)/CK$5,0) | CL31: ='Investment Analysis'!GD31 | CM31: 24470.48 | CN31: =IF(CM31>0,(CM31-CN$5)/CN$5,0) | CO31: ='Investment Analysis'!GT31 | CP31: 57552 | CQ31: =IF(CP31>0,(CP31-CQ$5)/CQ$5,0) | CR31: ='Investment Analysis'!HG31 | CS31: 6900 | CT31: =IF(CS31>0,(CS31-CT$5)/CT$5,0) | CU31: ='Investment Analysis'!HN31 | CV31: 23332 | CW31: =IF(CV31>0,(CV31-CW$5)/CW$5,0) | CX31: ='Investment Analysis'!IB31 | CY31: 21773 | CZ31: =IF(CY31>0,(CY31-CZ$5)/CZ$5,0) | DA31: ='Investment Analysis'!II31 | DC31: =IF(DB31>0,(DB31-DC$5)/DC$5,0) | DD31: ='Investment Analysis'!IP31 | DF31: =IF(DE31>0,(DE31-DF$5)/DF$5,0) | DG31: ='Investment Analysis'!IW31 | DH31: 13949.2 | DI31: =IF(DH31>0,(DH31-DI$5)/DI$5,0) | DJ31: ='Investment Analysis'!JD31 | DK31: 2054.6 | DL31: =IF(DK31>0,(DK31-DL$5)/DL$5,0) | DM31: ='Investment Analysis'!JK31 | DN31: 5354.5 | DO31: =IF(DN31>0,(DN31-DO$5)/DO$5,0) | DP31: ='Investment Analysis'!HU31 | DQ31: 30270 | DR31: =IF(DQ31>0,(DQ31-DR$5)/DR$5,0) | DS31: ='Investment Analysis'!JR31 | DT31: 4770 | DU31: =IF(DT31>0,(DT31-DU$5)/DU$5,0) | DV31: ='Investment Analysis'!JY31 | DW31: 25145.75 | DX31: =IF(DW31>0,(DW31-DX$5)/DX$5,0) | DY31: ='Investment Analysis'!KF31 | DZ31: 2565.6 | EA31: =IF(DZ31>0,(DZ31-EA$5)/EA$5,0) | EB31: ='Investment Analysis'!KM31 | EC31: 2280.1 | ED31: =IF(EC31>0,(EC31-ED$5)/ED$5,0) | EE31: ='Investment Analysis'!KT31 | EF31: 39135 | EG31: =IF(EF31>0,(EF31-EG$5)/EG$5,0) | EH31: ='Investment Analysis'!LH31 | EI31: 8821.98 | EJ31: =IF(EI31>0,(EI31-EJ$5)/EJ$5,0) | EK31: ='Investment Analysis'!LO31 | EM31: =IF(EL31>0,(EL31-EM$5)/EM$5,0) | EN31: ='Investment Analysis'!LV31 | EP31: =IF(EO31>0,(EO31-500-EP$5)/EP$5,0) | EQ31: ='Investment Analysis'!MC31 | ER31: 23481.62 | ES31: =IF(ER31>0,(ER31-ES$5)/ES$5,0) | ET31: ='Investment Analysis'!LA31 | EU31: 64302 | EV31: ='Investment Analysis'!ML31 | EW31: ='Investment Analysis'!MJ31 | EX31: 39308.5 | EY31: =IF(EX31>0,(EX31-EY$5)/EY$5,0) | EZ31: ='Investment Analysis'!MQ31 | FB31: =IF(FA31>0,(FA31-FB$5)/FB$5,0) | FC31: ='Investment Analysis'!MX31 | FD31: 5102.75 | FE31: =IF(FD31>0,(FD31-FE$5)/FE$5,0) | FF31: ='Investment Analysis'!NE31 | FH31: =IF(FG31>0,(FG31-FH$5)/FH$5,0) | FI31: ='Investment Analysis'!NL31 | FJ31: 9042.75 | FK31: =IF(FJ31>0,(FJ31-FK$5)/FK$5,0) | FL31: ='Investment Analysis'!NS31 | FM31: 32196.8 | FN31: =IF(FM31>0,(FM31-FN$5)/FN$5,0) | FO31: ='Investment Analysis'!NZ31 | FQ31: =IF(FP31>0,(FP31-FQ$5)/FQ$5,0) | FR31: ='Investment Analysis'!OG31 | FS31: 38888.25 | FT31: =IF(FS31>0,(FS31-FT$5)/FT$5,0) | FU31: ='Investment Analysis'!ON31 | FW31: =IF(FV31>0,(FV31-FW$5)/FW$5,0) | FX31: ='Investment Analysis'!OU31 | FZ31: =IF(FY31>0,(FY31-FZ$5)/FZ$5,0) | GA31: ='Investment Analysis'!PB31 | GC31: ='Investment Analysis'!PK31 | GD31: ='Investment Analysis'!PI31 | GE31: 7044 | GF31: ='Investment Analysis'!PY31 | GG31: ='Investment Analysis'!PW31 | GH31: 36898.75 | GI31: ='Investment Analysis'!QF31 | GJ31: ='Investment Analysis'!QD31 | GL31: ='Investment Analysis'!QM31 | GM31: ='Investment Analysis'!QK31 | GN31: 30654.4 | GO31: ='Investment Analysis'!QT31 | GP31: ='Investment Analysis'!QR31 | GQ31: 18750.2 | GR31: ='Investment Analysis'!RA31 | GS31: ='Investment Analysis'!QY31 | GT31: 16853 | GU31: ='Investment Analysis'!RH31 | GV31: ='Investment Analysis'!RF31 | GX31: ='Investment Analysis'!RO31 | GY31: ='Investment Analysis'!RM31 | HA31: ='Investment Analysis'!RV31 | HB31: ='Investment Analysis'!RT31 | HD31: ='Investment Analysis'!SC31 | HE31: ='Investment Analysis'!SA31 | HG31: ='Investment Analysis'!SJ31 | HH31: ='Investment Analysis'!SH31 | HJ31: ='Investment Analysis'!SM31 | HK31: ='Investment Analysis'!SK31 | HM31: ='Investment Analysis'!SP31 | HN31: ='Investment Analysis'!SN31 | HP31: ='Investment Analysis'!TE31 | HQ31: ='Investment Analysis'!TC31 | HS31: ='Investment Analysis'!TL31 | HT31: ='Investment Analysis'!TJ31 | HV31: ='Investment Analysis'!TS31 | HW31: ='Investment Analysis'!TQ31 | HY31: ='Investment Analysis'!TZ31 | HZ31: ='Investment Analysis'!TX31 | IB31: ='Investment Analysis'!UG31 | IC31: ='Investment Analysis'!UE31 | IE31: ='Investment Analysis'!UN31 | IF31: ='Investment Analysis'!UL31 | IH31: ='Investment Analysis'!UU31 | II31: ='Investment Analysis'!US31 | IK31: ='Investment Analysis'!VB31 | IL31: ='Investment Analysis'!UZ31 | IN31: ='Investment Analysis'!VI31 | IO31: ='Investment Analysis'!VG31 | IS31: =IF(IT31>0,IT31-IT30,0) | IT31: =FY31+FV31+FS31+FP31+FM31+FJ31+FG31+FD31+FA31+EX31+EU31+ER31+EO31+EL31+EI31+EF31+EC31+DZ31+DW31+DT31+DQ31+DN31+DK31+DH31+DE31+DB31+CY31+CV31+CS31+CP31+CJ31+CG31+CD31+CA31+BX31+P31+CM31+GT31+GQ31+GN31+GK31+GH31+GE31+GB31+BU31+BR31+BO31+BL31+BI31+BF31+BC31+AZ31+AW31+AT31+AQ31+AN31+AK31+AH31+AE31+AB31+Y31+V31+S31+GW31+GZ31+HC31+HF31+HI31+HL31+HO31+HR31+HU31 | IU31: =IF(IT31>0,IV31,0) | IV31: 3600 | IW31: =IF(IT31>0,(IT31+IV$11-I$2)/I$2,0) | IX31: =IF(IT31>0,IT31+IV$11-I$2,0) | IY31: =IF(IT31>0,(IT31+IV$11-IT$8)/IT$8,0) | IZ31: =IF(IT31>0,IT31+IV$11-IT$8,0)
A32: ='Investment Analysis'!A32 | B32: ='Investment Analysis'!B32 | C32: ='Investment Analysis'!C32 | D32: ='Investment Analysis'!D32 | E32: ='Investment Analysis'!E32 | F32: ='Investment Analysis'!G32 | G32: ='Investment Analysis'!H32 | H32: ='Investment Analysis'!I32 | I32: ='Investment Analysis'!K32 | J32: ='Investment Analysis'!L32 | K32: ='Investment Analysis'!M32 | L32: ='Investment Analysis'!T32 | M32: ='Investment Analysis'!V32 | N32: ='Investment Analysis'!W32 | P32: ='Investment Analysis'!Y32 | S32: 22619.73 | T32: =IF(S32>0,(S32+10000-T$5)/T$5,0) | U32: ='Investment Analysis'!AF32 | V32: 18482.04 | W32: =IF(V32>0,(V32+5000-W$5)/W$5,0) | X32: ='Investment Analysis'!AT32 | Y32: 10179.98 | Z32: =IF(Y32>0,(Y32-Z$5)/Z$5,0) | AA32: ='Investment Analysis'!GK32 | AB32: 2679.54 | AC32: =IF(AB32>0,(AB32+8000-AC$5)/AC$5,0) | AD32: ='Investment Analysis'!AT32 | AE32: 22683.75 | AF32: =IF(AE32>0,(AE32+30000-AF$5)/AF$5,0) | AG32: ='Investment Analysis'!BA32 | AI32: =IF(AH32>0,(AH32-5000-AI$5)/AI$5,0) | AJ32: ='Investment Analysis'!BH32 | AK32: 19892.65 | AL32: =IF(AK32>0,(AK32+7000-AL$5)/AL$5,0) | AM32: ='Investment Analysis'!BO32 | AN32: 14997.7 | AO32: =IF(AN32>0,(AN32-AO$5)/AO$5,0) | AP32: ='Investment Analysis'!BV32 | AR32: =IF(AQ32>0,(AQ32+10000-AR$5)/AR$5,0) | AS32: ='Investment Analysis'!CC32 | AT32: 28405.12 | AU32: =IF(AT32>0,(AT32+10000-AU$5)/AU$5,0) | AV32: ='Investment Analysis'!CJ32 | AW32: 19757.62 | AX32: =IF(AW32>0,(AW32+2000-AX$5)/AX$5,0) | AY32: ='Investment Analysis'!CQ32 | AZ32: 16990.49 | BA32: =IF(AZ32>0,(AZ32+15000-BA$5)/BA$5,0) | BB32: ='Investment Analysis'!CX32 | BC32: 10213.78 | BD32: =IF(BC32>0,(BC32-10000-BD$5)/BD$5,0) | BE32: ='Investment Analysis'!DE32 | BF32: 4331.7 | BG32: =IF(BF32>0,(BF32-BG$5)/BG$5,0) | BH32: ='Investment Analysis'!DL32 | BI32: 2428.92 | BJ32: =IF(BI32>0,(BI32-BJ$5)/BJ$5,0) | BK32: ='Investment Analysis'!DZ32 | BL32: 4204.92 | BM32: =IF(BL32>0,(BL32-BM$5)/BM$5,0) | BN32: ='Investment Analysis'!EG32 | BP32: =IF(BO32>0,(BO32+5000-BP$5)/BP$5,0) | BQ32: ='Investment Analysis'!DS32 | BR32: 6169.53 | BS32: =IF(BR32>0,(BR32-BS$5)/BS$5,0) | BT32: ='Investment Analysis'!EN32 | BU32: 14874.39 | BV32: =IF(BU32>0,(BU32+8000-BV$5)/BV$5,0) | BW32: ='Investment Analysis'!EU32 | BY32: =IF(BX32>0,(BX32-10000-BY$5)/BY$5,0) | BZ32: ='Investment Analysis'!FB32 | CA32: 22577.85 | CB32: =IF(CA32>0,(CA32-CB$5)/CB$5,0) | CC32: ='Investment Analysis'!FI32 | CD32: 19694.92 | CE32: =IF(CD32>0,(CD32+20000-CE$5)/CE$5,0) | CF32: ='Investment Analysis'!FP32 | CG32: 5129.21 | CH32: =IF(CG32>0,(CG32+10000-CH$5)/CH$5,0) | CI32: ='Investment Analysis'!FW32 | CK32: =IF(CJ32>0,(CJ32+5000-CK$5)/CK$5,0) | CL32: ='Investment Analysis'!GD32 | CM32: 24418.38 | CN32: =IF(CM32>0,(CM32-CN$5)/CN$5,0) | CO32: ='Investment Analysis'!GT32 | CP32: 58831.5 | CQ32: =IF(CP32>0,(CP32-CQ$5)/CQ$5,0) | CR32: ='Investment Analysis'!HG32 | CS32: 7290 | CT32: =IF(CS32>0,(CS32-CT$5)/CT$5,0) | CU32: ='Investment Analysis'!HN32 | CV32: 23730 | CW32: =IF(CV32>0,(CV32-CW$5)/CW$5,0) | CX32: ='Investment Analysis'!IB32 | CY32: 22243 | CZ32: =IF(CY32>0,(CY32-CZ$5)/CZ$5,0) | DA32: ='Investment Analysis'!II32 | DC32: =IF(DB32>0,(DB32-DC$5)/DC$5,0) | DD32: ='Investment Analysis'!IP32 | DF32: =IF(DE32>0,(DE32-DF$5)/DF$5,0) | DG32: ='Investment Analysis'!IW32 | DH32: 14083.8 | DI32: =IF(DH32>0,(DH32-DI$5)/DI$5,0) | DJ32: ='Investment Analysis'!JD32 | DK32: 2061.85 | DL32: =IF(DK32>0,(DK32-DL$5)/DL$5,0) | DM32: ='Investment Analysis'!JK32 | DN32: 5498 | DO32: =IF(DN32>0,(DN32-DO$5)/DO$5,0) | DP32: ='Investment Analysis'!HU32 | DQ32: 30834 | DR32: =IF(DQ32>0,(DQ32-DR$5)/DR$5,0) | DS32: ='Investment Analysis'!JR32 | DT32: 4596 | DU32: =IF(DT32>0,(DT32-DU$5)/DU$5,0) | DV32: ='Investment Analysis'!JY32 | DW32: 25546.5 | DX32: =IF(DW32>0,(DW32-DX$5)/DX$5,0) | DY32: ='Investment Analysis'!KF32 | DZ32: 2578.8 | EA32: =IF(DZ32>0,(DZ32-EA$5)/EA$5,0) | EB32: ='Investment Analysis'!KM32 | EC32: 2328 | ED32: =IF(EC32>0,(EC32-ED$5)/ED$5,0) | EE32: ='Investment Analysis'!KT32 | EF32: 39112.5 | EG32: =IF(EF32>0,(EF32-EG$5)/EG$5,0) | EH32: ='Investment Analysis'!LH32 | EI32: 8889.87 | EJ32: =IF(EI32>0,(EI32-EJ$5)/EJ$5,0) | EK32: ='Investment Analysis'!LO32 | EM32: =IF(EL32>0,(EL32-EM$5)/EM$5,0) | EN32: ='Investment Analysis'!LV32 | EP32: =IF(EO32>0,(EO32-500-EP$5)/EP$5,0) | EQ32: ='Investment Analysis'!MC32 | ER32: 23232.99 | ES32: =IF(ER32>0,(ER32-ES$5)/ES$5,0) | ET32: ='Investment Analysis'!LA32 | EU32: 65646 | EV32: ='Investment Analysis'!ML32 | EW32: ='Investment Analysis'!MJ32 | EX32: 38972.5 | EY32: =IF(EX32>0,(EX32-EY$5)/EY$5,0) | EZ32: ='Investment Analysis'!MQ32 | FB32: =IF(FA32>0,(FA32-FB$5)/FB$5,0) | FC32: ='Investment Analysis'!MX32 | FD32: 5054.5 | FE32: =IF(FD32>0,(FD32-FE$5)/FE$5,0) | FF32: ='Investment Analysis'!NE32 | FH32: =IF(FG32>0,(FG32-FH$5)/FH$5,0) | FI32: ='Investment Analysis'!NL32 | FJ32: 8913.25 | FK32: =IF(FJ32>0,(FJ32-FK$5)/FK$5,0) | FL32: ='Investment Analysis'!NS32 | FM32: 33020.8 | FN32: =IF(FM32>0,(FM32-FN$5)/FN$5,0) | FO32: ='Investment Analysis'!NZ32 | FQ32: =IF(FP32>0,(FP32-FQ$5)/FQ$5,0) | FR32: ='Investment Analysis'!OG32 | FS32: 38190 | FT32: =IF(FS32>0,(FS32-FT$5)/FT$5,0) | FU32: ='Investment Analysis'!ON32 | FW32: =IF(FV32>0,(FV32-FW$5)/FW$5,0) | FX32: ='Investment Analysis'!OU32 | FZ32: =IF(FY32>0,(FY32-FZ$5)/FZ$5,0) | GA32: ='Investment Analysis'!PB32 | GC32: ='Investment Analysis'!PK32 | GD32: ='Investment Analysis'!PI32 | GE32: 7100 | GF32: ='Investment Analysis'!PY32 | GG32: ='Investment Analysis'!PW32 | GH32: 37472.5 | GI32: ='Investment Analysis'!QF32 | GJ32: ='Investment Analysis'!QD32 | GL32: ='Investment Analysis'!QM32 | GM32: ='Investment Analysis'!QK32 | GN32: 31216.98 | GO32: ='Investment Analysis'!QT32 | GP32: ='Investment Analysis'!QR32 | GQ32: 18885.9 | GR32: ='Investment Analysis'!RA32 | GS32: ='Investment Analysis'!QY32 | GT32: 16833 | GU32: ='Investment Analysis'!RH32 | GV32: ='Investment Analysis'!RF32 | GX32: ='Investment Analysis'!RO32 | GY32: ='Investment Analysis'!RM32 | HA32: ='Investment Analysis'!RV32 | HB32: ='Investment Analysis'!RT32 | HD32: ='Investment Analysis'!SC32 | HE32: ='Investment Analysis'!SA32 | HG32: ='Investment Analysis'!SJ32 | HH32: ='Investment Analysis'!SH32 | HJ32: ='Investment Analysis'!SM32 | HK32: ='Investment Analysis'!SK32 | HM32: ='Investment Analysis'!SP32 | HN32: ='Investment Analysis'!SN32 | HP32: ='Investment Analysis'!TE32 | HQ32: ='Investment Analysis'!TC32 | HS32: ='Investment Analysis'!TL32 | HT32: ='Investment Analysis'!TJ32 | HV32: ='Investment Analysis'!TS32 | HW32: ='Investment Analysis'!TQ32 | HY32: ='Investment Analysis'!TZ32 | HZ32: ='Investment Analysis'!TX32 | IB32: ='Investment Analysis'!UG32 | IC32: ='Investment Analysis'!UE32 | IE32: ='Investment Analysis'!UN32 | IF32: ='Investment Analysis'!UL32 | IH32: ='Investment Analysis'!UU32 | II32: ='Investment Analysis'!US32 | IK32: ='Investment Analysis'!VB32 | IL32: ='Investment Analysis'!UZ32 | IN32: ='Investment Analysis'!VI32 | IO32: ='Investment Analysis'!VG32 | IS32: =IF(IT32>0,IT32-IT31,0) | IT32: =FY32+FV32+FS32+FP32+FM32+FJ32+FG32+FD32+FA32+EX32+EU32+ER32+EO32+EL32+EI32+EF32+EC32+DZ32+DW32+DT32+DQ32+DN32+DK32+DH32+DE32+DB32+CY32+CV32+CS32+CP32+CJ32+CG32+CD32+CA32+BX32+P32+CM32+GT32+GQ32+GN32+GK32+GH32+GE32+GB32+BU32+BR32+BO32+BL32+BI32+BF32+BC32+AZ32+AW32+AT32+AQ32+AN32+AK32+AH32+AE32+AB32+Y32+V32+S32+GW32+GZ32+HC32+HF32+HI32+HL32+HO32+HR32+HU32 | IU32: =IF(IT32>0,IV32,0) | IW32: =IF(IT32>0,(IT32+IV$11-I$2)/I$2,0) | IX32: =IF(IT32>0,IT32+IV$11-I$2,0) | IY32: =IF(IT32>0,(IT32+IV$11-IT$8)/IT$8,0) | IZ32: =IF(IT32>0,IT32+IV$11-IT$8,0)
A33: ='Investment Analysis'!A33 | B33: ='Investment Analysis'!B33 | C33: ='Investment Analysis'!C33 | D33: ='Investment Analysis'!D33 | E33: ='Investment Analysis'!E33 | F33: ='Investment Analysis'!G33 | G33: ='Investment Analysis'!H33 | H33: ='Investment Analysis'!I33 | I33: ='Investment Analysis'!K33 | J33: ='Investment Analysis'!L33 | K33: ='Investment Analysis'!M33 | L33: ='Investment Analysis'!T33 | M33: ='Investment Analysis'!V33 | N33: ='Investment Analysis'!W33 | P33: ='Investment Analysis'!Y33 | T33: =IF(S33>0,(S33+10000-T$5)/T$5,0) | U33: ='Investment Analysis'!AF33 | W33: =IF(V33>0,(V33+5000-W$5)/W$5,0) | X33: ='Investment Analysis'!AT33 | Z33: =IF(Y33>0,(Y33-Z$5)/Z$5,0) | AA33: ='Investment Analysis'!GK33 | AC33: =IF(AB33>0,(AB33+8000-AC$5)/AC$5,0) | AD33: ='Investment Analysis'!AT33 | AF33: =IF(AE33>0,(AE33+30000-AF$5)/AF$5,0) | AG33: ='Investment Analysis'!BA33 | AI33: =IF(AH33>0,(AH33-5000-AI$5)/AI$5,0) | AJ33: ='Investment Analysis'!BH33 | AL33: =IF(AK33>0,(AK33+7000-AL$5)/AL$5,0) | AM33: ='Investment Analysis'!BO33 | AO33: =IF(AN33>0,(AN33-AO$5)/AO$5,0) | AP33: ='Investment Analysis'!BV33 | AR33: =IF(AQ33>0,(AQ33+10000-AR$5)/AR$5,0) | AS33: ='Investment Analysis'!CC33 | AU33: =IF(AT33>0,(AT33+10000-AU$5)/AU$5,0) | AV33: ='Investment Analysis'!CJ33 | AX33: =IF(AW33>0,(AW33+2000-AX$5)/AX$5,0) | AY33: ='Investment Analysis'!CQ33 | BA33: =IF(AZ33>0,(AZ33+15000-BA$5)/BA$5,0) | BB33: ='Investment Analysis'!CX33 | BD33: =IF(BC33>0,(BC33-10000-BD$5)/BD$5,0) | BE33: ='Investment Analysis'!DE33 | BG33: =IF(BF33>0,(BF33-BG$5)/BG$5,0) | BH33: ='Investment Analysis'!DL33 | BJ33: =IF(BI33>0,(BI33-BJ$5)/BJ$5,0) | BK33: ='Investment Analysis'!DZ33 | BM33: =IF(BL33>0,(BL33-BM$5)/BM$5,0) | BN33: ='Investment Analysis'!EG33 | BP33: =IF(BO33>0,(BO33+5000-BP$5)/BP$5,0) | BQ33: ='Investment Analysis'!DS33 | BS33: =IF(BR33>0,(BR33-BS$5)/BS$5,0) | BT33: ='Investment Analysis'!EN33 | BV33: =IF(BU33>0,(BU33+8000-BV$5)/BV$5,0) | BW33: ='Investment Analysis'!EU33 | BY33: =IF(BX33>0,(BX33-10000-BY$5)/BY$5,0) | BZ33: ='Investment Analysis'!FB33 | CB33: =IF(CA33>0,(CA33-CB$5)/CB$5,0) | CC33: ='Investment Analysis'!FI33 | CE33: =IF(CD33>0,(CD33+20000-CE$5)/CE$5,0) | CF33: ='Investment Analysis'!FP33 | CH33: =IF(CG33>0,(CG33+10000-CH$5)/CH$5,0) | CI33: ='Investment Analysis'!FW33 | CK33: =IF(CJ33>0,(CJ33+5000-CK$5)/CK$5,0) | CL33: ='Investment Analysis'!GD33 | CN33: =IF(CM33>0,(CM33-CN$5)/CN$5,0) | CO33: ='Investment Analysis'!GT33 | CQ33: =IF(CP33>0,(CP33-CQ$5)/CQ$5,0) | CR33: ='Investment Analysis'!HG33 | CT33: =IF(CS33>0,(CS33-CT$5)/CT$5,0) | CU33: ='Investment Analysis'!HN33 | CW33: =IF(CV33>0,(CV33-CW$5)/CW$5,0) | CX33: ='Investment Analysis'!IB33 | CZ33: =IF(CY33>0,(CY33-CZ$5)/CZ$5,0) | DA33: ='Investment Analysis'!II33 | DC33: =IF(DB33>0,(DB33-DC$5)/DC$5,0) | DD33: ='Investment Analysis'!IP33 | DF33: =IF(DE33>0,(DE33-DF$5)/DF$5,0) | DG33: ='Investment Analysis'!IW33 | DI33: =IF(DH33>0,(DH33-DI$5)/DI$5,0) | DJ33: ='Investment Analysis'!JD33 | DL33: =IF(DK33>0,(DK33-DL$5)/DL$5,0) | DM33: ='Investment Analysis'!JK33 | DO33: =IF(DN33>0,(DN33-DO$5)/DO$5,0) | DP33: ='Investment Analysis'!HU33 | DR33: =IF(DQ33>0,(DQ33-DR$5)/DR$5,0) | DS33: ='Investment Analysis'!JR33 | DU33: =IF(DT33>0,(DT33-DU$5)/DU$5,0) | DV33: ='Investment Analysis'!JY33 | DX33: =IF(DW33>0,(DW33-DX$5)/DX$5,0) | DY33: ='Investment Analysis'!KF33 | EA33: =IF(DZ33>0,(DZ33-EA$5)/EA$5,0) | EB33: ='Investment Analysis'!KM33 | ED33: =IF(EC33>0,(EC33-ED$5)/ED$5,0) | EE33: ='Investment Analysis'!KT33 | EG33: =IF(EF33>0,(EF33-EG$5)/EG$5,0) | EH33: ='Investment Analysis'!LH33 | EJ33: =IF(EI33>0,(EI33-EJ$5)/EJ$5,0) | EK33: ='Investment Analysis'!LO33 | EM33: =IF(EL33>0,(EL33-EM$5)/EM$5,0) | EN33: ='Investment Analysis'!LV33 | EP33: =IF(EO33>0,(EO33-500-EP$5)/EP$5,0) | EQ33: ='Investment Analysis'!MC33 | ES33: =IF(ER33>0,(ER33-ES$5)/ES$5,0) | ET33: ='Investment Analysis'!LA33 | EV33: ='Investment Analysis'!ML33 | EW33: ='Investment Analysis'!MJ33 | EY33: =IF(EX33>0,(EX33-EY$5)/EY$5,0) | EZ33: ='Investment Analysis'!MQ33 | FB33: =IF(FA33>0,(FA33-FB$5)/FB$5,0) | FC33: ='Investment Analysis'!MX33 | FE33: =IF(FD33>0,(FD33-FE$5)/FE$5,0) | FF33: ='Investment Analysis'!NE33 | FH33: =IF(FG33>0,(FG33-FH$5)/FH$5,0) | FI33: ='Investment Analysis'!NL33 | FK33: =IF(FJ33>0,(FJ33-FK$5)/FK$5,0) | FL33: ='Investment Analysis'!NS33 | FN33: =IF(FM33>0,(FM33-FN$5)/FN$5,0) | FO33: ='Investment Analysis'!NZ33 | FQ33: =IF(FP33>0,(FP33-FQ$5)/FQ$5,0) | FR33: ='Investment Analysis'!OG33 | FT33: =IF(FS33>0,(FS33-FT$5)/FT$5,0) | FU33: ='Investment Analysis'!ON33 | FW33: =IF(FV33>0,(FV33-FW$5)/FW$5,0) | FX33: ='Investment Analysis'!OU33 | FZ33: =IF(FY33>0,(FY33-FZ$5)/FZ$5,0) | GA33: ='Investment Analysis'!PB33 | GC33: ='Investment Analysis'!PK33 | GD33: ='Investment Analysis'!PI33 | GF33: ='Investment Analysis'!PY33 | GG33: ='Investment Analysis'!PW33 | GI33: ='Investment Analysis'!QF33 | GJ33: ='Investment Analysis'!QD33 | GL33: ='Investment Analysis'!QM33 | GM33: ='Investment Analysis'!QK33 | GO33: ='Investment Analysis'!QT33 | GP33: ='Investment Analysis'!QR33 | GR33: ='Investment Analysis'!RA33 | GS33: ='Investment Analysis'!QY33 | GU33: ='Investment Analysis'!RH33 | GV33: ='Investment Analysis'!RF33 | GX33: ='Investment Analysis'!RO33 | GY33: ='Investment Analysis'!RM33 | HA33: ='Investment Analysis'!RV33 | HB33: ='Investment Analysis'!RT33 | HD33: ='Investment Analysis'!SC33 | HE33: ='Investment Analysis'!SA33 | HG33: ='Investment Analysis'!SJ33 | HH33: ='Investment Analysis'!SH33 | HJ33: ='Investment Analysis'!SM33 | HK33: ='Investment Analysis'!SK33 | HM33: ='Investment Analysis'!SP33 | HN33: ='Investment Analysis'!SN33 | HP33: ='Investment Analysis'!TE33 | HQ33: ='Investment Analysis'!TC33 | HS33: ='Investment Analysis'!TL33 | HT33: ='Investment Analysis'!TJ33 | HV33: ='Investment Analysis'!TS33 | HW33: ='Investment Analysis'!TQ33 | HY33: ='Investment Analysis'!TZ33 | HZ33: ='Investment Analysis'!TX33 | IB33: ='Investment Analysis'!UG33 | IC33: ='Investment Analysis'!UE33 | IE33: ='Investment Analysis'!UN33 | IF33: ='Investment Analysis'!UL33 | IH33: ='Investment Analysis'!UU33 | II33: ='Investment Analysis'!US33 | IK33: ='Investment Analysis'!VB33 | IL33: ='Investment Analysis'!UZ33 | IN33: ='Investment Analysis'!VI33 | IO33: ='Investment Analysis'!VG33 | IS33: =IF(IT33>0,IT33-IT32,0) | IT33: =FY33+FV33+FS33+FP33+FM33+FJ33+FG33+FD33+FA33+EX33+EU33+ER33+EO33+EL33+EI33+EF33+EC33+DZ33+DW33+DT33+DQ33+DN33+DK33+DH33+DE33+DB33+CY33+CV33+CS33+CP33+CJ33+CG33+CD33+CA33+BX33+P33+CM33+GT33+GQ33+GN33+GK33+GH33+GE33+GB33+BU33+BR33+BO33+BL33+BI33+BF33+BC33+AZ33+AW33+AT33+AQ33+AN33+AK33+AH33+AE33+AB33+Y33+V33+S33+GW33+GZ33+HC33+HF33+HI33+HL33+HO33+HR33+HU33 | IU33: =IF(IT33>0,IV33,0) | IW33: =IF(IT33>0,(IT33+IV$11-I$2)/I$2,0) | IX33: =IF(IT33>0,IT33+IV$11-I$2,0) | IY33: =IF(IT33>0,(IT33+IV$11+IV$33-IT$8)/IT$8,0) | IZ33: =IF(IT33>0,IT33+IV$11+IV$33-IT$8,0)
